{"PlayerName":"﻿$s$0b0acer $000| $fffracehans.$09fpG$000»$fff","RaceTime":"00:00:15.5000000","MaxSpeed":290.595947,"ControlNames":["_FakeFinishLine","Brake","Steer","Accelerate","_FakeIsRaceRunning"],"ControlEntries":[{"Time":100000,"Index":4,"Enabled":true},{"Time":100010,"Index":2,"Enabled":true},{"Time":100010,"Index":3,"Enabled":true},{"Time":100230,"Index":2,"Enabled":true},{"Time":100240,"Index":2,"Enabled":true},{"Time":100260,"Index":2,"Enabled":true},{"Time":100290,"Index":2,"Enabled":true},{"Time":100310,"Index":2,"Enabled":true},{"Time":100410,"Index":2,"Enabled":true},{"Time":100430,"Index":2,"Enabled":true},{"Time":100510,"Index":2,"Enabled":true},{"Time":100600,"Index":2,"Enabled":true},{"Time":100620,"Index":2,"Enabled":true},{"Time":100630,"Index":2,"Enabled":true},{"Time":100650,"Index":2,"Enabled":true},{"Time":100660,"Index":2,"Enabled":true},{"Time":100670,"Index":2,"Enabled":true},{"Time":100680,"Index":2,"Enabled":true},{"Time":100690,"Index":2,"Enabled":true},{"Time":100710,"Index":2,"Enabled":true},{"Time":100720,"Index":2,"Enabled":true},{"Time":100880,"Index":2,"Enabled":true},{"Time":100900,"Index":2,"Enabled":true},{"Time":100910,"Index":2,"Enabled":true},{"Time":100930,"Index":2,"Enabled":true},{"Time":100990,"Index":2,"Enabled":true},{"Time":101210,"Index":2,"Enabled":true},{"Time":101220,"Index":2,"Enabled":true},{"Time":101240,"Index":2,"Enabled":true},{"Time":101260,"Index":2,"Enabled":true},{"Time":101270,"Index":2,"Enabled":true},{"Time":101290,"Index":2,"Enabled":true},{"Time":101300,"Index":2,"Enabled":false},{"Time":101350,"Index":2,"Enabled":true},{"Time":101360,"Index":2,"Enabled":true},{"Time":101370,"Index":2,"Enabled":true},{"Time":101380,"Index":2,"Enabled":true},{"Time":101400,"Index":2,"Enabled":true},{"Time":101410,"Index":2,"Enabled":true},{"Time":101430,"Index":2,"Enabled":true},{"Time":101470,"Index":2,"Enabled":true},{"Time":101480,"Index":2,"Enabled":true},{"Time":101510,"Index":2,"Enabled":true},{"Time":101520,"Index":2,"Enabled":true},{"Time":101540,"Index":2,"Enabled":false},{"Time":101580,"Index":2,"Enabled":true},{"Time":101600,"Index":2,"Enabled":true},{"Time":101610,"Index":2,"Enabled":true},{"Time":101630,"Index":2,"Enabled":true},{"Time":101650,"Index":2,"Enabled":true},{"Time":101720,"Index":2,"Enabled":true},{"Time":101740,"Index":2,"Enabled":true},{"Time":101750,"Index":2,"Enabled":true},{"Time":101770,"Index":2,"Enabled":true},{"Time":101780,"Index":2,"Enabled":true},{"Time":101790,"Index":2,"Enabled":true},{"Time":101800,"Index":2,"Enabled":true},{"Time":101820,"Index":2,"Enabled":true},{"Time":101830,"Index":2,"Enabled":true},{"Time":101840,"Index":2,"Enabled":true},{"Time":101850,"Index":2,"Enabled":true},{"Time":101860,"Index":2,"Enabled":true},{"Time":101880,"Index":2,"Enabled":true},{"Time":101890,"Index":2,"Enabled":true},{"Time":101910,"Index":2,"Enabled":true},{"Time":101930,"Index":2,"Enabled":true},{"Time":101940,"Index":2,"Enabled":true},{"Time":101960,"Index":2,"Enabled":true},{"Time":101970,"Index":2,"Enabled":true},{"Time":101990,"Index":2,"Enabled":true},{"Time":102080,"Index":2,"Enabled":true},{"Time":102100,"Index":2,"Enabled":true},{"Time":102110,"Index":2,"Enabled":true},{"Time":102130,"Index":2,"Enabled":true},{"Time":102140,"Index":2,"Enabled":true},{"Time":102150,"Index":2,"Enabled":true},{"Time":102160,"Index":2,"Enabled":false},{"Time":102180,"Index":2,"Enabled":true},{"Time":102190,"Index":2,"Enabled":false},{"Time":102230,"Index":2,"Enabled":true},{"Time":102240,"Index":2,"Enabled":true},{"Time":102250,"Index":2,"Enabled":true},{"Time":102270,"Index":2,"Enabled":true},{"Time":102280,"Index":2,"Enabled":true},{"Time":102290,"Index":2,"Enabled":true},{"Time":102300,"Index":2,"Enabled":true},{"Time":102320,"Index":2,"Enabled":true},{"Time":102330,"Index":2,"Enabled":true},{"Time":102350,"Index":2,"Enabled":true},{"Time":102360,"Index":2,"Enabled":true},{"Time":102970,"Index":2,"Enabled":true},{"Time":102990,"Index":2,"Enabled":true},{"Time":103000,"Index":2,"Enabled":true},{"Time":103020,"Index":2,"Enabled":true},{"Time":103030,"Index":2,"Enabled":true},{"Time":103070,"Index":2,"Enabled":true},{"Time":103090,"Index":2,"Enabled":true},{"Time":103100,"Index":2,"Enabled":true},{"Time":103110,"Index":2,"Enabled":true},{"Time":103130,"Index":2,"Enabled":true},{"Time":103140,"Index":2,"Enabled":true},{"Time":103160,"Index":2,"Enabled":true},{"Time":103170,"Index":2,"Enabled":true},{"Time":103190,"Index":2,"Enabled":true},{"Time":103270,"Index":2,"Enabled":true},{"Time":103280,"Index":2,"Enabled":true},{"Time":103300,"Index":2,"Enabled":true},{"Time":103310,"Index":2,"Enabled":true},{"Time":103320,"Index":2,"Enabled":true},{"Time":103350,"Index":2,"Enabled":true},{"Time":103370,"Index":2,"Enabled":true},{"Time":103380,"Index":2,"Enabled":true},{"Time":103390,"Index":2,"Enabled":true},{"Time":103410,"Index":2,"Enabled":true},{"Time":103420,"Index":2,"Enabled":true},{"Time":103440,"Index":2,"Enabled":true},{"Time":103490,"Index":2,"Enabled":true},{"Time":103500,"Index":2,"Enabled":true},{"Time":103520,"Index":2,"Enabled":true},{"Time":103530,"Index":2,"Enabled":false},{"Time":103780,"Index":2,"Enabled":true},{"Time":103800,"Index":2,"Enabled":true},{"Time":103810,"Index":2,"Enabled":true},{"Time":103830,"Index":2,"Enabled":true},{"Time":103840,"Index":2,"Enabled":true},{"Time":103860,"Index":2,"Enabled":true},{"Time":103880,"Index":2,"Enabled":true},{"Time":103890,"Index":2,"Enabled":true},{"Time":103910,"Index":2,"Enabled":true},{"Time":103920,"Index":2,"Enabled":true},{"Time":103940,"Index":2,"Enabled":true},{"Time":103950,"Index":2,"Enabled":true},{"Time":103970,"Index":2,"Enabled":true},{"Time":103990,"Index":2,"Enabled":true},{"Time":104020,"Index":2,"Enabled":true},{"Time":104030,"Index":2,"Enabled":true},{"Time":104050,"Index":2,"Enabled":true},{"Time":104060,"Index":2,"Enabled":true},{"Time":104070,"Index":2,"Enabled":true},{"Time":104130,"Index":2,"Enabled":true},{"Time":104200,"Index":2,"Enabled":true},{"Time":104220,"Index":2,"Enabled":true},{"Time":104230,"Index":2,"Enabled":true},{"Time":104250,"Index":2,"Enabled":false},{"Time":104330,"Index":2,"Enabled":true},{"Time":104390,"Index":2,"Enabled":false},{"Time":104420,"Index":2,"Enabled":true},{"Time":104440,"Index":2,"Enabled":true},{"Time":104450,"Index":2,"Enabled":true},{"Time":104460,"Index":2,"Enabled":true},{"Time":104560,"Index":2,"Enabled":true},{"Time":104610,"Index":2,"Enabled":true},{"Time":104630,"Index":2,"Enabled":true},{"Time":104640,"Index":2,"Enabled":true},{"Time":104650,"Index":2,"Enabled":true},{"Time":104660,"Index":2,"Enabled":true},{"Time":104670,"Index":2,"Enabled":true},{"Time":104690,"Index":2,"Enabled":true},{"Time":104720,"Index":2,"Enabled":true},{"Time":104800,"Index":2,"Enabled":true},{"Time":104810,"Index":2,"Enabled":true},{"Time":104830,"Index":2,"Enabled":true},{"Time":104840,"Index":2,"Enabled":true},{"Time":104860,"Index":2,"Enabled":true},{"Time":104870,"Index":2,"Enabled":true},{"Time":104880,"Index":2,"Enabled":true},{"Time":104890,"Index":2,"Enabled":true},{"Time":104910,"Index":2,"Enabled":true},{"Time":104920,"Index":2,"Enabled":true},{"Time":104930,"Index":2,"Enabled":true},{"Time":104940,"Index":2,"Enabled":true},{"Time":104950,"Index":2,"Enabled":true},{"Time":104970,"Index":2,"Enabled":true},{"Time":105000,"Index":2,"Enabled":true},{"Time":105010,"Index":2,"Enabled":true},{"Time":105060,"Index":2,"Enabled":true},{"Time":105120,"Index":2,"Enabled":true},{"Time":105140,"Index":2,"Enabled":true},{"Time":105160,"Index":2,"Enabled":true},{"Time":105170,"Index":2,"Enabled":true},{"Time":105190,"Index":2,"Enabled":true},{"Time":105200,"Index":2,"Enabled":true},{"Time":105210,"Index":2,"Enabled":true},{"Time":105220,"Index":2,"Enabled":true},{"Time":105230,"Index":2,"Enabled":false},{"Time":105300,"Index":2,"Enabled":true},{"Time":105330,"Index":2,"Enabled":true},{"Time":105340,"Index":2,"Enabled":true},{"Time":105350,"Index":2,"Enabled":true},{"Time":105360,"Index":2,"Enabled":true},{"Time":105370,"Index":2,"Enabled":true},{"Time":105390,"Index":2,"Enabled":true},{"Time":105400,"Index":2,"Enabled":true},{"Time":105440,"Index":2,"Enabled":true},{"Time":105550,"Index":2,"Enabled":true},{"Time":105560,"Index":2,"Enabled":true},{"Time":105580,"Index":2,"Enabled":true},{"Time":105590,"Index":2,"Enabled":true},{"Time":105610,"Index":2,"Enabled":true},{"Time":105620,"Index":2,"Enabled":true},{"Time":105680,"Index":2,"Enabled":true},{"Time":105690,"Index":2,"Enabled":true},{"Time":105700,"Index":2,"Enabled":true},{"Time":105720,"Index":2,"Enabled":true},{"Time":105730,"Index":2,"Enabled":true},{"Time":105750,"Index":2,"Enabled":true},{"Time":105760,"Index":2,"Enabled":true},{"Time":105810,"Index":2,"Enabled":true},{"Time":105840,"Index":2,"Enabled":true},{"Time":105860,"Index":2,"Enabled":true},{"Time":105870,"Index":2,"Enabled":true},{"Time":105890,"Index":2,"Enabled":true},{"Time":105900,"Index":2,"Enabled":true},{"Time":106000,"Index":2,"Enabled":true},{"Time":106010,"Index":2,"Enabled":true},{"Time":106030,"Index":2,"Enabled":true},{"Time":106040,"Index":2,"Enabled":true},{"Time":106060,"Index":2,"Enabled":true},{"Time":106140,"Index":2,"Enabled":true},{"Time":106150,"Index":2,"Enabled":true},{"Time":106170,"Index":2,"Enabled":true},{"Time":106220,"Index":2,"Enabled":true},{"Time":106230,"Index":2,"Enabled":true},{"Time":106250,"Index":2,"Enabled":true},{"Time":106260,"Index":2,"Enabled":true},{"Time":106280,"Index":2,"Enabled":true},{"Time":106420,"Index":2,"Enabled":true},{"Time":106430,"Index":2,"Enabled":true},{"Time":106450,"Index":2,"Enabled":true},{"Time":106470,"Index":2,"Enabled":true},{"Time":106480,"Index":2,"Enabled":true},{"Time":106500,"Index":2,"Enabled":true},{"Time":106510,"Index":2,"Enabled":true},{"Time":106530,"Index":2,"Enabled":true},{"Time":106540,"Index":2,"Enabled":true},{"Time":106550,"Index":2,"Enabled":true},{"Time":106560,"Index":2,"Enabled":true},{"Time":106570,"Index":2,"Enabled":true},{"Time":106590,"Index":2,"Enabled":true},{"Time":106610,"Index":2,"Enabled":true},{"Time":106640,"Index":2,"Enabled":true},{"Time":106650,"Index":2,"Enabled":true},{"Time":106670,"Index":2,"Enabled":true},{"Time":106680,"Index":2,"Enabled":true},{"Time":106700,"Index":2,"Enabled":true},{"Time":106720,"Index":2,"Enabled":true},{"Time":106730,"Index":2,"Enabled":true},{"Time":106750,"Index":2,"Enabled":true},{"Time":106760,"Index":2,"Enabled":true},{"Time":106780,"Index":2,"Enabled":true},{"Time":106790,"Index":2,"Enabled":true},{"Time":106800,"Index":2,"Enabled":true},{"Time":106810,"Index":2,"Enabled":true},{"Time":106890,"Index":2,"Enabled":true},{"Time":106900,"Index":2,"Enabled":true},{"Time":106910,"Index":2,"Enabled":true},{"Time":106920,"Index":2,"Enabled":true},{"Time":106930,"Index":2,"Enabled":true},{"Time":107000,"Index":2,"Enabled":true},{"Time":107010,"Index":2,"Enabled":true},{"Time":107030,"Index":2,"Enabled":true},{"Time":107040,"Index":2,"Enabled":true},{"Time":107060,"Index":2,"Enabled":true},{"Time":107140,"Index":2,"Enabled":true},{"Time":107150,"Index":2,"Enabled":true},{"Time":107170,"Index":2,"Enabled":true},{"Time":107180,"Index":2,"Enabled":true},{"Time":107190,"Index":2,"Enabled":true},{"Time":107200,"Index":2,"Enabled":true},{"Time":107210,"Index":2,"Enabled":true},{"Time":107230,"Index":2,"Enabled":true},{"Time":107320,"Index":2,"Enabled":true},{"Time":107340,"Index":2,"Enabled":true},{"Time":107350,"Index":2,"Enabled":true},{"Time":107370,"Index":2,"Enabled":true},{"Time":107390,"Index":2,"Enabled":true},{"Time":107450,"Index":2,"Enabled":true},{"Time":107460,"Index":2,"Enabled":true},{"Time":107470,"Index":2,"Enabled":true},{"Time":107480,"Index":2,"Enabled":false},{"Time":107780,"Index":2,"Enabled":true},{"Time":107790,"Index":2,"Enabled":true},{"Time":107810,"Index":2,"Enabled":true},{"Time":107820,"Index":2,"Enabled":true},{"Time":107840,"Index":2,"Enabled":true},{"Time":107850,"Index":2,"Enabled":true},{"Time":107870,"Index":2,"Enabled":true},{"Time":107880,"Index":2,"Enabled":true},{"Time":107890,"Index":2,"Enabled":true},{"Time":107900,"Index":2,"Enabled":true},{"Time":107920,"Index":2,"Enabled":true},{"Time":107930,"Index":2,"Enabled":true},{"Time":108100,"Index":2,"Enabled":true},{"Time":108120,"Index":2,"Enabled":true},{"Time":108130,"Index":2,"Enabled":false},{"Time":108150,"Index":2,"Enabled":true},{"Time":108170,"Index":2,"Enabled":true},{"Time":108180,"Index":2,"Enabled":true},{"Time":108200,"Index":2,"Enabled":true},{"Time":108210,"Index":2,"Enabled":true},{"Time":108230,"Index":2,"Enabled":true},{"Time":108240,"Index":2,"Enabled":true},{"Time":108400,"Index":2,"Enabled":true},{"Time":108410,"Index":2,"Enabled":true},{"Time":108420,"Index":2,"Enabled":true},{"Time":108430,"Index":2,"Enabled":true},{"Time":108450,"Index":2,"Enabled":false},{"Time":108460,"Index":2,"Enabled":true},{"Time":108480,"Index":2,"Enabled":true},{"Time":108490,"Index":2,"Enabled":true},{"Time":108510,"Index":2,"Enabled":true},{"Time":108520,"Index":2,"Enabled":true},{"Time":108530,"Index":2,"Enabled":true},{"Time":108540,"Index":2,"Enabled":true},{"Time":108560,"Index":2,"Enabled":true},{"Time":108770,"Index":2,"Enabled":true},{"Time":108790,"Index":2,"Enabled":true},{"Time":108810,"Index":2,"Enabled":true},{"Time":108820,"Index":2,"Enabled":true},{"Time":108840,"Index":2,"Enabled":false},{"Time":108870,"Index":2,"Enabled":true},{"Time":108880,"Index":2,"Enabled":true},{"Time":108900,"Index":2,"Enabled":true},{"Time":108910,"Index":2,"Enabled":true},{"Time":108920,"Index":2,"Enabled":true},{"Time":108930,"Index":2,"Enabled":true},{"Time":108950,"Index":2,"Enabled":true},{"Time":109120,"Index":2,"Enabled":true},{"Time":109130,"Index":2,"Enabled":true},{"Time":109150,"Index":2,"Enabled":true},{"Time":109160,"Index":2,"Enabled":true},{"Time":109170,"Index":2,"Enabled":false},{"Time":109200,"Index":2,"Enabled":true},{"Time":109210,"Index":2,"Enabled":true},{"Time":109220,"Index":2,"Enabled":true},{"Time":109230,"Index":2,"Enabled":true},{"Time":109240,"Index":2,"Enabled":true},{"Time":109260,"Index":2,"Enabled":true},{"Time":109270,"Index":2,"Enabled":true},{"Time":109290,"Index":2,"Enabled":true},{"Time":109300,"Index":2,"Enabled":true},{"Time":109320,"Index":2,"Enabled":true},{"Time":109340,"Index":2,"Enabled":true},{"Time":109350,"Index":2,"Enabled":true},{"Time":109540,"Index":2,"Enabled":true},{"Time":109550,"Index":2,"Enabled":true},{"Time":109570,"Index":2,"Enabled":true},{"Time":109590,"Index":2,"Enabled":false},{"Time":109600,"Index":2,"Enabled":true},{"Time":109610,"Index":2,"Enabled":true},{"Time":109620,"Index":2,"Enabled":true},{"Time":109630,"Index":2,"Enabled":true},{"Time":109650,"Index":2,"Enabled":true},{"Time":109660,"Index":2,"Enabled":true},{"Time":109680,"Index":2,"Enabled":true},{"Time":109690,"Index":2,"Enabled":true},{"Time":109710,"Index":2,"Enabled":true},{"Time":109790,"Index":2,"Enabled":true},{"Time":109800,"Index":2,"Enabled":true},{"Time":109820,"Index":2,"Enabled":true},{"Time":109840,"Index":2,"Enabled":false},{"Time":109870,"Index":2,"Enabled":true},{"Time":109880,"Index":2,"Enabled":true},{"Time":109900,"Index":2,"Enabled":true},{"Time":109910,"Index":2,"Enabled":true},{"Time":109920,"Index":2,"Enabled":true},{"Time":109930,"Index":2,"Enabled":true},{"Time":109940,"Index":2,"Enabled":true},{"Time":110040,"Index":2,"Enabled":true},{"Time":110050,"Index":2,"Enabled":true},{"Time":110070,"Index":2,"Enabled":false},{"Time":110240,"Index":2,"Enabled":true},{"Time":110260,"Index":2,"Enabled":true},{"Time":110270,"Index":2,"Enabled":true},{"Time":110280,"Index":2,"Enabled":true},{"Time":110290,"Index":2,"Enabled":true},{"Time":110300,"Index":2,"Enabled":true},{"Time":110320,"Index":2,"Enabled":true},{"Time":110350,"Index":2,"Enabled":true},{"Time":110380,"Index":2,"Enabled":true},{"Time":110400,"Index":2,"Enabled":true},{"Time":110410,"Index":2,"Enabled":true},{"Time":110420,"Index":2,"Enabled":true},{"Time":110430,"Index":2,"Enabled":false},{"Time":110550,"Index":2,"Enabled":true},{"Time":110570,"Index":2,"Enabled":true},{"Time":110580,"Index":2,"Enabled":true},{"Time":110590,"Index":2,"Enabled":true},{"Time":110600,"Index":2,"Enabled":true},{"Time":110610,"Index":2,"Enabled":true},{"Time":110620,"Index":2,"Enabled":true},{"Time":110630,"Index":2,"Enabled":true},{"Time":110650,"Index":2,"Enabled":true},{"Time":110660,"Index":2,"Enabled":true},{"Time":110680,"Index":2,"Enabled":true},{"Time":110690,"Index":2,"Enabled":true},{"Time":110710,"Index":2,"Enabled":true},{"Time":111380,"Index":2,"Enabled":true},{"Time":111400,"Index":2,"Enabled":true},{"Time":111410,"Index":2,"Enabled":true},{"Time":111420,"Index":2,"Enabled":true},{"Time":111430,"Index":2,"Enabled":true},{"Time":111440,"Index":2,"Enabled":true},{"Time":111460,"Index":2,"Enabled":true},{"Time":111470,"Index":2,"Enabled":false},{"Time":111970,"Index":1,"Enabled":true},{"Time":112100,"Index":1,"Enabled":false},{"Time":112600,"Index":2,"Enabled":true},{"Time":112610,"Index":2,"Enabled":true},{"Time":112630,"Index":2,"Enabled":true},{"Time":112640,"Index":2,"Enabled":true},{"Time":112660,"Index":2,"Enabled":true},{"Time":112670,"Index":2,"Enabled":true},{"Time":112680,"Index":2,"Enabled":true},{"Time":112690,"Index":2,"Enabled":true},{"Time":112710,"Index":2,"Enabled":true},{"Time":112720,"Index":2,"Enabled":true},{"Time":112740,"Index":2,"Enabled":true},{"Time":112750,"Index":2,"Enabled":true},{"Time":113050,"Index":2,"Enabled":true},{"Time":113070,"Index":2,"Enabled":true},{"Time":113080,"Index":2,"Enabled":true},{"Time":113100,"Index":2,"Enabled":false},{"Time":113170,"Index":2,"Enabled":true},{"Time":113190,"Index":2,"Enabled":true},{"Time":113200,"Index":2,"Enabled":true},{"Time":113220,"Index":2,"Enabled":true},{"Time":113230,"Index":2,"Enabled":true},{"Time":113240,"Index":2,"Enabled":true},{"Time":113250,"Index":2,"Enabled":true},{"Time":113270,"Index":2,"Enabled":true},{"Time":113470,"Index":2,"Enabled":true},{"Time":113490,"Index":2,"Enabled":true},{"Time":113500,"Index":2,"Enabled":true},{"Time":113520,"Index":2,"Enabled":true},{"Time":113530,"Index":2,"Enabled":true},{"Time":113550,"Index":2,"Enabled":true},{"Time":113560,"Index":2,"Enabled":true},{"Time":113580,"Index":2,"Enabled":true},{"Time":113590,"Index":2,"Enabled":true},{"Time":113600,"Index":2,"Enabled":true},{"Time":113610,"Index":2,"Enabled":true},{"Time":113630,"Index":2,"Enabled":true},{"Time":113670,"Index":2,"Enabled":true},{"Time":113690,"Index":2,"Enabled":true},{"Time":113700,"Index":2,"Enabled":true},{"Time":113710,"Index":2,"Enabled":true},{"Time":113720,"Index":2,"Enabled":true},{"Time":113740,"Index":2,"Enabled":false},{"Time":113810,"Index":2,"Enabled":true},{"Time":113830,"Index":2,"Enabled":true},{"Time":113840,"Index":2,"Enabled":true},{"Time":113860,"Index":2,"Enabled":true},{"Time":113880,"Index":2,"Enabled":true},{"Time":113920,"Index":2,"Enabled":true},{"Time":113940,"Index":2,"Enabled":true},{"Time":113950,"Index":2,"Enabled":true},{"Time":113960,"Index":2,"Enabled":true},{"Time":113970,"Index":2,"Enabled":true},{"Time":113980,"Index":2,"Enabled":false},{"Time":114020,"Index":2,"Enabled":true},{"Time":114030,"Index":2,"Enabled":true},{"Time":114040,"Index":2,"Enabled":true},{"Time":114060,"Index":2,"Enabled":false},{"Time":114080,"Index":2,"Enabled":true},{"Time":114090,"Index":2,"Enabled":true},{"Time":114110,"Index":2,"Enabled":true},{"Time":114130,"Index":2,"Enabled":true},{"Time":114140,"Index":2,"Enabled":true},{"Time":114310,"Index":2,"Enabled":true},{"Time":114330,"Index":2,"Enabled":true},{"Time":114340,"Index":2,"Enabled":true},{"Time":114350,"Index":2,"Enabled":true},{"Time":114360,"Index":2,"Enabled":true},{"Time":114370,"Index":2,"Enabled":false},{"Time":114440,"Index":2,"Enabled":true},{"Time":114450,"Index":2,"Enabled":true},{"Time":114470,"Index":2,"Enabled":false},{"Time":114540,"Index":2,"Enabled":true},{"Time":114550,"Index":2,"Enabled":true},{"Time":114560,"Index":2,"Enabled":true},{"Time":114570,"Index":2,"Enabled":true},{"Time":114580,"Index":2,"Enabled":true},{"Time":114590,"Index":2,"Enabled":true},{"Time":114610,"Index":2,"Enabled":true},{"Time":114620,"Index":2,"Enabled":true},{"Time":114640,"Index":2,"Enabled":true},{"Time":114660,"Index":2,"Enabled":true},{"Time":114670,"Index":2,"Enabled":true},{"Time":114690,"Index":2,"Enabled":true},{"Time":114700,"Index":2,"Enabled":true},{"Time":114720,"Index":2,"Enabled":true},{"Time":114730,"Index":2,"Enabled":true},{"Time":114740,"Index":2,"Enabled":true},{"Time":114750,"Index":2,"Enabled":false},{"Time":114760,"Index":2,"Enabled":true},{"Time":114780,"Index":2,"Enabled":false},{"Time":114800,"Index":2,"Enabled":true},{"Time":114810,"Index":2,"Enabled":false},{"Time":114860,"Index":2,"Enabled":true},{"Time":114870,"Index":2,"Enabled":true},{"Time":114890,"Index":2,"Enabled":true},{"Time":114900,"Index":2,"Enabled":true},{"Time":114910,"Index":2,"Enabled":true},{"Time":114920,"Index":2,"Enabled":true},{"Time":114950,"Index":2,"Enabled":true},{"Time":114970,"Index":2,"Enabled":true},{"Time":114980,"Index":2,"Enabled":true},{"Time":115000,"Index":2,"Enabled":true},{"Time":115010,"Index":2,"Enabled":true},{"Time":115030,"Index":2,"Enabled":false},{"Time":115050,"Index":2,"Enabled":true},{"Time":115060,"Index":2,"Enabled":true},{"Time":115080,"Index":2,"Enabled":true},{"Time":115090,"Index":2,"Enabled":true},{"Time":115110,"Index":2,"Enabled":true},{"Time":115120,"Index":2,"Enabled":true},{"Time":115140,"Index":2,"Enabled":true},{"Time":115150,"Index":2,"Enabled":true},{"Time":115170,"Index":2,"Enabled":true},{"Time":115190,"Index":2,"Enabled":false},{"Time":115370,"Index":1,"Enabled":true},{"Time":115470,"Index":1,"Enabled":false},{"Time":115500,"Index":0,"Enabled":true}],"Samples":[{"Timestamp":"00:00:00","Position":{"x":244.8,"y":10.21,"z":368.0},"Rotation":{"x":3.38963218E-05,"y":-0.7070814,"z":0.0,"w":0.7071322},"PitchYawRoll":{"x":4.79383634E-05,"y":-1.57072449,"z":-4.79349146E-05},"Speed":2.11514867E-14,"Velocity":{"x":5.875413E-15,"y":0.0,"z":0.0}},{"Timestamp":"00:00:00.1000000","Position":{"x":244.744614,"y":10.09694,"z":367.9999},"Rotation":{"x":-0.0007796521,"y":-0.707114339,"z":-0.000813550549,"w":0.7070983},"PitchYawRoll":{"x":-0.00225312985,"y":-1.570819,"z":-4.79140763E-05},"Speed":9.042483,"Velocity":{"x":-1.37929571,"y":-2.09921122,"z":0.0}},{"Timestamp":"00:00:00.2000000","Position":{"x":244.532547,"y":10.0064535,"z":367.999146},"Rotation":{"x":-0.000779725553,"y":-0.707181,"z":-0.00152555271,"w":0.707030535},"PitchYawRoll":{"x":-0.003260271,"y":-1.57101083,"z":-0.00105441071},"Speed":10.8041878,"Velocity":{"x":-2.98648357,"y":-0.296474159,"z":0.0}},{"Timestamp":"00:00:00.3000000","Position":{"x":244.161758,"y":10.0080757,"z":367.99704},"Rotation":{"x":-0.000915766752,"y":-0.7075183,"z":-0.002068961,"w":0.706691444},"PitchYawRoll":{"x":-0.004222003,"y":-1.57196915,"z":-0.00162839144},"Speed":16.46001,"Velocity":{"x":-4.57047653,"y":-0.113082722,"z":-0.05655001}},{"Timestamp":"00:00:00.4000000","Position":{"x":243.632523,"y":10.0104275,"z":367.989929},"Rotation":{"x":-0.00180276611,"y":-0.709544063,"z":-0.00272117276,"w":0.7046535},"PitchYawRoll":{"x":-0.006402284,"y":-1.57771671,"z":-0.00127668423},"Speed":22.1299915,"Velocity":{"x":-6.14486933,"y":0.152036339,"z":-0.0760298}},{"Timestamp":"00:00:00.5000000","Position":{"x":242.9465,"y":10.0120659,"z":367.976929},"Rotation":{"x":-0.0023610245,"y":-0.7137837,"z":-0.00321649574,"w":0.7003549},"PitchYawRoll":{"x":-0.007898961,"y":-1.58979249,"z":-0.00113485567},"Speed":27.7693748,"Velocity":{"x":-7.7089963,"y":-0.190735966,"z":-0.190794334}},{"Timestamp":"00:00:00.6000000","Position":{"x":242.1051,"y":10.0115013,"z":367.950623},"Rotation":{"x":-0.00203652564,"y":-0.720034838,"z":-0.00307207,"w":0.6939281},"PitchYawRoll":{"x":-0.00725046964,"y":-1.607724,"z":-0.00133085309},"Speed":33.4126244,"Velocity":{"x":-9.272059,"y":-0.229409263,"z":-0.344307}},{"Timestamp":"00:00:00.7000000","Position":{"x":241.108978,"y":10.0088091,"z":367.899963},"Rotation":{"x":-0.000383981824,"y":-0.7281733,"z":-0.00237371447,"w":0.6853888},"PitchYawRoll":{"x":-0.00398332952,"y":-1.6313175,"z":-0.00269462727},"Speed":39.0535545,"Velocity":{"x":-10.8241587,"y":-0.2678113,"z":-0.670451462}},{"Timestamp":"00:00:00.8000000","Position":{"x":239.965,"y":9.987994,"z":367.810974},"Rotation":{"x":0.007829949,"y":-0.7390388,"z":0.00372021273,"w":0.673607051},"PitchYawRoll":{"x":0.0160484165,"y":-1.6633147,"z":-0.006561397},"Speed":44.7877121,"Velocity":{"x":-12.36503,"y":-0.612245858,"z":-1.229005}},{"Timestamp":"00:00:00.9000000","Position":{"x":238.670441,"y":9.946486,"z":367.668},"Rotation":{"x":0.0217307582,"y":-0.7515422,"z":0.0160414632,"w":0.659131765},"PitchYawRoll":{"x":0.0527865477,"y":-1.70132136,"z":-0.0115165431},"Speed":50.85273,"Velocity":{"x":-13.9780989,"y":-0.692115843,"z":-1.91593146}},{"Timestamp":"00:00:01","Position":{"x":237.20636,"y":9.887147,"z":367.446625},"Rotation":{"x":0.0297335163,"y":-0.7662963,"z":0.02371946,"w":0.641360462},"PitchYawRoll":{"x":0.07456971,"y":-1.74727643,"z":-0.0151445},"Speed":57.2217369,"Velocity":{"x":-15.614131,"y":-1.16086984,"z":-2.73861027}},{"Timestamp":"00:00:01.1000000","Position":{"x":235.566513,"y":9.773142,"z":367.117035},"Rotation":{"x":0.0265588872,"y":-0.7833231,"z":0.0161961839,"w":0.6208359},"PitchYawRoll":{"x":0.05839779,"y":-1.80058062,"z":-0.0214996915},"Speed":63.6203766,"Velocity":{"x":-17.15186,"y":-1.70269918,"z":-3.90201378}},{"Timestamp":"00:00:01.2000000","Position":{"x":233.7781,"y":9.666203,"z":366.683777},"Rotation":{"x":0.0150279049,"y":-0.801655233,"z":0.02926338,"w":0.596880853},"PitchYawRoll":{"x":0.0649074,"y":-1.8619231,"z":0.0108393189},"Speed":69.8907852,"Velocity":{"x":-18.5426941,"y":-1.84077024,"z":-5.448638}},{"Timestamp":"00:00:01.3000000","Position":{"x":231.855453,"y":9.546573,"z":366.101685},"Rotation":{"x":-0.00090256246,"y":-0.8185893,"z":0.0510411635,"w":0.572106242},"PitchYawRoll":{"x":0.0827736259,"y":-1.92410946,"z":0.0599154346},"Speed":76.31991,"Velocity":{"x":-19.8757858,"y":-2.4709444,"z":-6.948848}},{"Timestamp":"00:00:01.4000000","Position":{"x":229.776428,"y":9.421552,"z":365.328735},"Rotation":{"x":-0.0258168522,"y":-0.829536,"z":0.022803029,"w":0.5573899},"PitchYawRoll":{"x":0.009073043,"y":-1.95862782,"z":0.06830548},"Speed":82.5111847,"Velocity":{"x":-21.1968079,"y":-2.635173,"z":-8.310667}},{"Timestamp":"00:00:01.5000000","Position":{"x":227.5939,"y":9.364366,"z":364.400543},"Rotation":{"x":-0.00499018375,"y":-0.832756639,"z":-0.00387243344,"w":0.5536032},"PitchYawRoll":{"x":-0.0119751357,"y":-1.96817255,"z":0.004023645},"Speed":87.96455,"Velocity":{"x":-22.5980225,"y":-1.6801039,"z":-9.140906}},{"Timestamp":"00:00:01.6000000","Position":{"x":225.284592,"y":9.37166,"z":363.423035},"Rotation":{"x":0.0116024613,"y":-0.8316599,"z":-0.00705756526,"w":0.5551193},"PitchYawRoll":{"x":0.00114293268,"y":-1.96444142,"z":-0.0271375161},"Speed":93.59096,"Velocity":{"x":-24.1024265,"y":-0.596342146,"z":-9.725579}},{"Timestamp":"00:00:01.7000000","Position":{"x":222.807266,"y":9.351796,"z":362.4176},"Rotation":{"x":-0.00226762216,"y":-0.829872847,"z":0.00103435572,"w":0.55794704},"PitchYawRoll":{"x":-0.0008136686,"y":-1.95776677,"z":0.00491792755},"Speed":99.3783,"Velocity":{"x":-25.5928383,"y":-0.633217931,"z":-10.3269758}},{"Timestamp":"00:00:01.8000000","Position":{"x":220.1962,"y":9.353688,"z":361.368439},"Rotation":{"x":-0.00312784966,"y":-0.825911462,"z":0.00336543447,"w":0.563781142},"PitchYawRoll":{"x":0.00203233957,"y":-1.94367385,"z":0.008961511},"Speed":102.200218,"Velocity":{"x":-26.4488621,"y":-0.654397666,"z":-10.29378}},{"Timestamp":"00:00:01.9000000","Position":{"x":217.553421,"y":9.299821,"z":360.36853},"Rotation":{"x":0.0166044962,"y":-0.8148796,"z":0.01144888,"w":0.579279244},"PitchYawRoll":{"x":0.0379088819,"y":-1.90535355,"z":-0.013797571},"Speed":102.302467,"Velocity":{"x":-26.9276085,"y":-1.33330178,"z":-8.981768}},{"Timestamp":"00:00:02","Position":{"x":214.8427,"y":9.233453,"z":359.5035},"Rotation":{"x":0.017398797,"y":-0.7940545,"z":0.00970956,"w":0.6075199},"PitchYawRoll":{"x":0.0365728065,"y":-1.83513033,"z":-0.0158343446},"Speed":102.60984,"Velocity":{"x":-27.51297,"y":-1.36228549,"z":-7.32028055}},{"Timestamp":"00:00:02.1000000","Position":{"x":212.032883,"y":9.156992,"z":358.832977},"Rotation":{"x":0.0103127286,"y":-0.765522242,"z":-0.004954733,"w":0.6433077},"PitchYawRoll":{"x":0.00568402559,"y":-1.743798,"z":-0.0221658964},"Speed":105.418045,"Velocity":{"x":-28.8095856,"y":-1.42648661,"z":-5.045267}},{"Timestamp":"00:00:02.2000000","Position":{"x":209.0932,"y":9.08433151,"z":358.389435},"Rotation":{"x":0.0178214852,"y":-0.7389389,"z":-0.0008149782,"w":0.6735362},"PitchYawRoll":{"x":0.0228129569,"y":-1.66302454,"z":-0.0274392553},"Speed":109.391563,"Velocity":{"x":-30.2009182,"y":-1.49537742,"z":-3.00177813}},{"Timestamp":"00:00:02.3000000","Position":{"x":206.0447,"y":8.938132,"z":358.123535},"Rotation":{"x":0.0520308129,"y":-0.7237843,"z":0.0179187246,"w":0.6878285},"PitchYawRoll":{"x":0.0977963656,"y":-1.6192472,"z":-0.05068986},"Speed":113.742126,"Velocity":{"x":-31.4020233,"y":-3.11734128,"z":-1.562492}},{"Timestamp":"00:00:02.4000000","Position":{"x":202.835342,"y":8.676675,"z":358.023865},"Rotation":{"x":0.06961963,"y":-0.700298846,"z":-0.0069837193,"w":0.710412443},"PitchYawRoll":{"x":0.08977535,"y":-1.5516187,"z":-0.107639477},"Speed":118.0294,"Velocity":{"x":-32.623085,"y":-3.23855853,"z":0.4055018}},{"Timestamp":"00:00:02.5000000","Position":{"x":199.501831,"y":8.394559,"z":358.14502},"Rotation":{"x":0.0806079358,"y":-0.656901062,"z":-0.03814624,"w":0.748684347},"PitchYawRoll":{"x":0.07160139,"y":-1.43450546,"z":-0.16375272},"Speed":121.989357,"Velocity":{"x":-33.55525,"y":-3.33109641,"z":3.34747}},{"Timestamp":"00:00:02.6000000","Position":{"x":196.105576,"y":8.134405,"z":358.658478},"Rotation":{"x":0.08659919,"y":-0.602683544,"z":-0.0490546636,"w":0.7917492},"PitchYawRoll":{"x":0.07941002,"y":-1.2939744,"z":-0.1830829},"Speed":125.57885,"Velocity":{"x":-33.94788,"y":-3.37007356,"z":7.280719}},{"Timestamp":"00:00:02.7000000","Position":{"x":192.6878,"y":7.889926,"z":359.559326},"Rotation":{"x":0.0537539646,"y":-0.5454883,"z":-0.01790064,"w":0.836201251},"PitchYawRoll":{"x":0.0707057,"y":-1.152899,"z":-0.08869765},"Speed":128.757889,"Velocity":{"x":-34.0345459,"y":-3.37867713,"z":10.4616909}},{"Timestamp":"00:00:02.8000000","Position":{"x":189.252243,"y":7.731127,"z":360.742065},"Rotation":{"x":0.0389275439,"y":-0.480870247,"z":-0.0229366515,"w":0.875626862},"PitchYawRoll":{"x":0.0462689,"y":-1.00261712,"z":-0.0776842},"Speed":131.227676,"Velocity":{"x":-33.7122879,"y":-2.50642037,"z":13.6366282}},{"Timestamp":"00:00:02.9000000","Position":{"x":185.923,"y":7.58521366,"z":362.26767},"Rotation":{"x":0.0437293164,"y":-0.412530631,"z":-0.0153994812,"w":0.9097632},"PitchYawRoll":{"x":0.06704914,"y":-0.8492839,"z":-0.06414311},"Speed":132.546539,"Velocity":{"x":-32.5775032,"y":-1.61305249,"z":17.0793781}},{"Timestamp":"00:00:03","Position":{"x":182.706314,"y":7.552083,"z":364.1377},"Rotation":{"x":0.00142704812,"y":-0.342163473,"z":-0.00162389921,"w":0.939637959},"PitchYawRoll":{"x":0.00157055259,"y":-0.6984353,"z":-0.004028333},"Speed":133.210922,"Velocity":{"x":-31.1643066,"y":-0.7710672,"z":19.9352989}},{"Timestamp":"00:00:03.1000000","Position":{"x":179.619476,"y":7.6292,"z":366.242737},"Rotation":{"x":-0.01463058,"y":-0.286319673,"z":-0.03893881,"w":0.9572308},"PitchYawRoll":{"x":-0.05043946,"y":-0.582955658,"z":-0.06621719},"Speed":132.414063,"Velocity":{"x":-29.1221,"y":1.44196057,"z":22.4213352}},{"Timestamp":"00:00:03.2000000","Position":{"x":176.868591,"y":7.91623163,"z":368.647583},"Rotation":{"x":-0.0155525347,"y":-0.248661324,"z":-0.0445994325,"w":0.967438161},"PitchYawRoll":{"x":-0.05245865,"y":-0.5052338,"z":-0.07864079},"Speed":131.227676,"Velocity":{"x":-26.048769,"y":3.238366,"z":25.2929363}},{"Timestamp":"00:00:03.3000000","Position":{"x":174.351929,"y":8.239193,"z":371.28595},"Rotation":{"x":-0.03189002,"y":-0.206841961,"z":-0.04730391,"w":0.976709664},"PitchYawRoll":{"x":-0.08221408,"y":-0.420644939,"z":-0.0792950541},"Speed":131.096512,"Velocity":{"x":-24.0920086,"y":2.99510241,"z":27.1423588}},{"Timestamp":"00:00:03.4000000","Position":{"x":172.0236,"y":8.456127,"z":374.071716},"Rotation":{"x":-0.0203800239,"y":-0.173509926,"z":-0.0353004523,"w":0.9839882},"PitchYawRoll":{"x":-0.05248368,"y":-0.350717574,"z":-0.06243875},"Speed":130.834579,"Velocity":{"x":-22.0455246,"y":2.18850327,"z":28.8099747}},{"Timestamp":"00:00:03.5000000","Position":{"x":170.00029,"y":8.731468,"z":377.0676},"Rotation":{"x":-0.0429326445,"y":-0.13971512,"z":0.0111906277,"w":0.989197254},"PitchYawRoll":{"x":-0.08195011,"y":-0.279225647,"z":0.03414279},"Speed":130.3123,"Velocity":{"x":-19.2871056,"y":2.88383222,"z":30.49551}},{"Timestamp":"00:00:03.6000000","Position":{"x":168.145782,"y":8.993201,"z":380.183929},"Rotation":{"x":-0.0426808968,"y":-0.114265352,"z":0.01284112,"w":0.992449939},"PitchYawRoll":{"x":-0.08192516,"y":-0.227814913,"z":0.03524953},"Speed":130.965485,"Velocity":{"x":-17.53267,"y":2.17964983,"z":31.8010731}},{"Timestamp":"00:00:03.7000000","Position":{"x":166.511383,"y":9.212025,"z":383.4197},"Rotation":{"x":-0.0169377737,"y":-0.103586107,"z":-0.0313962772,"w":0.9939805},"PitchYawRoll":{"x":-0.0402568281,"y":-0.208864033,"z":-0.0589396581},"Speed":131.096512,"Velocity":{"x":-14.2952375,"y":2.13744164,"z":33.42425}},{"Timestamp":"00:00:03.8000000","Position":{"x":165.174484,"y":9.341787,"z":386.810547},"Rotation":{"x":0.009582921,"y":-0.0985040963,"z":-0.0665648654,"w":0.9928616},"PitchYawRoll":{"x":0.005969128,"y":-0.197375447,"z":-0.134472221},"Speed":132.679153,"Velocity":{"x":-12.0655174,"y":0.5974157,"z":34.8192635}},{"Timestamp":"00:00:03.9000000","Position":{"x":164.113632,"y":9.343114,"z":390.369324},"Rotation":{"x":0.0118168294,"y":-0.0913677663,"z":-0.0682479963,"w":0.9934055},"PitchYawRoll":{"x":0.0111126443,"y":-0.182663426,"z":-0.13819468},"Speed":134.953979,"Velocity":{"x":-9.176101,"y":-0.227035061,"z":36.3461}},{"Timestamp":"00:00:04","Position":{"x":163.319565,"y":9.374768,"z":394.086639},"Rotation":{"x":0.00716193672,"y":-0.07141536,"z":-0.08904274,"w":0.9934384},"PitchYawRoll":{"x":0.00153636723,"y":-0.1433894,"z":-0.178892538},"Speed":138.370361,"Velocity":{"x":-6.614249,"y":-0.327499956,"z":37.8614159}},{"Timestamp":"00:00:04.1000000","Position":{"x":162.790817,"y":9.415695,"z":397.948151},"Rotation":{"x":-0.004726055,"y":-0.0362684764,"z":-0.128184155,"w":0.9910757},"PitchYawRoll":{"x":-0.019298587,"y":-0.07564667,"z":-0.256542355},"Speed":141.30687,"Velocity":{"x":-3.31039023,"y":0.7494235,"z":39.1048851}},{"Timestamp":"00:00:04.2000000","Position":{"x":162.63179,"y":9.521067,"z":401.927},"Rotation":{"x":-0.0180172268,"y":0.0102138538,"z":-0.121323511,"w":0.992396951},"PitchYawRoll":{"x":-0.03430112,"y":0.0163849164,"z":-0.243571475},"Speed":144.450058,"Velocity":{"x":0.302016318,"y":0.9454001,"z":40.11274}},{"Timestamp":"00:00:04.3000000","Position":{"x":162.819824,"y":9.574589,"z":405.966278},"Rotation":{"x":-0.000112803034,"y":0.05006555,"z":-0.118448883,"w":0.9916972},"PitchYawRoll":{"x":0.0119720679,"y":0.102310136,"z":-0.237159044},"Speed":147.663162,"Velocity":{"x":4.04701853,"y":-0.200385317,"z":40.8169174}},{"Timestamp":"00:00:04.4000000","Position":{"x":163.2924,"y":9.501942,"z":410.082367},"Rotation":{"x":0.01588954,"y":0.07033117,"z":-0.11688707,"w":0.990524352},"PitchYawRoll":{"x":0.0492514856,"y":0.147494718,"z":-0.231383041},"Speed":151.704391,"Velocity":{"x":5.95902824,"y":-1.82275331,"z":41.6768074}},{"Timestamp":"00:00:04.5000000","Position":{"x":163.866272,"y":9.22272,"z":414.274536},"Rotation":{"x":0.0415706076,"y":0.07982966,"z":-0.125465408,"w":0.98800683},"PitchYawRoll":{"x":0.105482057,"y":0.174175292,"z":-0.243688956},"Speed":155.389343,"Velocity":{"x":6.59972048,"y":-4.45420742,"z":42.42298}},{"Timestamp":"00:00:04.6000000","Position":{"x":164.522644,"y":8.687119,"z":418.549},"Rotation":{"x":0.06693979,"y":0.08617144,"z":-0.115000278,"w":0.9873543},"PitchYawRoll":{"x":0.156301141,"y":0.191189542,"z":-0.2172606},"Speed":159.482437,"Velocity":{"x":6.873659,"y":-6.95920563,"z":43.2073174}},{"Timestamp":"00:00:04.7000000","Position":{"x":165.3001,"y":8.138999,"z":422.92514},"Rotation":{"x":0.0557658747,"y":0.0920826644,"z":-0.0734214,"w":0.9914738},"PitchYawRoll":{"x":0.125584438,"y":0.193765268,"z":-0.135737076},"Speed":162.54158,"Velocity":{"x":8.122776,"y":-5.779616,"z":44.0361061}},{"Timestamp":"00:00:04.8000000","Position":{"x":166.131516,"y":7.67225647,"z":427.369537},"Rotation":{"x":0.0210175,"y":0.103301637,"z":-0.07732042,"w":0.991417468},"PitchYawRoll":{"x":0.05833249,"y":0.212013066,"z":-0.149527922},"Speed":163.029938,"Velocity":{"x":9.153546,"y":-5.2346034,"z":44.0413666}},{"Timestamp":"00:00:04.9000000","Position":{"x":167.142044,"y":7.40352249,"z":431.7858},"Rotation":{"x":0.0158833321,"y":0.11791835,"z":-0.0255654324,"w":0.992567062},"PitchYawRoll":{"x":0.03761024,"y":0.237378851,"z":-0.0470222645},"Speed":164.3394,"Velocity":{"x":10.766305,"y":-3.00409245,"z":44.2602463}},{"Timestamp":"00:00:05","Position":{"x":168.318085,"y":7.272835,"z":436.261963},"Rotation":{"x":-0.002804235,"y":0.145859033,"z":-0.0284237377,"w":0.988893},"PitchYawRoll":{"x":0.002750021,"y":0.2929613,"z":-0.05706508},"Speed":167.827026,"Velocity":{"x":13.59856,"y":-1.01101732,"z":44.57973}},{"Timestamp":"00:00:05.1000000","Position":{"x":169.793152,"y":7.26972771,"z":440.739136},"Rotation":{"x":-0.009223238,"y":0.187554121,"z":-0.0349258743,"w":0.9815898},"PitchYawRoll":{"x":-0.005018945,"y":0.3774114,"z":-0.0720879},"Speed":171.046219,"Velocity":{"x":17.2280674,"y":0.0,"z":44.27938}},{"Timestamp":"00:00:05.2000000","Position":{"x":171.690933,"y":7.35032845,"z":445.1431},"Rotation":{"x":-0.0137107531,"y":0.236300781,"z":-0.01698135,"w":0.971434832},"PitchYawRoll":{"x":-0.0186283886,"y":0.476862162,"z":-0.03948253},"Speed":173.804962,"Velocity":{"x":21.8583679,"y":0.540819645,"z":43.0441246}},{"Timestamp":"00:00:05.3000000","Position":{"x":174.024048,"y":7.457213,"z":449.414948},"Rotation":{"x":-0.00637993,"y":0.272109866,"z":0.00945061,"w":0.9621986},"PitchYawRoll":{"x":-0.0174234957,"y":0.551334858,"z":0.0147151742},"Speed":176.961777,"Velocity":{"x":24.9282074,"y":0.0,"z":42.3662834}},{"Timestamp":"00:00:05.4000000","Position":{"x":176.553543,"y":7.436245,"z":453.6715},"Rotation":{"x":0.009884083,"y":0.294016451,"z":0.00138206792,"w":0.95574826},"PitchYawRoll":{"x":0.01808232,"y":0.5968069,"z":0.008454084},"Speed":180.3562,"Velocity":{"x":26.9824314,"y":-0.6675992,"z":42.20672}},{"Timestamp":"00:00:05.5000000","Position":{"x":179.321579,"y":7.40730572,"z":457.9073},"Rotation":{"x":7.79044E-05,"y":0.325019032,"z":0.006716315,"w":0.9456836},"PitchYawRoll":{"x":-0.00421887031,"y":0.6621061,"z":0.0127540044},"Speed":183.265121,"Velocity":{"x":28.9981289,"y":0.0,"z":41.84052}},{"Timestamp":"00:00:05.6000000","Position":{"x":182.308685,"y":7.47285271,"z":462.0914},"Rotation":{"x":-0.0112628881,"y":0.363013685,"z":0.0105538266,"w":0.931655943},"PitchYawRoll":{"x":-0.0286544524,"y":0.7432578,"z":0.0114881583},"Speed":185.848862,"Velocity":{"x":31.4693165,"y":0.0,"z":40.9242058}},{"Timestamp":"00:00:05.7000000","Position":{"x":185.515427,"y":7.513322,"z":466.157074},"Rotation":{"x":0.0164453629,"y":0.390935123,"z":0.03090111,"w":0.919752359},"PitchYawRoll":{"x":0.0061055515,"y":0.803602636,"z":0.06975744},"Speed":188.0925,"Velocity":{"x":33.36379,"y":0.0,"z":40.2082367}},{"Timestamp":"00:00:05.8000000","Position":{"x":188.9439,"y":7.55605125,"z":470.158325},"Rotation":{"x":0.0185922254,"y":0.4092604,"z":0.07121026,"w":0.9094445},"PitchYawRoll":{"x":-0.0247328263,"y":0.847526252,"z":0.1452519},"Speed":190.744308,"Velocity":{"x":35.32351,"y":0.0,"z":39.4919}},{"Timestamp":"00:00:05.9000000","Position":{"x":192.524628,"y":7.680727,"z":474.123962},"Rotation":{"x":-0.009430175,"y":0.432271183,"z":0.0546981953,"w":0.9000338},"PitchYawRoll":{"x":-0.06457239,"y":0.8984231,"z":0.09043086},"Speed":192.46875,"Velocity":{"x":37.0852432,"y":0.917562962,"z":38.4992638}},{"Timestamp":"00:00:06","Position":{"x":196.29007,"y":7.78605747,"z":477.927979},"Rotation":{"x":0.0131741306,"y":0.4496487,"z":0.04202175,"w":0.8921192},"PitchYawRoll":{"x":-0.0143389,"y":0.934345543,"z":0.08693375},"Speed":194.5976,"Velocity":{"x":39.3860054,"y":0.0,"z":37.02261}},{"Timestamp":"00:00:06.1000000","Position":{"x":200.242477,"y":7.74897432,"z":481.632263},"Rotation":{"x":0.04700466,"y":0.461136371,"z":0.0456771478,"w":0.884905338},"PitchYawRoll":{"x":0.04139475,"y":0.958210468,"z":0.124512494},"Speed":197.34111,"Velocity":{"x":40.84521,"y":-1.0105921,"z":36.54516}},{"Timestamp":"00:00:06.2000000","Position":{"x":204.3814,"y":7.600047,"z":485.2984},"Rotation":{"x":0.0376605131,"y":0.470263839,"z":0.0580742061,"w":0.879807353},"PitchYawRoll":{"x":0.0117597375,"y":0.980929434,"z":0.138047025},"Speed":199.923309,"Velocity":{"x":42.7242165,"y":-1.05708241,"z":35.4623337}},{"Timestamp":"00:00:06.3000000","Position":{"x":208.711792,"y":7.53661442,"z":488.854858},"Rotation":{"x":0.01565385,"y":0.477927566,"z":0.048487585,"w":0.8769203},"PitchYawRoll":{"x":-0.0189890731,"y":0.998955131,"z":0.100169741},"Speed":202.539276,"Velocity":{"x":44.5994568,"y":0.0,"z":34.29546}},{"Timestamp":"00:00:06.4000000","Position":{"x":213.193939,"y":7.49732828,"z":492.2852},"Rotation":{"x":0.014012781,"y":0.4911412,"z":0.0100825634,"w":0.8709089},"PitchYawRoll":{"x":0.0145114185,"y":1.02673948,"z":0.03133162},"Speed":204.77951,"Velocity":{"x":46.34805,"y":0.0,"z":32.9781227}},{"Timestamp":"00:00:06.5000000","Position":{"x":217.897675,"y":7.432891,"z":495.557037},"Rotation":{"x":-0.00176445488,"y":0.504199862,"z":-0.0172403976,"w":0.8634131},"PitchYawRoll":{"x":0.0143459393,"y":1.05731213,"z":-0.0315556824},"Speed":207.459015,"Velocity":{"x":48.5492859,"y":0.0,"z":31.0466824}},{"Timestamp":"00:00:06.6000000","Position":{"x":222.860214,"y":7.407889,"z":498.582916},"Rotation":{"x":-0.003184834,"y":0.515001357,"z":0.001728222,"w":0.8571817},"PitchYawRoll":{"x":-0.0072401,"y":1.08202517,"z":-0.000317587052},"Speed":210.383865,"Velocity":{"x":50.7305336,"y":0.0,"z":29.011076}},{"Timestamp":"00:00:06.7000000","Position":{"x":227.999161,"y":7.549671,"z":501.453369},"Rotation":{"x":-0.0276650842,"y":0.5304274,"z":-0.00193514954,"w":0.8472766},"PitchYawRoll":{"x":-0.044865977,"y":1.11795855,"z":-0.0326336436},"Speed":212.285873,"Velocity":{"x":52.2398872,"y":0.0,"z":27.3542461}},{"Timestamp":"00:00:06.8000000","Position":{"x":233.262238,"y":7.780509,"z":504.163757},"Rotation":{"x":-0.0477050468,"y":0.542095065,"z":-0.04310825,"w":0.8378537},"PitchYawRoll":{"x":-0.0334664732,"y":1.14645052,"z":-0.124277823},"Speed":214.419373,"Velocity":{"x":53.7370949,"y":1.329563,"z":25.6527271}},{"Timestamp":"00:00:06.9000000","Position":{"x":238.700851,"y":7.998218,"z":506.664063},"Rotation":{"x":-0.05125043,"y":0.563807547,"z":-0.05356946,"w":0.822572052},"PitchYawRoll":{"x":-0.0241696462,"y":1.19997454,"z":-0.1464431},"Speed":216.574326,"Velocity":{"x":55.20071,"y":1.36577582,"z":23.8785744}},{"Timestamp":"00:00:07","Position":{"x":244.261948,"y":8.14864,"z":509.043884},"Rotation":{"x":-0.08335912,"y":0.5817189,"z":-0.10351079,"w":0.802458644},"PitchYawRoll":{"x":-0.0138443448,"y":1.25265849,"z":-0.266243756},"Speed":218.750946,"Velocity":{"x":56.6288834,"y":0.0,"z":22.0329685}},{"Timestamp":"00:00:07.1000000","Position":{"x":249.962158,"y":8.141289,"z":511.226959},"Rotation":{"x":-0.0713547841,"y":0.5956616,"z":-0.117214009,"w":0.791426957},"PitchYawRoll":{"x":0.0277331863,"y":1.29420328,"z":-0.27395314},"Speed":221.613266,"Velocity":{"x":58.1584244,"y":0.0,"z":20.1776581}},{"Timestamp":"00:00:07.2000000","Position":{"x":255.837769,"y":8.000734,"z":513.1511},"Rotation":{"x":-0.0314852931,"y":0.612707555,"z":-0.08644533,"w":0.784936547},"PitchYawRoll":{"x":0.05741331,"y":1.33061969,"z":-0.175185457},"Speed":224.513046,"Velocity":{"x":59.6189423,"y":-1.4750917,"z":18.24188}},{"Timestamp":"00:00:07.3000000","Position":{"x":261.889435,"y":7.78753567,"z":514.8692},"Rotation":{"x":-0.0165840667,"y":0.625433266,"z":-0.04434338,"w":0.778840065},"PitchYawRoll":{"x":0.0297596324,"y":1.35451293,"z":-0.0899384543},"Speed":227.678345,"Velocity":{"x":61.3000679,"y":-1.51668608,"z":15.4855671}},{"Timestamp":"00:00:07.4000000","Position":{"x":268.068054,"y":7.62174,"z":516.381958},"Rotation":{"x":-0.02182717,"y":0.633014,"z":-0.0486163162,"w":0.7723039},"PitchYawRoll":{"x":0.027986899,"y":1.3746506,"z":-0.102908492},"Speed":230.426941,"Velocity":{"x":62.57862,"y":-1.54832,"z":13.3595247}},{"Timestamp":"00:00:07.5000000","Position":{"x":274.384766,"y":7.50227165,"z":517.662048},"Rotation":{"x":-0.013621687,"y":0.6413257,"z":-0.0188250374,"w":0.7669168},"PitchYawRoll":{"x":0.00325606414,"y":1.39297676,"z":-0.04636296},"Speed":232.975632,"Velocity":{"x":63.60488,"y":0.0,"z":11.9377127}},{"Timestamp":"00:00:07.6000000","Position":{"x":280.791656,"y":7.469187,"z":518.7742},"Rotation":{"x":0.005729601,"y":0.646038,"z":0.003778532,"w":0.763274431},"PitchYawRoll":{"x":0.00386471,"y":1.4047792,"z":0.0131715741},"Speed":235.081879,"Velocity":{"x":64.45821,"y":0.0,"z":10.4544983}},{"Timestamp":"00:00:07.7000000","Position":{"x":287.23587,"y":7.446987,"z":519.8441},"Rotation":{"x":0.00637135841,"y":0.648307443,"z":-0.00133645476,"w":0.7613508},"PitchYawRoll":{"x":0.0114350161,"y":1.41071916,"z":0.00622621644},"Speed":235.317062,"Velocity":{"x":64.5227051,"y":0.0,"z":10.4649582}},{"Timestamp":"00:00:07.8000000","Position":{"x":293.700836,"y":7.4258213,"z":520.8766},"Rotation":{"x":0.00233473233,"y":0.649367869,"z":0.008997098,"w":0.76041764},"PitchYawRoll":{"x":-0.00813533552,"y":1.41364765,"z":0.0167160816},"Speed":235.317062,"Velocity":{"x":64.6472,"y":0.0,"z":9.66613}},{"Timestamp":"00:00:07.9000000","Position":{"x":300.18045,"y":7.478216,"z":521.8842},"Rotation":{"x":0.000844129943,"y":0.6521719,"z":0.009160978,"w":0.7580153},"PitchYawRoll":{"x":-0.0106707392,"y":1.42104471,"z":0.014989919},"Speed":236.970062,"Velocity":{"x":65.2167358,"y":0.0,"z":8.92810249}},{"Timestamp":"00:00:08","Position":{"x":306.7317,"y":7.528406,"z":522.783142},"Rotation":{"x":-0.00169590826,"y":0.6674863,"z":0.005119829,"w":0.744602561},"PitchYawRoll":{"x":-0.009360658,"y":1.46170688,"z":0.00536051},"Speed":239.112427,"Velocity":{"x":66.0090256,"y":0.0,"z":7.3783803}},{"Timestamp":"00:00:08.1000000","Position":{"x":313.382568,"y":7.57782269,"z":523.4289},"Rotation":{"x":0.0062887324,"y":0.69407475,"z":0.0107816989,"w":0.71979475},"PitchYawRoll":{"x":-0.005915191,"y":1.53448963,"z":0.0242533},"Speed":241.999054,"Velocity":{"x":67.03694,"y":0.0,"z":4.984021}},{"Timestamp":"00:00:08.2000000","Position":{"x":320.1172,"y":7.53882,"z":523.8784},"Rotation":{"x":0.02579659,"y":0.720066845,"z":0.0175502822,"w":0.6932029},"PitchYawRoll":{"x":0.0105098663,"y":1.6084851,"z":0.0615211539},"Speed":244.431183,"Velocity":{"x":67.814476,"y":0.0,"z":3.35778666}},{"Timestamp":"00:00:08.3000000","Position":{"x":326.945435,"y":7.46475458,"z":524.1675},"Rotation":{"x":0.009141057,"y":0.724994063,"z":0.0117839286,"w":0.6885936},"PitchYawRoll":{"x":-0.00449958071,"y":1.62235212,"z":0.0294873733},"Speed":246.887756,"Velocity":{"x":68.5746841,"y":0.0,"z":0.848207533}},{"Timestamp":"00:00:08.4000000","Position":{"x":333.845764,"y":7.505761,"z":524.1665},"Rotation":{"x":0.004390331,"y":0.709935367,"z":0.007691937,"w":0.7042112},"PitchYawRoll":{"x":-0.004738824,"y":1.5789324,"z":0.0170680266},"Speed":249.618515,"Velocity":{"x":69.33848,"y":0.0,"z":0.0}},{"Timestamp":"00:00:08.5000000","Position":{"x":340.820618,"y":7.533921,"z":524.2544},"Rotation":{"x":0.004192171,"y":0.6885678,"z":0.00647003762,"w":0.725131},"PitchYawRoll":{"x":-0.00283070188,"y":1.51910233,"z":0.0151570179},"Speed":252.379486,"Velocity":{"x":70.05716,"y":0.0,"z":2.60069442}},{"Timestamp":"00:00:08.6000000","Position":{"x":347.8557,"y":7.52146053,"z":524.6439},"Rotation":{"x":0.00167400879,"y":0.684704959,"z":0.00105036027,"w":0.728817642},"PitchYawRoll":{"x":0.001001728,"y":1.50839937,"z":0.00382345566},"Speed":254.915924,"Velocity":{"x":70.67462,"y":0.0,"z":4.376267}},{"Timestamp":"00:00:08.7000000","Position":{"x":354.957245,"y":7.44759274,"z":525.0174},"Rotation":{"x":0.00480090454,"y":0.70032084,"z":-0.000805752934,"w":0.713811636},"PitchYawRoll":{"x":0.007982663,"y":1.55169475,"z":0.00557406433},"Speed":257.477875,"Velocity":{"x":71.4997559,"y":0.0,"z":1.76904678}},{"Timestamp":"00:00:08.8000000","Position":{"x":362.15625,"y":7.474572,"z":525.039551},"Rotation":{"x":0.009421217,"y":0.725153744,"z":0.015403484,"w":0.6883502},"PitchYawRoll":{"x":-0.009375433,"y":1.6230222,"z":0.0348767154},"Speed":260.065582,"Velocity":{"x":72.23492,"y":0.0,"z":-0.8934813}},{"Timestamp":"00:00:08.9000000","Position":{"x":369.411133,"y":7.50128651,"z":524.8306},"Rotation":{"x":0.00568180764,"y":0.745414436,"z":0.004538399,"w":0.666561663},"PitchYawRoll":{"x":0.0008086591,"y":1.68236589,"z":0.0145213595},"Speed":262.6793,"Velocity":{"x":72.87719,"y":0.0,"z":-3.60846329}},{"Timestamp":"00:00:09","Position":{"x":376.7311,"y":7.54304934,"z":524.3175},"Rotation":{"x":0.009561594,"y":0.7469854,"z":0.009669831,"w":0.664701343},"PitchYawRoll":{"x":-0.00173587678,"y":1.68726361,"z":0.0271431729},"Speed":265.5847,"Velocity":{"x":73.4972,"y":0.0,"z":-6.37928534}},{"Timestamp":"00:00:09.1000000","Position":{"x":384.104919,"y":7.52779531,"z":523.5982},"Rotation":{"x":0.0234755985,"y":0.73174274,"z":0.0149181178,"w":0.681013167},"PitchYawRoll":{"x":0.010157302,"y":1.64230406,"z":0.0547023453},"Speed":267.985748,"Velocity":{"x":74.16166,"y":0.0,"z":-6.43695831}},{"Timestamp":"00:00:09.2000000","Position":{"x":391.58017,"y":7.57959127,"z":523.0323},"Rotation":{"x":0.0193573479,"y":0.7094841,"z":0.0286979936,"w":0.7038707},"PitchYawRoll":{"x":-0.0135029415,"y":1.57919836,"z":0.06791902},"Speed":270.679047,"Velocity":{"x":75.09663,"y":0.0,"z":-3.71835732}},{"Timestamp":"00:00:09.3000000","Position":{"x":399.120178,"y":7.62445545,"z":522.692566},"Rotation":{"x":0.0335022,"y":0.697625756,"z":0.02653016,"w":0.7151867},"PitchYawRoll":{"x":0.0109439474,"y":1.54547369,"z":0.0847936049},"Speed":273.399445,"Velocity":{"x":75.92106,"y":0.0,"z":-1.87843847}},{"Timestamp":"00:00:09.4000000","Position":{"x":406.7624,"y":7.593935,"z":522.612244},"Rotation":{"x":0.0284578167,"y":0.7021405,"z":0.0296622477,"w":0.7108509},"PitchYawRoll":{"x":-0.00119965617,"y":1.55851686,"z":0.08222627},"Speed":276.423431,"Velocity":{"x":76.78429,"y":0.0,"z":0.0}},{"Timestamp":"00:00:09.5000000","Position":{"x":414.477661,"y":7.57346344,"z":522.569946},"Rotation":{"x":0.0276870821,"y":0.7206891,"z":0.032902807,"w":0.69192344},"PitchYawRoll":{"x":-0.009144273,"y":1.611909,"z":0.0855442956},"Speed":278.922455,"Velocity":{"x":77.45476,"y":0.0,"z":-1.91638541}},{"Timestamp":"00:00:09.6000000","Position":{"x":422.262268,"y":7.6076045,"z":522.2666},"Rotation":{"x":0.04065292,"y":0.743794441,"z":0.046841044,"w":0.6655247},"PitchYawRoll":{"x":-0.0156885926,"y":1.682724,"z":0.123133495},"Speed":281.725677,"Velocity":{"x":78.16138,"y":0.0,"z":-3.87010646}},{"Timestamp":"00:00:09.7000000","Position":{"x":430.104523,"y":7.6883707,"z":521.7531},"Rotation":{"x":0.04514794,"y":0.755560637,"z":0.045082815,"w":0.651964247},"PitchYawRoll":{"x":-0.00933162,"y":1.71833,"z":0.127352744},"Speed":284.272675,"Velocity":{"x":78.74729,"y":0.0,"z":-5.85465527}},{"Timestamp":"00:00:09.8000000","Position":{"x":438.009979,"y":7.75389242,"z":521.0037},"Rotation":{"x":0.0379546359,"y":0.748401642,"z":0.04257887,"w":0.660788536},"PitchYawRoll":{"x":-0.0136602568,"y":1.69575667,"z":0.113324285},"Speed":287.129639,"Velocity":{"x":79.36811,"y":0.0,"z":-7.87903}},{"Timestamp":"00:00:09.9000000","Position":{"x":445.978149,"y":7.838666,"z":520.1696},"Rotation":{"x":0.0348775871,"y":0.735091448,"z":0.0384534672,"w":0.6759774},"PitchYawRoll":{"x":-0.009431266,"y":1.65502179,"z":0.10344819},"Speed":289.435883,"Velocity":{"x":80.09771,"y":0.0,"z":-6.95218563}},{"Timestamp":"00:00:10","Position":{"x":454.029877,"y":8.043462,"z":519.5464},"Rotation":{"x":0.0204972811,"y":0.7282161,"z":0.0603100881,"w":0.682381},"PitchYawRoll":{"x":-0.06028029,"y":1.63915253,"z":0.112398326},"Speed":290.595947,"Velocity":{"x":80.5421448,"y":1.99277341,"z":-4.98880339}},{"Timestamp":"00:00:10.1000000","Position":{"x":462.054718,"y":9.275696,"z":519.1352},"Rotation":{"x":-0.03755678,"y":0.7187576,"z":0.137009919,"w":0.6805918},"PitchYawRoll":{"x":-0.252972037,"y":1.64225519,"z":0.132898077},"Speed":289.1466,"Velocity":{"x":78.69668,"y":15.7802658,"z":-2.97956848}},{"Timestamp":"00:00:10.2000000","Position":{"x":469.6583,"y":11.9272823,"z":518.948364},"Rotation":{"x":-0.0912598446,"y":0.7066867,"z":0.192827448,"w":0.6745985},"PitchYawRoll":{"x":-0.4105498,"y":1.64467835,"z":0.131557137},"Speed":286.269531,"Velocity":{"x":74.10201,"y":28.83135,"z":-0.983507633}},{"Timestamp":"00:00:10.3000000","Position":{"x":476.9178,"y":15.13899,"z":518.8387},"Rotation":{"x":-0.100230083,"y":0.7042605,"z":0.2044492,"w":0.672437},"PitchYawRoll":{"x":-0.440733165,"y":1.64712059,"z":0.134184554},"Speed":283.988525,"Velocity":{"x":72.0126648,"y":32.20451,"z":0.0}},{"Timestamp":"00:00:10.4000000","Position":{"x":484.034546,"y":18.4697247,"z":518.7883},"Rotation":{"x":-0.09481095,"y":0.7003264,"z":0.205133811,"w":0.677107036},"PitchYawRoll":{"x":-0.433617,"y":1.63661277,"z":0.145510823},"Speed":281.4441,"Velocity":{"x":71.3674545,"y":31.9159679,"z":0.0}},{"Timestamp":"00:00:10.5000000","Position":{"x":491.12146,"y":21.597456,"z":518.7682},"Rotation":{"x":-0.0802577,"y":0.6965461,"z":0.196287245,"w":0.68545866},"PitchYawRoll":{"x":-0.398792833,"y":1.61882257,"z":0.15794307},"Speed":276.976837,"Velocity":{"x":70.9900742,"y":29.6625538,"z":0.0}},{"Timestamp":"00:00:10.6000000","Position":{"x":498.187744,"y":24.4667,"z":518.748047},"Rotation":{"x":-0.06603717,"y":0.692582548,"z":0.187485456,"w":0.693410158},"PitchYawRoll":{"x":-0.3643883,"y":1.60087383,"z":0.1693445},"Speed":272.85318,"Velocity":{"x":71.29268,"y":25.7267246,"z":0.0}},{"Timestamp":"00:00:10.7000000","Position":{"x":505.233551,"y":27.0782318,"z":518.7279},"Rotation":{"x":-0.05207015,"y":0.6883332,"z":0.178836942,"w":0.70107305},"PitchYawRoll":{"x":-0.330433667,"y":1.5825572,"z":0.180043429},"Speed":268.790924,"Velocity":{"x":70.83665,"y":23.59882,"z":0.0}},{"Timestamp":"00:00:10.8000000","Position":{"x":512.2586,"y":29.4327984,"z":518.707764},"Rotation":{"x":-0.03848961,"y":0.6837608,"z":0.1702594,"w":0.7085206},"PitchYawRoll":{"x":-0.2969739,"y":1.56370318,"z":0.189766109},"Speed":265.319244,"Velocity":{"x":70.4765,"y":21.5574188,"z":0.0}},{"Timestamp":"00:00:10.9000000","Position":{"x":519.2633,"y":31.531126,"z":518.6876},"Rotation":{"x":-0.0251697525,"y":0.6789181,"z":0.1617957,"w":0.715722561},"PitchYawRoll":{"x":-0.263908148,"y":1.54449093,"z":0.1987308},"Speed":261.892426,"Velocity":{"x":70.07127,"y":19.551796,"z":0.0}},{"Timestamp":"00:00:11","Position":{"x":526.2471,"y":33.3739471,"z":518.6675},"Rotation":{"x":-0.0121139148,"y":0.673788,"z":0.153438747,"w":0.722716749},"PitchYawRoll":{"x":-0.231224388,"y":1.52486813,"z":0.206934825},"Speed":258.7685,"Velocity":{"x":70.10611,"y":15.8709888,"z":0.0}},{"Timestamp":"00:00:11.1000000","Position":{"x":533.211548,"y":34.9619942,"z":518.647339},"Rotation":{"x":0.000672909431,"y":0.668427,"z":0.145164952,"w":0.72947377},"PitchYawRoll":{"x":-0.198912844,"y":1.504979,"z":0.2143247},"Speed":255.937637,"Velocity":{"x":69.7062149,"y":13.9774971,"z":0.0}},{"Timestamp":"00:00:11.2000000","Position":{"x":540.1552,"y":36.2959824,"z":518.6272},"Rotation":{"x":0.0131235849,"y":0.662769437,"z":0.137024358,"w":0.736063},"PitchYawRoll":{"x":-0.167131022,"y":1.48467779,"z":0.220905229},"Speed":253.644531,"Velocity":{"x":69.6822,"y":10.4189692,"z":0.0}},{"Timestamp":"00:00:11.3000000","Position":{"x":547.077942,"y":37.3766632,"z":518.607056},"Rotation":{"x":0.0253000669,"y":0.656913757,"z":0.128968284,"w":0.7424227},"PitchYawRoll":{"x":-0.135754,"y":1.46421027,"z":0.226674035},"Speed":251.372,"Velocity":{"x":69.2921448,"y":8.614353,"z":0.0}},{"Timestamp":"00:00:11.4000000","Position":{"x":553.98175,"y":38.2047539,"z":518.5869},"Rotation":{"x":0.0371995121,"y":0.650833666,"z":0.121021651,"w":0.748589},"PitchYawRoll":{"x":-0.104823016,"y":1.443523,"z":0.231679365},"Speed":249.618515,"Velocity":{"x":68.99932,"y":6.8497,"z":0.0}},{"Timestamp":"00:00:11.5000000","Position":{"x":560.8649,"y":38.78099,"z":518.5668},"Rotation":{"x":0.0488197878,"y":0.644543946,"z":0.113184541,"w":0.7545654},"PitchYawRoll":{"x":-0.07435575,"y":1.4226619,"z":0.235925838},"Speed":248.125275,"Velocity":{"x":68.8393555,"y":3.40853286,"z":0.0}},{"Timestamp":"00:00:11.6000000","Position":{"x":567.727356,"y":39.10605,"z":518.546631},"Rotation":{"x":0.0601734035,"y":0.6382074,"z":0.105449758,"w":0.760230839},"PitchYawRoll":{"x":-0.0443865173,"y":1.40206325,"z":0.239419311},"Speed":247.134781,"Velocity":{"x":68.62755,"y":1.69798267,"z":0.0}},{"Timestamp":"00:00:11.7000000","Position":{"x":574.5707,"y":39.1806946,"z":518.5265},"Rotation":{"x":0.0712027848,"y":0.6318061,"z":0.09783861,"w":0.765623152},"PitchYawRoll":{"x":-0.0150404051,"y":1.38168955,"z":0.242147177},"Speed":246.148209,"Velocity":{"x":68.3745041,"y":0.0,"z":0.0}},{"Timestamp":"00:00:11.8000000","Position":{"x":581.39386,"y":39.00562,"z":518.506348},"Rotation":{"x":0.081985876,"y":0.625428,"z":0.0903275758,"w":0.7706874},"PitchYawRoll":{"x":0.0137938466,"y":1.361759,"z":0.244201079},"Speed":245.6564,"Velocity":{"x":68.21702,"y":-1.6878252,"z":0.0}},{"Timestamp":"00:00:11.9000000","Position":{"x":588.1966,"y":38.5815468,"z":518.4862},"Rotation":{"x":0.09252698,"y":0.6190437,"z":0.08296623,"w":0.7754613},"PitchYawRoll":{"x":0.0420578271,"y":1.34220231,"z":0.245695189},"Speed":245.6564,"Velocity":{"x":68.05008,"y":-5.05934525,"z":0.0}},{"Timestamp":"00:00:12","Position":{"x":594.9822,"y":37.90715,"z":518.4674},"Rotation":{"x":0.100077167,"y":0.612409234,"z":0.07780645,"w":0.7803112},"PitchYawRoll":{"x":0.06282281,"y":1.323056,"z":0.246491343},"Speed":245.6564,"Velocity":{"x":67.90411,"y":-6.740977,"z":0.0}},{"Timestamp":"00:00:12.1000000","Position":{"x":601.7551,"y":36.9802742,"z":518.4491},"Rotation":{"x":0.101287171,"y":0.605221748,"z":0.07756961,"w":0.785767436},"PitchYawRoll":{"x":0.06737715,"y":1.30427921,"z":0.247009933},"Speed":246.148209,"Velocity":{"x":67.62277,"y":-10.111042,"z":0.0}},{"Timestamp":"00:00:12.2000000","Position":{"x":608.5078,"y":35.8064575,"z":518.4308},"Rotation":{"x":0.102461167,"y":0.598136961,"z":0.07733213,"w":0.7910459},"PitchYawRoll":{"x":0.07184045,"y":1.28589368,"z":0.247435272},"Speed":247.134781,"Velocity":{"x":67.62195,"y":-11.827776,"z":0.0}},{"Timestamp":"00:00:12.3000000","Position":{"x":615.240234,"y":34.3864822,"z":518.4125},"Rotation":{"x":0.103595048,"y":0.5911248,"z":0.07706115,"w":0.7961791},"PitchYawRoll":{"x":0.0762540847,"y":1.2678082,"z":0.247709632},"Speed":248.125275,"Velocity":{"x":67.2226257,"y":-15.21821,"z":0.0}},{"Timestamp":"00:00:12.4000000","Position":{"x":621.9525,"y":32.72113,"z":518.394165},"Rotation":{"x":0.104703568,"y":0.5842629,"z":0.07676801,"w":0.8011122},"PitchYawRoll":{"x":0.0806013644,"y":1.2502147,"z":0.247879058},"Speed":249.618515,"Velocity":{"x":67.2278061,"y":-16.97783,"z":0.0}},{"Timestamp":"00:00:12.5000000","Position":{"x":628.6447,"y":30.8110943,"z":518.375854},"Rotation":{"x":0.105719343,"y":0.5774863,"z":0.07647276,"w":0.8059063},"PitchYawRoll":{"x":0.08476536,"y":1.23295081,"z":0.24789381},"Speed":251.372,"Velocity":{"x":67.2564545,"y":-18.7663841,"z":0.0}},{"Timestamp":"00:00:12.6000000","Position":{"x":635.316833,"y":28.65712,"z":518.357544},"Rotation":{"x":0.106762826,"y":0.5708187,"z":0.0761531442,"w":0.810535848},"PitchYawRoll":{"x":0.0889634863,"y":1.21605384,"z":0.247864366},"Speed":253.391022,"Velocity":{"x":66.77819,"y":-22.246767,"z":0.0}},{"Timestamp":"00:00:12.7000000","Position":{"x":641.968933,"y":26.2599125,"z":518.339233},"Rotation":{"x":0.107704058,"y":0.564169466,"z":0.07579544,"w":0.815087557},"PitchYawRoll":{"x":0.09302054,"y":1.19930327,"z":0.247608945},"Speed":255.681839,"Velocity":{"x":66.80605,"y":-24.1076775,"z":0.0}},{"Timestamp":"00:00:12.8000000","Position":{"x":648.5921,"y":24.16751,"z":518.4758},"Rotation":{"x":0.09864783,"y":0.5609972,"z":0.07130983,"w":0.818819642},"PitchYawRoll":{"x":0.08383346,"y":1.19168448,"z":0.229470655},"Speed":243.94281,"Velocity":{"x":66.3580551,"y":-13.3061237,"z":3.3510778}},{"Timestamp":"00:00:12.9000000","Position":{"x":655.2075,"y":23.9283524,"z":519.5011},"Rotation":{"x":0.0600217357,"y":0.5767777,"z":0.03612986,"w":0.8138916},"PitchYawRoll":{"x":0.0565197058,"y":1.2294029,"z":0.128402516},"Speed":241.033,"Velocity":{"x":65.9321747,"y":-1.63129365,"z":11.5357475}},{"Timestamp":"00:00:13","Position":{"x":661.795837,"y":23.73994,"z":520.867859},"Rotation":{"x":0.036250744,"y":0.5665156,"z":0.0211818274,"w":0.8229807},"PitchYawRoll":{"x":0.03577857,"y":1.20439577,"z":0.07601087},"Speed":242.968979,"Velocity":{"x":65.8055344,"y":-1.62816024,"z":14.90196}},{"Timestamp":"00:00:13.1000000","Position":{"x":668.3677,"y":23.5839767,"z":522.54364},"Rotation":{"x":0.0333564878,"y":0.5399668,"z":0.0143710738,"w":0.840902269},"PitchYawRoll":{"x":0.0406642035,"y":1.14041746,"z":0.0602285378},"Speed":245.165588,"Velocity":{"x":65.57582,"y":-1.6224767,"z":18.3030415}},{"Timestamp":"00:00:13.2000000","Position":{"x":674.9003,"y":23.439146,"z":524.5786},"Rotation":{"x":0.0105806263,"y":0.5192532,"z":-0.00149384292,"w":0.85455364},"PitchYawRoll":{"x":0.0196367521,"y":1.09194028,"z":0.00843501},"Speed":246.887756,"Velocity":{"x":65.06433,"y":0.0,"z":21.675806}},{"Timestamp":"00:00:13.3000000","Position":{"x":681.381348,"y":23.4838581,"z":526.9434},"Rotation":{"x":-0.0064595514,"y":0.5008905,"z":0.0112403762,"w":0.865413547},"PitchYawRoll":{"x":-0.0224445388,"y":1.0494976,"z":0.0129844565},"Speed":248.37355,"Velocity":{"x":64.2974,"y":0.0,"z":25.0166073}},{"Timestamp":"00:00:13.4000000","Position":{"x":687.772156,"y":23.531496,"z":529.590637},"Rotation":{"x":0.005431563,"y":0.470116258,"z":0.0103466613,"w":0.8825271},"PitchYawRoll":{"x":-0.000141302531,"y":0.9789194,"z":0.0233714785},"Speed":249.618515,"Velocity":{"x":63.2972565,"y":0.0,"z":28.3069229}},{"Timestamp":"00:00:13.5000000","Position":{"x":694.040955,"y":23.55342,"z":532.585},"Rotation":{"x":0.0127204051,"y":0.431337059,"z":0.00407537771,"w":0.902092},"PitchYawRoll":{"x":0.0194387157,"y":0.8918557,"z":0.0183273219},"Speed":250.618988,"Velocity":{"x":62.0677,"y":0.0,"z":31.5284348}},{"Timestamp":"00:00:13.6000000","Position":{"x":700.14856,"y":23.5635719,"z":535.950562},"Rotation":{"x":0.0140091777,"y":0.395278573,"z":0.0147964023,"w":0.918335259},"PitchYawRoll":{"x":0.0140435807,"y":0.81265223,"z":0.0382605046},"Speed":250.618988,"Velocity":{"x":60.0004959,"y":0.0,"z":35.30413}},{"Timestamp":"00:00:13.7000000","Position":{"x":705.9993,"y":23.60288,"z":539.738342},"Rotation":{"x":0.00508495048,"y":0.359544426,"z":0.0161971375,"w":0.9329735},"PitchYawRoll":{"x":-0.00216017477,"y":0.7357069,"z":0.0338860154},"Speed":250.118256,"Velocity":{"x":57.10349,"y":0.0,"z":39.5763321}},{"Timestamp":"00:00:13.8000000","Position":{"x":711.6034,"y":23.6274223,"z":543.8608},"Rotation":{"x":0.0112978322,"y":0.327650636,"z":0.0123746544,"w":0.944650352},"PitchYawRoll":{"x":0.0132425381,"y":0.667525232,"z":0.03078779},"Speed":250.3685,"Velocity":{"x":55.1315231,"y":0.0,"z":42.39426}},{"Timestamp":"00:00:13.9000000","Position":{"x":716.925842,"y":23.5832634,"z":548.331848},"Rotation":{"x":0.0134157389,"y":0.306325525,"z":0.00142579584,"w":0.9518312},"PitchYawRoll":{"x":0.0246695,"y":0.6225849,"z":0.0109336181},"Speed":250.3685,"Velocity":{"x":51.8365555,"y":0.0,"z":46.3651772}},{"Timestamp":"00:00:14","Position":{"x":721.9553,"y":23.5598812,"z":553.1507},"Rotation":{"x":0.00260938052,"y":0.276296318,"z":-0.00157626532,"w":0.9610677},"PitchYawRoll":{"x":0.0058866567,"y":0.5598839,"z":-0.00158787146},"Speed":250.3685,"Velocity":{"x":48.8719559,"y":0.0,"z":49.4801979}},{"Timestamp":"00:00:14.1000000","Position":{"x":726.67,"y":23.544775,"z":558.278137},"Rotation":{"x":0.00043098352,"y":0.2568674,"z":0.006687915,"w":0.9664234},"PitchYawRoll":{"x":-0.00260301749,"y":0.519587934,"z":0.0131485052},"Speed":250.618988,"Velocity":{"x":45.76625,"y":0.0,"z":52.4584732}},{"Timestamp":"00:00:14.2000000","Position":{"x":731.058655,"y":23.517662,"z":563.692444},"Rotation":{"x":0.00394709362,"y":0.237260088,"z":0.00974284,"w":0.9713893},"PitchYawRoll":{"x":0.00304581854,"y":0.479084164,"z":0.0208026581},"Speed":251.120728,"Velocity":{"x":42.5216331,"y":0.0,"z":55.29717}},{"Timestamp":"00:00:14.3000000","Position":{"x":735.122131,"y":23.52124,"z":569.3801},"Rotation":{"x":0.006037747,"y":0.202755108,"z":0.0123453122,"w":0.979133},"PitchYawRoll":{"x":0.006819835,"y":0.4082896,"z":0.02662692},"Speed":251.875214,"Velocity":{"x":39.1400642,"y":0.0,"z":57.99314}},{"Timestamp":"00:00:14.4000000","Position":{"x":738.8316,"y":23.55304,"z":575.3273},"Rotation":{"x":0.00329805887,"y":0.1641734,"z":0.009654045,"w":0.9863787},"PitchYawRoll":{"x":0.0033370778,"y":0.329823673,"z":0.0201293565},"Speed":252.379486,"Velocity":{"x":35.5521278,"y":0.0,"z":60.421978}},{"Timestamp":"00:00:14.5000000","Position":{"x":742.2286,"y":23.5241623,"z":581.473267},"Rotation":{"x":0.0106548062,"y":0.141935021,"z":0.007991616,"w":0.9897864},"PitchYawRoll":{"x":0.0188278388,"y":0.284679919,"z":0.0188456811},"Speed":253.391022,"Velocity":{"x":32.65088,"y":0.0,"z":62.3551521}},{"Timestamp":"00:00:14.6000000","Position":{"x":745.2939,"y":23.4838486,"z":587.8327},"Rotation":{"x":0.00179014471,"y":0.129205,"z":0.0126083679,"w":0.99153614},"PitchYawRoll":{"x":0.0002919526,"y":0.259151846,"z":0.02546865},"Speed":254.152328,"Velocity":{"x":28.82106,"y":0.0,"z":64.44692}},{"Timestamp":"00:00:14.7000000","Position":{"x":748.019165,"y":23.4898911,"z":594.3717},"Rotation":{"x":0.000340667117,"y":0.10606467,"z":-0.00163228309,"w":0.9943578},"PitchYawRoll":{"x":0.00102375052,"y":0.212531015,"z":-0.0031738868},"Speed":256.1937,"Velocity":{"x":26.6225719,"y":0.0,"z":65.9976044}},{"Timestamp":"00:00:14.8000000","Position":{"x":750.5995,"y":23.4136086,"z":601.0066},"Rotation":{"x":0.00448318059,"y":0.08088667,"z":-0.0179720018,"w":0.996551156},"PitchYawRoll":{"x":0.0118504055,"y":0.162186116,"z":-0.0351019874},"Speed":257.22052,"Velocity":{"x":25.0744686,"y":-0.620392442,"z":66.90299}},{"Timestamp":"00:00:14.9000000","Position":{"x":752.958435,"y":23.431448,"z":607.7814},"Rotation":{"x":-0.00555461366,"y":0.067727685,"z":0.006423581,"w":0.99766773},"PitchYawRoll":{"x":-0.0119545814,"y":0.135636166,"z":0.0120650893},"Speed":258.509857,"Velocity":{"x":22.6961823,"y":0.0,"z":68.1272}},{"Timestamp":"00:00:15","Position":{"x":755.013245,"y":23.7916927,"z":614.6907},"Rotation":{"x":-0.0531177856,"y":0.04975571,"z":0.00167851639,"w":0.9973465},"PitchYawRoll":{"x":-0.106321104,"y":0.09959042,"z":-0.00193770265},"Speed":258.2515,"Velocity":{"x":19.2525787,"y":5.888997,"z":68.85337}},{"Timestamp":"00:00:15.1000000","Position":{"x":756.7898,"y":24.647707,"z":621.6196},"Rotation":{"x":-0.0691376,"y":0.0341400579,"z":0.006018834,"w":0.9970046},"PitchYawRoll":{"x":-0.138720125,"y":0.0689643249,"z":0.007280952},"Speed":259.0274,"Velocity":{"x":17.4523926,"y":8.32878,"z":69.30472}},{"Timestamp":"00:00:15.2000000","Position":{"x":758.335449,"y":25.417738,"z":628.5825},"Rotation":{"x":-0.0324948765,"y":0.0302864,"z":0.006561077,"w":0.9989914},"PitchYawRoll":{"x":-0.06537223,"y":0.0609796755,"z":0.0111408439},"Speed":259.0274,"Velocity":{"x":15.4584131,"y":6.45915651,"z":69.97439}},{"Timestamp":"00:00:15.3000000","Position":{"x":759.8257,"y":25.9679947,"z":635.5478},"Rotation":{"x":0.0103829829,"y":0.0292071979,"z":0.0052656,"w":0.9995056},"PitchYawRoll":{"x":0.0204508044,"y":0.0583128221,"z":0.0111327386},"Speed":257.735474,"Velocity":{"x":15.3264446,"y":3.8705678,"z":69.82624}},{"Timestamp":"00:00:15.4000000","Position":{"x":761.3118,"y":26.26133,"z":642.5053},"Rotation":{"x":0.03968314,"y":0.0280346,"z":0.004348485,"w":0.9988095},"PitchYawRoll":{"x":0.0791152,"y":0.05568942,"z":0.0109118344},"Speed":256.450043,"Velocity":{"x":15.6854992,"y":1.16617584,"z":69.47798}},{"Timestamp":"00:00:15.5000000","Position":{"x":762.794861,"y":26.28601,"z":649.466736},"Rotation":{"x":0.0396419466,"y":0.0267536417,"z":0.00426643668,"w":0.9988466},"PitchYawRoll":{"x":0.07905094,"y":0.0531353168,"z":0.0106443651},"Speed":255.681839,"Velocity":{"x":15.662487,"y":-0.775517166,"z":69.26987}},{"Timestamp":"00:00:15.6000000","Position":{"x":763.0056,"y":25.66478,"z":655.9642},"Rotation":{"x":-0.0130160376,"y":0.191318527,"z":-0.03325575,"w":0.9808781},"PitchYawRoll":{"x":-0.0128414622,"y":0.384808034,"z":-0.07027793},"Speed":222.7241,"Velocity":{"x":-3.2466,"y":-9.357734,"z":61.0697823}},{"Timestamp":"00:00:15.7000000","Position":{"x":762.696045,"y":25.1129379,"z":661.758},"Rotation":{"x":-0.0133101121,"y":0.3245556,"z":-0.0247288179,"w":0.94544965},"PitchYawRoll":{"x":-0.009130477,"y":0.6611014,"z":-0.0554278232},"Speed":196.356873,"Velocity":{"x":-2.25125742,"y":-7.04709959,"z":54.0395432}},{"Timestamp":"00:00:15.8000000","Position":{"x":762.638245,"y":25.0479717,"z":666.7418},"Rotation":{"x":0.009892998,"y":0.4021979,"z":0.0235951487,"w":0.9151952},"PitchYawRoll":{"x":-0.000872931443,"y":0.828142464,"z":0.0511685461},"Speed":166.323349,"Velocity":{"x":0.931107938,"y":-0.6625132,"z":46.1868}},{"Timestamp":"00:00:15.9000000","Position":{"x":762.769,"y":25.0176849,"z":671.014343},"Rotation":{"x":0.0031853707,"y":0.4400401,"z":0.0055483724,"w":0.897955358},"PitchYawRoll":{"x":0.000837696949,"y":0.911301434,"z":0.01276811},"Speed":135.901978,"Velocity":{"x":3.26433539,"y":0.0,"z":37.60915}},{"Timestamp":"00:00:16","Position":{"x":763.1393,"y":25.0419827,"z":674.3821},"Rotation":{"x":0.008594672,"y":0.458478,"z":0.0119612161,"w":0.8885837},"PitchYawRoll":{"x":0.004308105,"y":0.9526129,"z":0.0291421451},"Speed":107.54763,"Velocity":{"x":4.76966524,"y":0.354612142,"z":29.4889946}},{"Timestamp":"00:00:16.1000000","Position":{"x":763.6407,"y":25.0623074,"z":677.0318},"Rotation":{"x":0.0134290233,"y":0.467535973,"z":0.0250470228,"w":0.8835171},"PitchYawRoll":{"x":0.000309274328,"y":0.9734212,"z":0.05684666},"Speed":86.65492,"Velocity":{"x":5.604744,"y":0.0,"z":23.4092045}},{"Timestamp":"00:00:16.2000000","Position":{"x":764.2233,"y":25.0507221,"z":679.20636},"Rotation":{"x":0.0129703386,"y":0.472067654,"z":0.0236999374,"w":0.8811482},"PitchYawRoll":{"x":0.000482337869,"y":0.9836476,"z":0.0540383644},"Speed":74.36117,"Velocity":{"x":6.278058,"y":-0.3108537,"z":19.6762486}},{"Timestamp":"00:00:16.3000000","Position":{"x":764.8622,"y":25.022665,"z":681.042358},"Rotation":{"x":0.0056646415,"y":0.4745361,"z":0.00641592,"w":0.8801944},"PitchYawRoll":{"x":0.00388335017,"y":0.988881,"z":0.01667144},"Speed":64.19554,"Velocity":{"x":6.86654472,"y":-0.3399922,"z":16.45353}},{"Timestamp":"00:00:16.4000000","Position":{"x":765.551331,"y":25.012682,"z":682.5734},"Rotation":{"x":-0.000205240387,"y":0.475704342,"z":-0.00230327132,"w":0.8796022},"PitchYawRoll":{"x":0.0018303101,"y":0.991535962,"z":-0.00424720533},"Speed":55.697422,"Velocity":{"x":7.17693043,"y":0.0,"z":13.7061729}},{"Timestamp":"00:00:16.5000000","Position":{"x":766.035645,"y":25.0248852,"z":683.7941},"Rotation":{"x":0.00178827776,"y":0.472196341,"z":-0.00251267315,"w":0.881488},"PitchYawRoll":{"x":0.00552569,"y":0.983574152,"z":-0.00274094963},"Speed":42.05313,"Velocity":{"x":1.58003616,"y":-0.117471553,"z":11.5734777}},{"Timestamp":"00:00:16.6000000","Position":{"x":766.0517,"y":25.0392933,"z":684.853638},"Rotation":{"x":0.000811996229,"y":0.457792461,"z":-0.0101186866,"w":0.889001131},"PitchYawRoll":{"x":0.0107100457,"y":0.9511666,"z":-0.0172484517},"Speed":36.1231461,"Velocity":{"x":0.482115418,"y":-0.5666099,"z":10.00659}},{"Timestamp":"00:00:16.7000000","Position":{"x":766.081665,"y":25.0205822,"z":685.7494},"Rotation":{"x":0.00246598083,"y":0.44730553,"z":0.008321007,"w":0.8943391},"PitchYawRoll":{"x":-0.00303366641,"y":0.9275644,"z":0.01709053},"Speed":30.0822067,"Velocity":{"x":0.306579947,"y":0.04584022,"z":8.350417}}]}