{"PlayerName":"﻿$ff0UwS$fff|$000|$i$fffFranzis$c02²$000вгат","RaceTime":"00:00:26.8100000","MaxSpeed":499.163574,"ControlNames":["_FakeFinishLine","Steer","Brake","Accelerate","_FakeIsRaceRunning"],"ControlEntries":[{"Time":100000,"Index":4,"Enabled":true},{"Time":100010,"Index":3,"Enabled":true},{"Time":100340,"Index":1,"Enabled":true},{"Time":100360,"Index":1,"Enabled":true},{"Time":100370,"Index":1,"Enabled":true},{"Time":100390,"Index":1,"Enabled":true},{"Time":100400,"Index":1,"Enabled":true},{"Time":100410,"Index":1,"Enabled":true},{"Time":100420,"Index":1,"Enabled":false},{"Time":100610,"Index":1,"Enabled":true},{"Time":100620,"Index":1,"Enabled":true},{"Time":100640,"Index":1,"Enabled":true},{"Time":100650,"Index":1,"Enabled":true},{"Time":100670,"Index":1,"Enabled":true},{"Time":100720,"Index":1,"Enabled":true},{"Time":100730,"Index":1,"Enabled":true},{"Time":100750,"Index":1,"Enabled":false},{"Time":100900,"Index":1,"Enabled":true},{"Time":100920,"Index":1,"Enabled":true},{"Time":100940,"Index":1,"Enabled":true},{"Time":100970,"Index":1,"Enabled":true},{"Time":100980,"Index":1,"Enabled":true},{"Time":101000,"Index":1,"Enabled":false},{"Time":101150,"Index":1,"Enabled":true},{"Time":101160,"Index":1,"Enabled":true},{"Time":101170,"Index":1,"Enabled":true},{"Time":101190,"Index":1,"Enabled":true},{"Time":101220,"Index":1,"Enabled":true},{"Time":101230,"Index":1,"Enabled":true},{"Time":101250,"Index":1,"Enabled":true},{"Time":101260,"Index":1,"Enabled":false},{"Time":101430,"Index":1,"Enabled":true},{"Time":101450,"Index":1,"Enabled":true},{"Time":101470,"Index":1,"Enabled":true},{"Time":101480,"Index":1,"Enabled":true},{"Time":101500,"Index":1,"Enabled":true},{"Time":101530,"Index":1,"Enabled":true},{"Time":101540,"Index":1,"Enabled":true},{"Time":101550,"Index":1,"Enabled":false},{"Time":101820,"Index":1,"Enabled":true},{"Time":101840,"Index":1,"Enabled":true},{"Time":101870,"Index":1,"Enabled":true},{"Time":101890,"Index":1,"Enabled":true},{"Time":101900,"Index":1,"Enabled":false},{"Time":102170,"Index":1,"Enabled":true},{"Time":102180,"Index":1,"Enabled":true},{"Time":102200,"Index":1,"Enabled":true},{"Time":102230,"Index":1,"Enabled":true},{"Time":102250,"Index":1,"Enabled":true},{"Time":102260,"Index":1,"Enabled":false},{"Time":102450,"Index":1,"Enabled":true},{"Time":102460,"Index":1,"Enabled":true},{"Time":102480,"Index":1,"Enabled":true},{"Time":102510,"Index":1,"Enabled":true},{"Time":102530,"Index":1,"Enabled":true},{"Time":102540,"Index":1,"Enabled":false},{"Time":102810,"Index":1,"Enabled":true},{"Time":102820,"Index":1,"Enabled":true},{"Time":102870,"Index":1,"Enabled":true},{"Time":102890,"Index":1,"Enabled":false},{"Time":103170,"Index":1,"Enabled":true},{"Time":103180,"Index":1,"Enabled":true},{"Time":103230,"Index":1,"Enabled":true},{"Time":103240,"Index":1,"Enabled":false},{"Time":103450,"Index":1,"Enabled":true},{"Time":103460,"Index":1,"Enabled":true},{"Time":103480,"Index":1,"Enabled":true},{"Time":103500,"Index":1,"Enabled":true},{"Time":103510,"Index":1,"Enabled":true},{"Time":103530,"Index":1,"Enabled":false},{"Time":103850,"Index":1,"Enabled":true},{"Time":103870,"Index":1,"Enabled":true},{"Time":103880,"Index":1,"Enabled":true},{"Time":103900,"Index":1,"Enabled":true},{"Time":103920,"Index":1,"Enabled":true},{"Time":103930,"Index":1,"Enabled":false},{"Time":104310,"Index":1,"Enabled":true},{"Time":104320,"Index":1,"Enabled":true},{"Time":104340,"Index":1,"Enabled":true},{"Time":104350,"Index":1,"Enabled":true},{"Time":104370,"Index":1,"Enabled":true},{"Time":104380,"Index":1,"Enabled":true},{"Time":104400,"Index":1,"Enabled":true},{"Time":104410,"Index":1,"Enabled":true},{"Time":104620,"Index":1,"Enabled":true},{"Time":104630,"Index":1,"Enabled":false},{"Time":104760,"Index":1,"Enabled":true},{"Time":104770,"Index":1,"Enabled":true},{"Time":104790,"Index":1,"Enabled":true},{"Time":104800,"Index":1,"Enabled":true},{"Time":104820,"Index":1,"Enabled":true},{"Time":104850,"Index":1,"Enabled":false},{"Time":105520,"Index":1,"Enabled":true},{"Time":105540,"Index":1,"Enabled":true},{"Time":105550,"Index":1,"Enabled":true},{"Time":105570,"Index":1,"Enabled":true},{"Time":105580,"Index":1,"Enabled":true},{"Time":105600,"Index":1,"Enabled":true},{"Time":106050,"Index":1,"Enabled":true},{"Time":106070,"Index":1,"Enabled":true},{"Time":106080,"Index":1,"Enabled":true},{"Time":106100,"Index":1,"Enabled":false},{"Time":106180,"Index":1,"Enabled":true},{"Time":106190,"Index":1,"Enabled":true},{"Time":106210,"Index":1,"Enabled":true},{"Time":106220,"Index":1,"Enabled":true},{"Time":106240,"Index":1,"Enabled":true},{"Time":106250,"Index":1,"Enabled":true},{"Time":106260,"Index":1,"Enabled":true},{"Time":106290,"Index":1,"Enabled":true},{"Time":106300,"Index":1,"Enabled":true},{"Time":106320,"Index":1,"Enabled":true},{"Time":106330,"Index":1,"Enabled":false},{"Time":106460,"Index":1,"Enabled":true},{"Time":106470,"Index":1,"Enabled":true},{"Time":106490,"Index":1,"Enabled":true},{"Time":106500,"Index":1,"Enabled":true},{"Time":106520,"Index":1,"Enabled":true},{"Time":106530,"Index":1,"Enabled":true},{"Time":106550,"Index":1,"Enabled":true},{"Time":106570,"Index":1,"Enabled":true},{"Time":106580,"Index":1,"Enabled":true},{"Time":106600,"Index":1,"Enabled":true},{"Time":106610,"Index":1,"Enabled":true},{"Time":106630,"Index":1,"Enabled":true},{"Time":106640,"Index":1,"Enabled":false},{"Time":107160,"Index":1,"Enabled":true},{"Time":107170,"Index":1,"Enabled":true},{"Time":107180,"Index":1,"Enabled":true},{"Time":107190,"Index":1,"Enabled":true},{"Time":107210,"Index":1,"Enabled":true},{"Time":107220,"Index":1,"Enabled":true},{"Time":107240,"Index":1,"Enabled":false},{"Time":107750,"Index":1,"Enabled":true},{"Time":107760,"Index":1,"Enabled":true},{"Time":107770,"Index":1,"Enabled":true},{"Time":107780,"Index":1,"Enabled":true},{"Time":107790,"Index":1,"Enabled":true},{"Time":107800,"Index":1,"Enabled":true},{"Time":107810,"Index":1,"Enabled":true},{"Time":107830,"Index":1,"Enabled":true},{"Time":107850,"Index":1,"Enabled":true},{"Time":107860,"Index":1,"Enabled":false},{"Time":108160,"Index":3,"Enabled":false},{"Time":108300,"Index":3,"Enabled":true},{"Time":108330,"Index":2,"Enabled":true},{"Time":108340,"Index":1,"Enabled":true},{"Time":108360,"Index":1,"Enabled":true},{"Time":108380,"Index":1,"Enabled":true},{"Time":108390,"Index":1,"Enabled":true},{"Time":108410,"Index":1,"Enabled":true},{"Time":108420,"Index":1,"Enabled":true},{"Time":108440,"Index":1,"Enabled":true},{"Time":108450,"Index":1,"Enabled":true},{"Time":110750,"Index":1,"Enabled":true},{"Time":110760,"Index":1,"Enabled":true},{"Time":110780,"Index":1,"Enabled":true},{"Time":110780,"Index":2,"Enabled":false},{"Time":110790,"Index":1,"Enabled":false},{"Time":111060,"Index":1,"Enabled":true},{"Time":111070,"Index":1,"Enabled":true},{"Time":111090,"Index":1,"Enabled":true},{"Time":111100,"Index":1,"Enabled":true},{"Time":111120,"Index":1,"Enabled":true},{"Time":111140,"Index":1,"Enabled":false},{"Time":111420,"Index":1,"Enabled":true},{"Time":111430,"Index":1,"Enabled":true},{"Time":111450,"Index":1,"Enabled":true},{"Time":111460,"Index":1,"Enabled":true},{"Time":111480,"Index":1,"Enabled":true},{"Time":111490,"Index":1,"Enabled":true},{"Time":111510,"Index":1,"Enabled":true},{"Time":111520,"Index":1,"Enabled":true},{"Time":111530,"Index":1,"Enabled":false},{"Time":111820,"Index":1,"Enabled":true},{"Time":111830,"Index":1,"Enabled":true},{"Time":111840,"Index":1,"Enabled":true},{"Time":111880,"Index":1,"Enabled":true},{"Time":111900,"Index":1,"Enabled":false},{"Time":112200,"Index":1,"Enabled":true},{"Time":112210,"Index":1,"Enabled":true},{"Time":112230,"Index":1,"Enabled":true},{"Time":112240,"Index":1,"Enabled":true},{"Time":114890,"Index":1,"Enabled":true},{"Time":114910,"Index":1,"Enabled":true},{"Time":114930,"Index":1,"Enabled":false},{"Time":115080,"Index":1,"Enabled":true},{"Time":115100,"Index":1,"Enabled":true},{"Time":115110,"Index":1,"Enabled":true},{"Time":115130,"Index":1,"Enabled":true},{"Time":115140,"Index":1,"Enabled":true},{"Time":115160,"Index":1,"Enabled":true},{"Time":115180,"Index":1,"Enabled":true},{"Time":115190,"Index":1,"Enabled":true},{"Time":116350,"Index":1,"Enabled":true},{"Time":116360,"Index":1,"Enabled":true},{"Time":116380,"Index":1,"Enabled":true},{"Time":116390,"Index":1,"Enabled":true},{"Time":116410,"Index":1,"Enabled":true},{"Time":116420,"Index":1,"Enabled":true},{"Time":116440,"Index":1,"Enabled":true},{"Time":116450,"Index":1,"Enabled":true},{"Time":116460,"Index":1,"Enabled":true},{"Time":116470,"Index":1,"Enabled":true},{"Time":116630,"Index":1,"Enabled":true},{"Time":116640,"Index":1,"Enabled":true},{"Time":116660,"Index":1,"Enabled":true},{"Time":116670,"Index":1,"Enabled":true},{"Time":116690,"Index":1,"Enabled":true},{"Time":116710,"Index":1,"Enabled":true},{"Time":116720,"Index":1,"Enabled":true},{"Time":116740,"Index":1,"Enabled":true},{"Time":116750,"Index":1,"Enabled":true},{"Time":116860,"Index":1,"Enabled":true},{"Time":116880,"Index":1,"Enabled":true},{"Time":116890,"Index":1,"Enabled":true},{"Time":116900,"Index":1,"Enabled":true},{"Time":116910,"Index":1,"Enabled":true},{"Time":116920,"Index":1,"Enabled":true},{"Time":116940,"Index":1,"Enabled":true},{"Time":116950,"Index":1,"Enabled":true},{"Time":116970,"Index":1,"Enabled":true},{"Time":116990,"Index":1,"Enabled":true},{"Time":117240,"Index":1,"Enabled":true},{"Time":117250,"Index":1,"Enabled":true},{"Time":117270,"Index":1,"Enabled":true},{"Time":117280,"Index":1,"Enabled":true},{"Time":117300,"Index":1,"Enabled":true},{"Time":117310,"Index":1,"Enabled":true},{"Time":117330,"Index":1,"Enabled":true},{"Time":117470,"Index":1,"Enabled":true},{"Time":117490,"Index":1,"Enabled":true},{"Time":117500,"Index":1,"Enabled":true},{"Time":117520,"Index":1,"Enabled":true},{"Time":117530,"Index":1,"Enabled":true},{"Time":117550,"Index":1,"Enabled":true},{"Time":117560,"Index":1,"Enabled":true},{"Time":117580,"Index":1,"Enabled":true},{"Time":117590,"Index":1,"Enabled":true},{"Time":117610,"Index":1,"Enabled":true},{"Time":118340,"Index":1,"Enabled":true},{"Time":118360,"Index":1,"Enabled":false},{"Time":118480,"Index":1,"Enabled":true},{"Time":118500,"Index":1,"Enabled":true},{"Time":118510,"Index":1,"Enabled":true},{"Time":118530,"Index":1,"Enabled":true},{"Time":118550,"Index":1,"Enabled":true},{"Time":118560,"Index":1,"Enabled":true},{"Time":118580,"Index":1,"Enabled":true},{"Time":118590,"Index":1,"Enabled":true},{"Time":118610,"Index":1,"Enabled":false},{"Time":118890,"Index":1,"Enabled":true},{"Time":118900,"Index":1,"Enabled":true},{"Time":118920,"Index":1,"Enabled":true},{"Time":118930,"Index":1,"Enabled":true},{"Time":118940,"Index":1,"Enabled":true},{"Time":118960,"Index":1,"Enabled":true},{"Time":118970,"Index":1,"Enabled":false},{"Time":119280,"Index":1,"Enabled":true},{"Time":119290,"Index":1,"Enabled":true},{"Time":119310,"Index":1,"Enabled":true},{"Time":119330,"Index":1,"Enabled":true},{"Time":119340,"Index":1,"Enabled":true},{"Time":119370,"Index":1,"Enabled":true},{"Time":119390,"Index":1,"Enabled":true},{"Time":119400,"Index":1,"Enabled":false},{"Time":119970,"Index":1,"Enabled":true},{"Time":119980,"Index":1,"Enabled":true},{"Time":120000,"Index":1,"Enabled":true},{"Time":120010,"Index":1,"Enabled":true},{"Time":120030,"Index":1,"Enabled":true},{"Time":120040,"Index":1,"Enabled":true},{"Time":120060,"Index":1,"Enabled":true},{"Time":120070,"Index":1,"Enabled":true},{"Time":120090,"Index":1,"Enabled":true},{"Time":120110,"Index":1,"Enabled":true},{"Time":120120,"Index":1,"Enabled":true},{"Time":120140,"Index":1,"Enabled":true},{"Time":120150,"Index":1,"Enabled":true},{"Time":120220,"Index":1,"Enabled":true},{"Time":120230,"Index":1,"Enabled":true},{"Time":120250,"Index":1,"Enabled":true},{"Time":120260,"Index":1,"Enabled":true},{"Time":120280,"Index":1,"Enabled":false},{"Time":120490,"Index":1,"Enabled":true},{"Time":120500,"Index":1,"Enabled":true},{"Time":120510,"Index":1,"Enabled":true},{"Time":120530,"Index":1,"Enabled":true},{"Time":120540,"Index":1,"Enabled":true},{"Time":120640,"Index":1,"Enabled":true},{"Time":120650,"Index":1,"Enabled":true},{"Time":120670,"Index":1,"Enabled":true},{"Time":120680,"Index":1,"Enabled":true},{"Time":120700,"Index":1,"Enabled":true},{"Time":120750,"Index":1,"Enabled":false},{"Time":120920,"Index":1,"Enabled":true},{"Time":120930,"Index":1,"Enabled":true},{"Time":120950,"Index":1,"Enabled":true},{"Time":120960,"Index":1,"Enabled":true},{"Time":120980,"Index":1,"Enabled":true},{"Time":121000,"Index":1,"Enabled":true},{"Time":121030,"Index":1,"Enabled":true},{"Time":121040,"Index":1,"Enabled":true},{"Time":121060,"Index":1,"Enabled":true},{"Time":121070,"Index":1,"Enabled":true},{"Time":121090,"Index":1,"Enabled":false},{"Time":122540,"Index":1,"Enabled":true},{"Time":122560,"Index":1,"Enabled":true},{"Time":122570,"Index":1,"Enabled":true},{"Time":122590,"Index":1,"Enabled":true},{"Time":122610,"Index":1,"Enabled":true},{"Time":122620,"Index":1,"Enabled":true},{"Time":122630,"Index":1,"Enabled":true},{"Time":122650,"Index":1,"Enabled":true},{"Time":122680,"Index":1,"Enabled":true},{"Time":122700,"Index":1,"Enabled":true},{"Time":122710,"Index":1,"Enabled":true},{"Time":122730,"Index":1,"Enabled":false},{"Time":122790,"Index":1,"Enabled":true},{"Time":122810,"Index":1,"Enabled":true},{"Time":122820,"Index":1,"Enabled":true},{"Time":122840,"Index":1,"Enabled":true},{"Time":122850,"Index":1,"Enabled":true},{"Time":122870,"Index":1,"Enabled":true},{"Time":122880,"Index":1,"Enabled":true},{"Time":122930,"Index":1,"Enabled":true},{"Time":122940,"Index":1,"Enabled":true},{"Time":122950,"Index":1,"Enabled":true},{"Time":122960,"Index":1,"Enabled":true},{"Time":122980,"Index":1,"Enabled":true},{"Time":122990,"Index":1,"Enabled":true},{"Time":123050,"Index":1,"Enabled":true},{"Time":123070,"Index":1,"Enabled":true},{"Time":123090,"Index":1,"Enabled":true},{"Time":123100,"Index":1,"Enabled":false},{"Time":123340,"Index":1,"Enabled":true},{"Time":123350,"Index":1,"Enabled":true},{"Time":123370,"Index":1,"Enabled":true},{"Time":123380,"Index":1,"Enabled":true},{"Time":123400,"Index":1,"Enabled":true},{"Time":123410,"Index":1,"Enabled":true},{"Time":123430,"Index":1,"Enabled":true},{"Time":123440,"Index":1,"Enabled":true},{"Time":123460,"Index":1,"Enabled":true},{"Time":123470,"Index":1,"Enabled":true},{"Time":123490,"Index":1,"Enabled":true},{"Time":123510,"Index":1,"Enabled":true},{"Time":123520,"Index":1,"Enabled":false},{"Time":123650,"Index":1,"Enabled":true},{"Time":123660,"Index":1,"Enabled":true},{"Time":123680,"Index":1,"Enabled":true},{"Time":123690,"Index":1,"Enabled":true},{"Time":123710,"Index":1,"Enabled":true},{"Time":124020,"Index":1,"Enabled":true},{"Time":124040,"Index":1,"Enabled":true},{"Time":124050,"Index":1,"Enabled":true},{"Time":124070,"Index":1,"Enabled":false},{"Time":124240,"Index":1,"Enabled":true},{"Time":124260,"Index":1,"Enabled":true},{"Time":124270,"Index":1,"Enabled":true},{"Time":124290,"Index":1,"Enabled":true},{"Time":124300,"Index":1,"Enabled":true},{"Time":124320,"Index":1,"Enabled":true},{"Time":124360,"Index":1,"Enabled":true},{"Time":124370,"Index":1,"Enabled":true},{"Time":124380,"Index":1,"Enabled":true},{"Time":124400,"Index":1,"Enabled":false},{"Time":124780,"Index":1,"Enabled":true},{"Time":124790,"Index":1,"Enabled":true},{"Time":124800,"Index":1,"Enabled":true},{"Time":124820,"Index":1,"Enabled":true},{"Time":124850,"Index":1,"Enabled":true},{"Time":124860,"Index":1,"Enabled":true},{"Time":124880,"Index":1,"Enabled":false},{"Time":125350,"Index":1,"Enabled":true},{"Time":125360,"Index":1,"Enabled":true},{"Time":125380,"Index":1,"Enabled":true},{"Time":125430,"Index":1,"Enabled":false},{"Time":126150,"Index":1,"Enabled":true},{"Time":126160,"Index":1,"Enabled":true},{"Time":126170,"Index":1,"Enabled":true},{"Time":126190,"Index":1,"Enabled":true},{"Time":126200,"Index":1,"Enabled":true},{"Time":126210,"Index":1,"Enabled":true},{"Time":126270,"Index":1,"Enabled":true},{"Time":126280,"Index":1,"Enabled":true},{"Time":126300,"Index":1,"Enabled":true},{"Time":126310,"Index":1,"Enabled":false},{"Time":126430,"Index":1,"Enabled":true},{"Time":126440,"Index":1,"Enabled":true},{"Time":126460,"Index":1,"Enabled":true},{"Time":126470,"Index":1,"Enabled":true},{"Time":126490,"Index":1,"Enabled":true},{"Time":126500,"Index":1,"Enabled":true},{"Time":126520,"Index":1,"Enabled":false},{"Time":126810,"Index":0,"Enabled":true}],"Samples":[{"Timestamp":"00:00:00","Position":{"x":1012.8,"y":42.21,"z":400.0},"Rotation":{"x":3.38963218E-05,"y":-0.7070814,"z":0.0,"w":0.7071322},"PitchYawRoll":{"x":4.79383634E-05,"y":-1.57072449,"z":-4.79349146E-05},"Speed":2.11514867E-14,"Velocity":{"x":5.875413E-15,"y":0.0,"z":0.0}},{"Timestamp":"00:00:00.1000000","Position":{"x":1012.74445,"y":42.0969467,"z":400.0},"Rotation":{"x":-0.0007796147,"y":-0.7070805,"z":-0.000813511549,"w":0.7071322},"PitchYawRoll":{"x":-0.00225301948,"y":-1.5707233,"z":-4.801974E-05},"Speed":9.042483,"Velocity":{"x":-1.37929571,"y":-2.09921122,"z":0.0}},{"Timestamp":"00:00:00.2000000","Position":{"x":1012.53278,"y":42.0064278,"z":400.000458},"Rotation":{"x":-0.00152533245,"y":-0.7070793,"z":-0.000779615249,"w":0.7071322},"PitchYawRoll":{"x":-0.00325973053,"y":-1.57071984,"z":0.00105448009},"Speed":10.8041878,"Velocity":{"x":-2.98648357,"y":-0.296474159,"z":0.0}},{"Timestamp":"00:00:00.3000000","Position":{"x":1012.16174,"y":42.0079575,"z":400.0006},"Rotation":{"x":-0.00199987832,"y":-0.7070778,"z":-0.00101688935,"w":0.7071322},"PitchYawRoll":{"x":-0.004266414,"y":-1.57071638,"z":0.00138998916},"Speed":16.4764786,"Velocity":{"x":-4.5753994,"y":-0.113204524,"z":0.0}},{"Timestamp":"00:00:00.4000000","Position":{"x":1011.6319,"y":42.00976,"z":399.995636},"Rotation":{"x":-0.00240858388,"y":-0.707650065,"z":-0.00213720486,"w":0.7065557},"PitchYawRoll":{"x":-0.00642842846,"y":-1.57234263,"z":0.00038876044},"Speed":22.1078739,"Velocity":{"x":-6.137319,"y":0.151849523,"z":-0.151896}},{"Timestamp":"00:00:00.5000000","Position":{"x":1010.94574,"y":42.0117645,"z":399.990265},"Rotation":{"x":-0.0027592252,"y":-0.710586131,"z":-0.00303176721,"w":0.703598261},"PitchYawRoll":{"x":-0.008191528,"y":-1.58068013,"z":-0.000344957953},"Speed":27.7693748,"Velocity":{"x":-7.71135569,"y":-0.190794334,"z":0.0}},{"Timestamp":"00:00:00.6000000","Position":{"x":1010.103,"y":42.0113754,"z":399.981659},"Rotation":{"x":-0.00249201735,"y":-0.7121037,"z":-0.002935824,"w":0.702063739},"PitchYawRoll":{"x":-0.007680409,"y":-1.58499742,"z":-0.0005731215},"Speed":33.4460564,"Velocity":{"x":-9.287019,"y":-0.229779378,"z":-0.114907265}},{"Timestamp":"00:00:00.7000000","Position":{"x":1009.10431,"y":42.0079842,"z":399.9601},"Rotation":{"x":-0.0009933019,"y":-0.714495957,"z":-0.00202086149,"w":0.6996359},"PitchYawRoll":{"x":-0.00427771127,"y":-1.591815,"z":-0.00140831468},"Speed":39.1317368,"Velocity":{"x":-10.8632774,"y":-0.268779159,"z":-0.268861443}},{"Timestamp":"00:00:00.8000000","Position":{"x":1007.9552,"y":41.9848862,"z":399.926819},"Rotation":{"x":0.00645697769,"y":-0.720265865,"z":0.004730644,"w":0.6936519},"PitchYawRoll":{"x":0.0157731455,"y":-1.608416,"z":-0.002738644},"Speed":44.9222755,"Velocity":{"x":-12.45933,"y":-0.616915047,"z":-0.308646351}},{"Timestamp":"00:00:00.9000000","Position":{"x":1006.64954,"y":41.9414864,"z":399.875031},"Rotation":{"x":0.0194607917,"y":-0.723452,"z":0.017489003,"w":0.6898787},"PitchYawRoll":{"x":0.05218018,"y":-1.61819172,"z":-0.00402732566},"Speed":51.0055161,"Velocity":{"x":-14.1411228,"y":-0.700187862,"z":-0.52559644}},{"Timestamp":"00:00:01","Position":{"x":1005.16571,"y":41.8831863,"z":399.792084},"Rotation":{"x":0.02824305,"y":-0.7278838,"z":0.0251872186,"w":0.6846554},"PitchYawRoll":{"x":0.07541337,"y":-1.63173389,"z":-0.006626235},"Speed":57.4510841,"Velocity":{"x":-15.8842878,"y":-1.18095517,"z":-0.9862909}},{"Timestamp":"00:00:01.1000000","Position":{"x":1003.48895,"y":41.7724533,"z":399.682251},"Rotation":{"x":0.0238800421,"y":-0.733379364,"z":0.0196678918,"w":0.6791153},"PitchYawRoll":{"x":0.0613232,"y":-1.64733791,"z":-0.008312823},"Speed":63.9392738,"Velocity":{"x":-17.6632748,"y":-1.31321836,"z":-1.31684279}},{"Timestamp":"00:00:01.2000000","Position":{"x":1001.63208,"y":41.6689072,"z":399.5328},"Rotation":{"x":0.01628638,"y":-0.736834168,"z":0.0122964168,"w":0.675765455},"PitchYawRoll":{"x":0.04014426,"y":-1.65705717,"z":-0.007381803},"Speed":70.24111,"Velocity":{"x":-19.3848362,"y":-1.44121194,"z":-1.687176}},{"Timestamp":"00:00:01.3000000","Position":{"x":999.616333,"y":41.5569267,"z":399.335541},"Rotation":{"x":0.0169831254,"y":-0.745702744,"z":0.0120154042,"w":0.665953934},"PitchYawRoll":{"x":0.0405526757,"y":-1.68347335,"z":-0.00932545},"Speed":76.39626,"Velocity":{"x":-21.0592632,"y":-1.56570113,"z":-2.096365}},{"Timestamp":"00:00:01.4000000","Position":{"x":997.439941,"y":41.4460449,"z":399.079132},"Rotation":{"x":0.0206414554,"y":-0.751265168,"z":0.0156384148,"w":0.6594922},"PitchYawRoll":{"x":0.0507474653,"y":-1.70045412,"z":-0.0103877746},"Speed":82.5937347,"Velocity":{"x":-22.739584,"y":-1.1259346,"z":-2.83043313}},{"Timestamp":"00:00:01.5000000","Position":{"x":995.0746,"y":41.3661156,"z":398.7636},"Rotation":{"x":0.00531921629,"y":-0.754813969,"z":0.000289483549,"w":0.6559173},"PitchYawRoll":{"x":0.00741522945,"y":-1.71074522,"z":-0.00765035767},"Speed":88.67108,"Velocity":{"x":-24.3733845,"y":-1.20683122,"z":-3.34077883}},{"Timestamp":"00:00:01.6000000","Position":{"x":992.5581,"y":41.3650856,"z":398.3989},"Rotation":{"x":-0.00514046755,"y":-0.760490358,"z":-0.00535934046,"w":0.6493068},"PitchYawRoll":{"x":-0.0148274833,"y":-1.72819412,"z":0.00085884},"Speed":94.2484,"Velocity":{"x":-25.8843575,"y":-0.6404307,"z":-3.871446}},{"Timestamp":"00:00:01.7000000","Position":{"x":989.913269,"y":41.3498878,"z":397.971283},"Rotation":{"x":0.00260012853,"y":-0.7639265,"z":0.00369881024,"w":0.6452874},"PitchYawRoll":{"x":0.009007024,"y":-1.73878014,"z":0.0008009771},"Speed":99.9763641,"Velocity":{"x":-27.4046078,"y":-0.678044736,"z":-4.446122}},{"Timestamp":"00:00:01.8000000","Position":{"x":987.1305,"y":41.3352928,"z":397.493134},"Rotation":{"x":0.006422677,"y":-0.765569568,"z":0.00414730376,"w":0.6433077},"PitchYawRoll":{"x":0.0146142822,"y":-1.74388909,"z":-0.00449804263},"Speed":102.404823,"Velocity":{"x":-28.0702744,"y":-0.6945147,"z":-4.55412}},{"Timestamp":"00:00:01.9000000","Position":{"x":984.332153,"y":41.2900772,"z":396.9943},"Rotation":{"x":0.012699767,"y":-0.767810166,"z":0.00692095561,"w":0.640514135},"PitchYawRoll":{"x":0.0269014873,"y":-1.75094,"z":-0.0106362812},"Speed":102.60984,"Velocity":{"x":-28.0421333,"y":-1.38848674,"z":-4.91086769}},{"Timestamp":"00:00:02","Position":{"x":981.541,"y":41.1724243,"z":396.4766},"Rotation":{"x":0.025232764,"y":-0.7703813,"z":0.0194031727,"w":0.6367885},"PitchYawRoll":{"x":0.0620776378,"y":-1.75966358,"z":-0.0141667379},"Speed":103.021095,"Velocity":{"x":-28.0484676,"y":-2.08533025,"z":-5.27881956}},{"Timestamp":"00:00:02.1000000","Position":{"x":978.7156,"y":40.97527,"z":395.9294},"Rotation":{"x":0.0351176932,"y":-0.771395,"z":0.0291838422,"w":0.634716332},"PitchYawRoll":{"x":0.08973763,"y":-1.76382494,"z":-0.0171331428},"Speed":106.690681,"Velocity":{"x":-28.9852428,"y":-2.87742281,"z":-5.46684933}},{"Timestamp":"00:00:02.2000000","Position":{"x":975.7597,"y":40.699585,"z":395.344147},"Rotation":{"x":0.0375225171,"y":-0.772071958,"z":0.03155178,"w":0.6336414},"PitchYawRoll":{"x":0.09643706,"y":-1.766251,"z":-0.0179561041},"Speed":111.601425,"Velocity":{"x":-30.2466717,"y":-3.0026474,"z":-6.09487772}},{"Timestamp":"00:00:02.3000000","Position":{"x":972.6556,"y":40.4314728,"z":394.7129},"Rotation":{"x":0.0274102949,"y":-0.775500834,"z":0.020762248,"w":0.6304095},"PitchYawRoll":{"x":0.06682032,"y":-1.77592421,"z":-0.0163367037},"Speed":116.388512,"Velocity":{"x":-31.61189,"y":-2.35026145,"z":-6.356314}},{"Timestamp":"00:00:02.4000000","Position":{"x":969.428467,"y":40.22904,"z":394.0325},"Rotation":{"x":0.0213686544,"y":-0.7777322,"z":0.0146222543,"w":0.628062248},"PitchYawRoll":{"x":0.04961192,"y":-1.78256106,"z":-0.014871357},"Speed":121.017342,"Velocity":{"x":-32.78508,"y":-2.437485,"z":-7.016255}},{"Timestamp":"00:00:02.5000000","Position":{"x":966.078247,"y":40.0777473,"z":393.3069},"Rotation":{"x":0.0112466821,"y":-0.7793716,"z":0.007211784,"w":0.6264195},"PitchYawRoll":{"x":0.0253352262,"y":-1.787439,"z":-0.008495588},"Speed":125.327934,"Velocity":{"x":-34.0049248,"y":-1.68373013,"z":-7.26617146}},{"Timestamp":"00:00:02.6000000","Position":{"x":962.6163,"y":40.01599,"z":392.530762},"Rotation":{"x":0.00146364607,"y":-0.7828666,"z":0.0,"w":0.622187853},"PitchYawRoll":{"x":0.00182133145,"y":-1.79852033,"z":-0.00229168124},"Speed":129.40329,"Velocity":{"x":-35.0474854,"y":-0.867144763,"z":-7.93666172}},{"Timestamp":"00:00:02.7000000","Position":{"x":959.0581,"y":40.01405,"z":391.699524},"Rotation":{"x":-0.002746389,"y":-0.7847914,"z":-0.003235497,"w":0.6197455},"PitchYawRoll":{"x":-0.008482607,"y":-1.80474055,"z":0.0003003156},"Speed":133.344208,"Velocity":{"x":-36.11484,"y":-0.893553257,"z":-8.17836952}},{"Timestamp":"00:00:02.8000000","Position":{"x":955.403931,"y":40.0137,"z":390.824463},"Rotation":{"x":-0.00290048588,"y":-0.7857689,"z":-0.003540885,"w":0.6185032},"PitchYawRoll":{"x":-0.0091526825,"y":-1.80790246,"z":0.000178125934},"Speed":137.2678,"Velocity":{"x":-37.0705681,"y":-0.91719985,"z":-8.878329}},{"Timestamp":"00:00:02.9000000","Position":{"x":951.6527,"y":40.014328,"z":389.905182},"Rotation":{"x":-0.0006421561,"y":-0.7879677,"z":-0.00234198826,"w":0.615711868},"PitchYawRoll":{"x":-0.00448161131,"y":-1.81501424,"z":-0.00187198445},"Speed":141.024521,"Velocity":{"x":-38.0851059,"y":0.942301631,"z":-9.121309}},{"Timestamp":"00:00:03","Position":{"x":947.8031,"y":40.018692,"z":388.9334},"Rotation":{"x":0.00178094883,"y":-0.790441334,"z":-0.00125045551,"w":0.612533867},"PitchYawRoll":{"x":0.000204961456,"y":-1.823064,"z":-0.00434737746},"Speed":145.029022,"Velocity":{"x":-39.0475845,"y":0.9661152,"z":-9.864164}},{"Timestamp":"00:00:03.1000000","Position":{"x":943.8508,"y":40.0214653,"z":387.9092},"Rotation":{"x":0.00132830569,"y":-0.791674,"z":-0.00117650069,"w":0.6109412},"PitchYawRoll":{"x":-0.0002397783,"y":-1.82709289,"z":-0.00354072312},"Speed":148.998138,"Velocity":{"x":-40.11623,"y":0.9925556,"z":-10.1341248}},{"Timestamp":"00:00:03.2000000","Position":{"x":939.7939,"y":40.0197563,"z":386.8443},"Rotation":{"x":-0.0011015312,"y":-0.792346835,"z":-0.00155733968,"w":0.610067964},"PitchYawRoll":{"x":-0.00381193333,"y":-1.82929754,"z":-0.00015457657},"Speed":152.922882,"Velocity":{"x":-41.1729279,"y":-1.01870036,"z":-10.4010668}},{"Timestamp":"00:00:03.3000000","Position":{"x":935.6364,"y":40.01765,"z":385.73938},"Rotation":{"x":-0.00201573945,"y":-0.7933675,"z":-0.00155934936,"w":0.608737648},"PitchYawRoll":{"x":-0.00492841145,"y":-1.83264756,"z":0.00129997544},"Speed":156.794159,"Velocity":{"x":-42.0930176,"y":-5.15473759E-15,"z":-11.18584}},{"Timestamp":"00:00:03.4000000","Position":{"x":931.378662,"y":40.017868,"z":384.594421},"Rotation":{"x":-0.000799277739,"y":-0.7939535,"z":-0.00121794816,"w":0.607976735},"PitchYawRoll":{"x":-0.002905877,"y":-1.83457172,"z":-0.000211789607},"Speed":160.763412,"Velocity":{"x":-43.1586075,"y":5.28523E-15,"z":-11.4690113}},{"Timestamp":"00:00:03.5000000","Position":{"x":927.03595,"y":40.01903,"z":383.416351},"Rotation":{"x":0.0005713738,"y":-0.7945949,"z":-0.0008761069,"w":0.607139051},"PitchYawRoll":{"x":-0.000698494841,"y":-1.8366822,"z":-0.00197186018},"Speed":162.216812,"Velocity":{"x":-43.5487862,"y":5.33301176E-15,"z":-11.5726976}},{"Timestamp":"00:00:03.6000000","Position":{"x":922.689,"y":40.0199776,"z":382.2159},"Rotation":{"x":0.00164302392,"y":-0.797061145,"z":-0.000343889,"w":0.6038963},"PitchYawRoll":{"x":0.00143623818,"y":-1.84482753,"z":-0.0030345323},"Speed":162.216812,"Velocity":{"x":-43.40232,"y":5.315076E-15,"z":-12.1104307}},{"Timestamp":"00:00:03.7000000","Position":{"x":918.3201,"y":40.0193558,"z":380.9809},"Rotation":{"x":0.00110997469,"y":-0.79842037,"z":-0.00072722527,"w":0.602098942},"PitchYawRoll":{"x":0.000175366848,"y":-1.84933627,"z":-0.002648179},"Speed":165.3284,"Velocity":{"x":-44.23485,"y":-5.41702769E-15,"z":-12.3427286}},{"Timestamp":"00:00:03.8000000","Position":{"x":913.8525,"y":40.01773,"z":379.700165},"Rotation":{"x":-0.0008810539,"y":-0.799081862,"z":-0.00199195254,"w":0.6012182},"PitchYawRoll":{"x":-0.00424289238,"y":-1.85154152,"z":-0.0009871281},"Speed":169.175034,"Velocity":{"x":-45.2501945,"y":-1.11958027,"z":-12.6299019}},{"Timestamp":"00:00:03.9000000","Position":{"x":909.2849,"y":40.01836,"z":378.378876},"Rotation":{"x":-0.00180184084,"y":-0.79971385,"z":-0.002031869,"w":0.6003752},"PitchYawRoll":{"x":-0.00541341538,"y":-1.85364556,"z":0.000442146731},"Speed":173.111145,"Velocity":{"x":-46.1396751,"y":1.14158773,"z":-13.4956255}},{"Timestamp":"00:00:04","Position":{"x":904.6209,"y":40.019577,"z":377.0075},"Rotation":{"x":-0.00049967115,"y":-0.8017845,"z":-0.00142214249,"w":0.597611368},"PitchYawRoll":{"x":-0.00287772715,"y":-1.860555,"z":-0.00089852},"Speed":176.961777,"Velocity":{"x":-47.1804276,"y":-5.777745E-15,"z":-13.7958193}},{"Timestamp":"00:00:04.1000000","Position":{"x":899.8595,"y":40.01926,"z":375.579865},"Rotation":{"x":0.000962277642,"y":-0.8029287,"z":-0.00130869914,"w":0.596072853},"PitchYawRoll":{"x":-0.0009544137,"y":-1.86438978,"z":-0.00310544576},"Speed":180.898087,"Velocity":{"x":-48.2151451,"y":-1.19293892,"z":-14.1026907}},{"Timestamp":"00:00:04.2000000","Position":{"x":894.9962,"y":40.0176468,"z":374.106445},"Rotation":{"x":0.000577756669,"y":-0.8034714,"z":-0.00146365189,"w":0.595341265},"PitchYawRoll":{"x":-0.00166408671,"y":-1.86621237,"z":-0.00267116982},"Speed":184.921936,"Velocity":{"x":-49.287632,"y":-1.21947443,"z":-14.4163876}},{"Timestamp":"00:00:04.3000000","Position":{"x":890.018066,"y":40.151825,"z":372.599548},"Rotation":{"x":-0.0248499047,"y":-0.8034214,"z":-0.01410457,"w":0.594724834},"PitchYawRoll":{"x":-0.0522593223,"y":-1.86653638,"z":0.0231552813},"Speed":188.280685,"Velocity":{"x":-50.13678,"y":2.48248768,"z":-14.6782322}},{"Timestamp":"00:00:04.4000000","Position":{"x":884.9822,"y":40.72311,"z":371.035736},"Rotation":{"x":-0.06782134,"y":-0.804228842,"z":-0.0500906743,"w":0.5883087},"PitchYawRoll":{"x":-0.161268666,"y":-1.87440145,"z":0.05017124},"Speed":190.36319,"Velocity":{"x":-49.8170357,"y":7.448705,"z":-16.0914}},{"Timestamp":"00:00:04.5000000","Position":{"x":880.0432,"y":41.757267,"z":369.302551},"Rotation":{"x":-0.100516036,"y":-0.8171944,"z":-0.07349039,"w":0.5627513},"PitchYawRoll":{"x":-0.2362133,"y":-1.925778,"z":0.0816593841},"Speed":191.700424,"Velocity":{"x":-48.3434448,"y":12.20874,"z":-18.6931324}},{"Timestamp":"00:00:04.6000000","Position":{"x":875.29895,"y":43.12407,"z":367.2323},"Rotation":{"x":-0.131620511,"y":-0.837174058,"z":-0.08301865,"w":0.52433157},"PitchYawRoll":{"x":-0.283297271,"y":-2.00341272,"z":0.133718088},"Speed":192.276382,"Velocity":{"x":-46.09428,"y":14.0993633,"z":-23.00358}},{"Timestamp":"00:00:04.7000000","Position":{"x":870.8394,"y":44.75022,"z":364.725739},"Rotation":{"x":-0.16491127,"y":-0.855808139,"z":-0.09593736,"w":0.480825037},"PitchYawRoll":{"x":-0.335016131,"y":-2.08539939,"z":0.191168919},"Speed":192.46875,"Velocity":{"x":-42.94293,"y":16.7080841,"z":-27.1126385}},{"Timestamp":"00:00:04.8000000","Position":{"x":866.693,"y":46.6132469,"z":361.866943},"Rotation":{"x":-0.203819454,"y":-0.860601544,"z":-0.109084673,"w":0.4537876},"PitchYawRoll":{"x":-0.395369649,"y":-2.11985683,"z":0.254552275},"Speed":192.276382,"Velocity":{"x":-39.95422,"y":19.067297,"z":-29.8787212}},{"Timestamp":"00:00:04.9000000","Position":{"x":862.792542,"y":48.6468163,"z":358.829285},"Rotation":{"x":-0.216974109,"y":-0.861101031,"z":-0.109097578,"w":0.446682185},"PitchYawRoll":{"x":-0.408437848,"y":-2.12622571,"z":0.2798478},"Speed":192.0842,"Velocity":{"x":-39.0987663,"y":19.86094,"z":-30.3935757}},{"Timestamp":"00:00:05","Position":{"x":858.9355,"y":50.4974556,"z":355.7533},"Rotation":{"x":-0.200967237,"y":-0.866317451,"z":-0.0894877,"w":0.448439777},"PitchYawRoll":{"x":-0.355456442,"y":-2.137259,"z":0.2712575},"Speed":188.469055,"Velocity":{"x":-38.93997,"y":17.4141941,"z":-30.3514538}},{"Timestamp":"00:00:05.1000000","Position":{"x":855.088867,"y":52.0941238,"z":352.686035},"Rotation":{"x":-0.185278192,"y":-0.870830536,"z":-0.07014075,"w":0.449895978},"PitchYawRoll":{"x":-0.303777426,"y":-2.1474483,"z":0.262586981},"Speed":185.106964,"Velocity":{"x":-38.6977654,"y":15.0563917,"z":-30.3259048}},{"Timestamp":"00:00:05.2000000","Position":{"x":851.253052,"y":53.4375229,"z":349.627716},"Rotation":{"x":-0.169938534,"y":-0.874673367,"z":-0.05118541,"w":0.451051533},"PitchYawRoll":{"x":-0.2535908,"y":-2.156838,"z":0.253823638},"Speed":182.351074,"Velocity":{"x":-38.4549751,"y":12.8110533,"z":-30.37805}},{"Timestamp":"00:00:05.3000000","Position":{"x":847.428,"y":54.5283,"z":346.578369},"Rotation":{"x":-0.15514493,"y":-0.8778472,"z":-0.0324927643,"w":0.451949775},"PitchYawRoll":{"x":-0.204808533,"y":-2.16534472,"z":0.245474771},"Speed":179.815948,"Velocity":{"x":-38.3904457,"y":9.695191,"z":-30.4477768}},{"Timestamp":"00:00:05.4000000","Position":{"x":843.613464,"y":55.3671379,"z":343.53775},"Rotation":{"x":-0.1406758,"y":-0.8804595,"z":-0.014191919,"w":0.452548355},"PitchYawRoll":{"x":-0.157348022,"y":-2.1732583,"z":0.237088546},"Speed":177.848816,"Velocity":{"x":-38.3982239,"y":7.69961548,"z":-30.114687}},{"Timestamp":"00:00:05.5000000","Position":{"x":839.809448,"y":55.9546776,"z":340.506042},"Rotation":{"x":-0.12663278,"y":-0.882497549,"z":0.00371829839,"w":0.452933043},"PitchYawRoll":{"x":-0.111274667,"y":-2.18042326,"z":0.2288673},"Speed":176.255356,"Velocity":{"x":-38.1459541,"y":4.74228,"z":-30.3226185}},{"Timestamp":"00:00:05.6000000","Position":{"x":836.015564,"y":56.2914162,"z":337.483032},"Rotation":{"x":-0.113380946,"y":-0.88398993,"z":0.0210241936,"w":0.453061253},"PitchYawRoll":{"x":-0.0672564358,"y":-2.18689275,"z":0.221307814},"Speed":175.025879,"Velocity":{"x":-38.0664063,"y":2.83013749,"z":-30.1111012}},{"Timestamp":"00:00:05.7000000","Position":{"x":832.230957,"y":56.3774872,"z":334.468475},"Rotation":{"x":-0.101708032,"y":-0.8849491,"z":0.0370442048,"w":0.452933043},"PitchYawRoll":{"x":-0.0272002332,"y":-2.19253922,"z":0.215227768},"Speed":174.501587,"Velocity":{"x":-38.04548,"y":-0.941321135,"z":-30.0209026}},{"Timestamp":"00:00:05.8000000","Position":{"x":828.343262,"y":56.2258644,"z":331.543518},"Rotation":{"x":-0.0851131454,"y":-0.8792627,"z":0.0491312444,"w":0.46608907},"PitchYawRoll":{"x":0.00719682,"y":-2.167444,"z":0.19673942},"Speed":177.848816,"Velocity":{"x":-40.8361855,"y":-3.03606367,"z":-27.636755}},{"Timestamp":"00:00:05.9000000","Position":{"x":824.199646,"y":56.0445633,"z":328.779755},"Rotation":{"x":-0.0186766144,"y":-0.8637155,"z":0.0123010231,"w":0.503483236},"PitchYawRoll":{"x":0.00244488567,"y":-2.08610463,"z":0.04466413},"Speed":181.260254,"Velocity":{"x":-43.95981,"y":-2.17663932,"z":-24.45255}},{"Timestamp":"00:00:06","Position":{"x":819.7062,"y":56.0326576,"z":326.4025},"Rotation":{"x":0.0135968672,"y":-0.8365997,"z":-0.009667065,"w":0.5475606},"PitchYawRoll":{"x":-0.0012854255,"y":-1.98253953,"z":-0.0333430544},"Speed":184.737122,"Velocity":{"x":-46.8305626,"y":-1.15868163,"z":-20.9493256}},{"Timestamp":"00:00:06.1000000","Position":{"x":814.8714,"y":56.02897,"z":324.546631},"Rotation":{"x":-0.011532235,"y":-0.8045061,"z":0.006248574,"w":0.593799531},"PitchYawRoll":{"x":-0.003642877,"y":-1.86987269,"z":0.02597923},"Speed":188.280685,"Velocity":{"x":-49.8045425,"y":-1.2322638,"z":-15.9153652}},{"Timestamp":"00:00:06.2000000","Position":{"x":809.7849,"y":56.0345154,"z":323.1386},"Rotation":{"x":-0.0140877,"y":-0.7794141,"z":0.0100530712,"w":0.62627},"PitchYawRoll":{"x":-0.00197557779,"y":-1.78779888,"z":0.0345590562},"Speed":192.0842,"Velocity":{"x":-52.0239372,"y":-1.287176,"z":-11.7810555}},{"Timestamp":"00:00:06.3000000","Position":{"x":804.5042,"y":56.0312233,"z":322.077454},"Rotation":{"x":-0.01224918,"y":-0.7626788,"z":0.00855687,"w":0.646604836},"PitchYawRoll":{"x":-0.00278971018,"y":-1.73511147,"z":0.0297545977},"Speed":195.964554,"Velocity":{"x":-53.7160149,"y":-1.32904148,"z":-8.714884}},{"Timestamp":"00:00:06.4000000","Position":{"x":799.07196,"y":56.0182343,"z":321.254822},"Rotation":{"x":-0.006427971,"y":-0.749078035,"z":0.00337564712,"w":0.662442},"PitchYawRoll":{"x":-0.00345942122,"y":-1.6933738,"z":0.0141029125},"Speed":199.7235,"Velocity":{"x":-55.03809,"y":-1.36175227,"z":-6.84439325}},{"Timestamp":"00:00:06.5000000","Position":{"x":793.515869,"y":56.00912,"z":320.6076},"Rotation":{"x":-0.00238285842,"y":-0.7418887,"z":0.000177825568,"w":0.6705188},"PitchYawRoll":{"x":-0.00293167424,"y":-1.67176628,"z":0.00377411116},"Speed":202.741913,"Velocity":{"x":-56.0245857,"y":-1.38616014,"z":-5.56337452}},{"Timestamp":"00:00:06.6000000","Position":{"x":787.8753,"y":56.012722,"z":320.097473},"Rotation":{"x":-0.00333856465,"y":-0.733077645,"z":0.00151114713,"w":0.6801351},"PitchYawRoll":{"x":-0.00232583168,"y":-1.64567828,"z":0.00695047854},"Speed":205.189468,"Velocity":{"x":-56.8707161,"y":1.40709507,"z":-3.52258825}},{"Timestamp":"00:00:06.7000000","Position":{"x":782.1535,"y":56.02084,"z":319.7473},"Rotation":{"x":-0.00723055424,"y":-0.721651554,"z":0.005051176,"w":0.692200243},"PitchYawRoll":{"x":-0.00272002118,"y":-1.61242759,"z":0.0174296144},"Speed":207.459015,"Velocity":{"x":-57.57022,"y":1.42440224,"z":-2.13780236}},{"Timestamp":"00:00:06.8000000","Position":{"x":776.355835,"y":56.0234,"z":319.5418},"Rotation":{"x":-0.008403431,"y":-0.71546334,"z":0.006071335,"w":0.698573351},"PitchYawRoll":{"x":-0.003053837,"y":-1.59465289,"z":0.0205086768},"Speed":209.963531,"Velocity":{"x":-58.28752,"y":-1.44214976,"z":-1.44259107}},{"Timestamp":"00:00:06.9000000","Position":{"x":770.487061,"y":56.01628,"z":319.414},"Rotation":{"x":-0.00474708248,"y":-0.712397456,"z":0.002288187,"w":0.7017564},"PitchYawRoll":{"x":-0.00340257,"y":-1.58582842,"z":0.009975284},"Speed":212.49826,"Velocity":{"x":-59.0047264,"y":-1.45989478,"z":-0.730059}},{"Timestamp":"00:00:07","Position":{"x":764.5491,"y":56.01345,"z":319.327545},"Rotation":{"x":3.40777369E-05,"y":-0.710865736,"z":-0.00170389016,"w":0.7033257},"PitchYawRoll":{"x":-0.002374548,"y":-1.5814625,"z":-0.00244523119},"Speed":215.0636,"Velocity":{"x":-59.7216148,"y":1.477632,"z":0.0}},{"Timestamp":"00:00:07.1000000","Position":{"x":758.5412,"y":56.0200768,"z":319.266083},"Rotation":{"x":0.00207656273,"y":-0.7101185,"z":-0.00241699582,"w":0.704075038},"PitchYawRoll":{"x":-0.0005086051,"y":-1.57934475,"z":-0.006352747},"Speed":217.442368,"Velocity":{"x":-60.38218,"y":1.49397564,"z":0.0}},{"Timestamp":"00:00:07.2000000","Position":{"x":752.462769,"y":56.0250664,"z":319.221069},"Rotation":{"x":0.000102039325,"y":-0.709517539,"z":-0.0006462492,"w":0.7046875},"PitchYawRoll":{"x":-0.0007732391,"y":-1.57762754,"z":-0.001055605},"Speed":220.0674,"Velocity":{"x":-61.1298332,"y":7.485998E-15,"z":0.0}},{"Timestamp":"00:00:07.3000000","Position":{"x":746.314636,"y":56.0229836,"z":319.202667},"Rotation":{"x":-0.00301588955,"y":-0.7068701,"z":0.001423235,"w":0.707335532},"PitchYawRoll":{"x":-0.00225445349,"y":-1.570131,"z":0.00627713464},"Speed":222.5015,"Velocity":{"x":-61.7870636,"y":-1.5287354,"z":0.0}},{"Timestamp":"00:00:07.4000000","Position":{"x":740.0971,"y":56.019516,"z":319.216675},"Rotation":{"x":-0.00327939959,"y":-0.705238938,"z":0.00165661285,"w":0.708960235},"PitchYawRoll":{"x":-0.00231337035,"y":-1.56552553,"z":0.00697452249},"Speed":224.962524,"Velocity":{"x":-62.48959,"y":-7.652515E-15,"z":0.0}},{"Timestamp":"00:00:07.5000000","Position":{"x":733.756958,"y":56.0183945,"z":319.251923},"Rotation":{"x":-0.001654695,"y":-0.7044301,"z":-0.0006753866,"w":0.709771156},"PitchYawRoll":{"x":-0.003300444,"y":-1.56324065,"z":0.00137249462},"Speed":234.612183,"Velocity":{"x":-65.150116,"y":1.611944,"z":0.0}},{"Timestamp":"00:00:07.6000000","Position":{"x":727.060242,"y":56.0217743,"z":319.303345},"Rotation":{"x":-0.00286880857,"y":-0.7040395,"z":-0.00421889825,"w":0.7101425},"PitchYawRoll":{"x":-0.0100152548,"y":-1.562175,"z":-0.00195252988},"Speed":247.382034,"Velocity":{"x":-68.6962051,"y":1.6996814,"z":0.0}},{"Timestamp":"00:00:07.7000000","Position":{"x":720.017944,"y":56.0250359,"z":319.365631},"Rotation":{"x":-0.004082603,"y":-0.703823447,"z":-0.005094936,"w":0.710345},"PitchYawRoll":{"x":-0.0129723623,"y":-1.561583,"z":-0.00149146176},"Speed":260.065582,"Velocity":{"x":-72.21834,"y":-1.7868259,"z":0.0}},{"Timestamp":"00:00:07.8000000","Position":{"x":712.59,"y":56.0230064,"z":319.4362},"Rotation":{"x":-0.00394632947,"y":-0.703590155,"z":-0.004452352,"w":0.7105811},"PitchYawRoll":{"x":-0.0118739186,"y":-1.560914,"z":-0.0007743175},"Speed":275.044739,"Velocity":{"x":-76.3779449,"y":-1.889743,"z":0.0}},{"Timestamp":"00:00:07.9000000","Position":{"x":704.746,"y":56.0201874,"z":319.5336},"Rotation":{"x":-0.003800546,"y":-0.7015847,"z":-0.00329608913,"w":0.712568343},"PitchYawRoll":{"x":-0.01004144,"y":-1.55525959,"z":0.0006354324},"Speed":290.01535,"Velocity":{"x":-80.55366,"y":-9.86465243E-15,"z":0.996376753}},{"Timestamp":"00:00:08","Position":{"x":696.4733,"y":56.27863,"z":319.676025},"Rotation":{"x":-0.0343868732,"y":-0.6992555,"z":-0.0301233884,"w":0.713408649},"PitchYawRoll":{"x":-0.09131974,"y":-1.55052614,"z":0.00510987267},"Speed":303.667664,"Velocity":{"x":-84.1135254,"y":6.25362062,"z":1.0432806}},{"Timestamp":"00:00:08.1000000","Position":{"x":687.9493,"y":57.7812042,"z":319.847443},"Rotation":{"x":-0.0885910243,"y":-0.693875,"z":-0.0884583,"w":0.7091292},"PitchYawRoll":{"x":-0.251032025,"y":-1.54936945,"z":-0.002514535},"Speed":315.744659,"Velocity":{"x":-85.03053,"y":21.4737644,"z":1.08477235}},{"Timestamp":"00:00:08.2000000","Position":{"x":679.436,"y":60.49405,"z":320.039368},"Rotation":{"x":-0.131645,"y":-0.6867156,"z":-0.132930428,"w":0.7024391},"PitchYawRoll":{"x":-0.376343668,"y":-1.549292,"z":-0.00594576029},"Speed":319.237,"Velocity":{"x":-82.63577,"y":32.151638,"z":1.09677064}},{"Timestamp":"00:00:08.3000000","Position":{"x":671.573364,"y":64.25583,"z":320.2343},"Rotation":{"x":-0.177163884,"y":-0.6762255,"z":-0.177674383,"w":0.6926499},"PitchYawRoll":{"x":-0.507199645,"y":-1.54849219,"z":-0.00652686739},"Speed":304.275574,"Velocity":{"x":-74.3806152,"y":40.1276665,"z":1.04536915}},{"Timestamp":"00:00:08.4000000","Position":{"x":664.1196,"y":68.11212,"z":320.427551},"Rotation":{"x":-0.1792692,"y":-0.675536,"z":-0.17710641,"w":0.692926466},"PitchYawRoll":{"x":-0.509483933,"y":-1.54622483,"z":-0.00323786284},"Speed":299.4459,"Velocity":{"x":-74.15438,"y":37.66809,"z":1.02877641}},{"Timestamp":"00:00:08.5000000","Position":{"x":656.6867,"y":71.70442,"z":320.6203},"Rotation":{"x":-0.180794179,"y":-0.6750135,"z":-0.176329553,"w":0.6932374},"PitchYawRoll":{"x":-0.510617733,"y":-1.54426384,"z":-0.000399472949},"Speed":294.692932,"Velocity":{"x":-73.87194,"y":35.2538033,"z":1.012447}},{"Timestamp":"00:00:08.6000000","Position":{"x":649.276062,"y":75.0362854,"z":320.811646},"Rotation":{"x":-0.18213366,"y":-0.6745769,"z":-0.17566976,"w":0.69347924},"PitchYawRoll":{"x":-0.511652052,"y":-1.54262018,"z":0.00207965029},"Speed":290.01535,"Velocity":{"x":-73.5353,"y":32.88544,"z":0.996376753}},{"Timestamp":"00:00:08.7000000","Position":{"x":641.887634,"y":78.10853,"z":321.0024},"Rotation":{"x":-0.183340117,"y":-0.6741628,"z":-0.175185755,"w":0.6936864},"PitchYawRoll":{"x":-0.51274693,"y":-1.54116285,"z":0.004154227},"Speed":285.6976,"Velocity":{"x":-73.21963,"y":30.5941544,"z":0.981542647}},{"Timestamp":"00:00:08.8000000","Position":{"x":634.5213,"y":80.921936,"z":321.192841},"Rotation":{"x":-0.184347361,"y":-0.673783,"z":-0.1747689,"w":0.6938936},"PitchYawRoll":{"x":-0.513646,"y":-1.5398463,"z":0.00587823242},"Speed":281.725677,"Velocity":{"x":-72.92581,"y":28.37372,"z":0.9678967}},{"Timestamp":"00:00:08.9000000","Position":{"x":627.176941,"y":83.4772644,"z":321.382355},"Rotation":{"x":-0.1853019,"y":-0.6734654,"z":-0.174435243,"w":0.694031656},"PitchYawRoll":{"x":-0.5145885,"y":-1.53875649,"z":0.00746173365},"Speed":278.086945,"Velocity":{"x":-73.2809,"y":24.4131088,"z":0.9553955}},{"Timestamp":"00:00:09","Position":{"x":619.854553,"y":85.7753,"z":321.5715},"Rotation":{"x":-0.186122343,"y":-0.6731658,"z":-0.174168646,"w":0.6941697},"PitchYawRoll":{"x":-0.5154296,"y":-1.53776288,"z":0.00877731},"Speed":274.4952,"Velocity":{"x":-72.9083252,"y":22.30127,"z":0.943055749}},{"Timestamp":"00:00:09.1000000","Position":{"x":612.554138,"y":87.81682,"z":321.7601},"Rotation":{"x":-0.1868088,"y":-0.6728849,"z":-0.173969045,"w":0.6943077},"PitchYawRoll":{"x":-0.5161688,"y":-1.53686678,"z":0.009825695},"Speed":271.220947,"Velocity":{"x":-72.545,"y":20.2420311,"z":1.86347091}},{"Timestamp":"00:00:09.2000000","Position":{"x":605.2757,"y":89.60258,"z":321.9479},"Rotation":{"x":-0.187501281,"y":-0.672626257,"z":-0.173811018,"w":0.6944112},"PitchYawRoll":{"x":-0.51697737,"y":-1.53606,"z":0.01084414},"Speed":268.253876,"Velocity":{"x":-72.22462,"y":18.2397346,"z":1.843085}},{"Timestamp":"00:00:09.3000000","Position":{"x":598.019043,"y":91.13336,"z":322.134552},"Rotation":{"x":-0.188068688,"y":-0.672418058,"z":-0.173727989,"w":0.6944802},"PitchYawRoll":{"x":-0.5177071,"y":-1.53544152,"z":0.0116205346},"Speed":265.5847,"Velocity":{"x":-72.31152,"y":14.4999132,"z":1.824746}},{"Timestamp":"00:00:09.4000000","Position":{"x":590.7841,"y":92.40996,"z":322.3204},"Rotation":{"x":-0.188571438,"y":-0.6722274,"z":-0.173644975,"w":0.694549143},"PitchYawRoll":{"x":-0.5183409,"y":-1.53487039,"z":0.0123161431},"Speed":263.20517,"Velocity":{"x":-71.9971542,"y":12.5930443,"z":1.808397}},{"Timestamp":"00:00:09.5000000","Position":{"x":583.570862,"y":93.43305,"z":322.5058},"Rotation":{"x":-0.189071745,"y":-0.672028363,"z":-0.173595443,"w":0.694618165},"PitchYawRoll":{"x":-0.5190196,"y":-1.53430021,"z":0.0129584158},"Speed":261.107941,"Velocity":{"x":-71.95389,"y":8.94526,"z":1.79398763}},{"Timestamp":"00:00:09.6000000","Position":{"x":576.3792,"y":94.20344,"z":322.690735},"Rotation":{"x":-0.189440757,"y":-0.6718573,"z":-0.173579365,"w":0.6946871},"PitchYawRoll":{"x":-0.5195502,"y":-1.53382862,"z":0.0133880088},"Speed":259.545959,"Velocity":{"x":-71.7215042,"y":7.11993647,"z":1.7832557}},{"Timestamp":"00:00:09.7000000","Position":{"x":569.2091,"y":94.72189,"z":322.8749},"Rotation":{"x":-0.189818442,"y":-0.6717171,"z":-0.173571333,"w":0.6947216},"PitchYawRoll":{"x":-0.520104945,"y":-1.53344584,"z":0.0138415294},"Speed":257.993378,"Velocity":{"x":-71.44571,"y":5.311802,"z":1.77258837}},{"Timestamp":"00:00:09.8000000","Position":{"x":562.0605,"y":94.98915,"z":323.058746},"Rotation":{"x":-0.190193743,"y":-0.6715687,"z":-0.173596755,"w":0.6947561},"PitchYawRoll":{"x":-0.5207043,"y":-1.53306425,"z":0.0142420018},"Speed":256.96344,"Velocity":{"x":-71.33507,"y":1.76497209,"z":1.76551223}},{"Timestamp":"00:00:09.9000000","Position":{"x":554.9333,"y":95.00597,"z":323.241852},"Rotation":{"x":-0.190504566,"y":-0.671438336,"z":-0.173622176,"w":0.694790542},"PitchYawRoll":{"x":-0.521207333,"y":-1.53273129,"z":0.01456256},"Speed":256.1937,"Velocity":{"x":-71.121376,"y":-1.75968492,"z":1.76022351}},{"Timestamp":"00:00:10","Position":{"x":547.827454,"y":94.7731,"z":323.424469},"Rotation":{"x":-0.190748662,"y":-0.6713181,"z":-0.173681051,"w":0.694825},"PitchYawRoll":{"x":-0.5216583,"y":-1.532449,"z":0.0147507293},"Speed":255.681839,"Velocity":{"x":-70.80559,"y":-5.26421,"z":1.75670671}},{"Timestamp":"00:00:10.1000000","Position":{"x":540.742859,"y":94.29129,"z":323.606659},"Rotation":{"x":-0.190994978,"y":-0.6712058,"z":-0.173706457,"w":0.6948595},"PitchYawRoll":{"x":-0.5220648,"y":-1.53216469,"z":0.0149912769},"Speed":255.42627,"Velocity":{"x":-70.58309,"y":-7.006924,"z":1.75495076}},{"Timestamp":"00:00:10.2000000","Position":{"x":533.679565,"y":93.56129,"z":323.7881},"Rotation":{"x":-0.191247821,"y":-0.671116531,"z":-0.173773363,"w":0.6948595},"PitchYawRoll":{"x":-0.52254,"y":-1.53197122,"z":0.0152035877},"Speed":255.681839,"Velocity":{"x":-70.45862,"y":-8.759369,"z":1.75670671}},{"Timestamp":"00:00:10.3000000","Position":{"x":526.6374,"y":92.583786,"z":323.9692},"Rotation":{"x":-0.19142741,"y":-0.671014369,"z":-0.173832223,"w":0.694893956},"PitchYawRoll":{"x":-0.5228944,"y":-1.53173769,"z":0.0153117608},"Speed":256.1937,"Velocity":{"x":-70.07923,"y":-12.2575808,"z":1.76022351}},{"Timestamp":"00:00:10.4000000","Position":{"x":519.616333,"y":91.35961,"z":324.149567},"Rotation":{"x":-0.19161582,"y":-0.67094326,"z":-0.173899114,"w":0.694893956},"PitchYawRoll":{"x":-0.523273,"y":-1.53159308,"z":0.0154444128},"Speed":256.96344,"Velocity":{"x":-69.96419,"y":-14.0292263,"z":1.76551223}},{"Timestamp":"00:00:10.5000000","Position":{"x":512.6163,"y":89.88947,"z":324.3295},"Rotation":{"x":-0.191804215,"y":-0.6708721,"z":-0.17396602,"w":0.694893956},"PitchYawRoll":{"x":-0.5236516,"y":-1.53144848,"z":0.0155769484},"Speed":257.993378,"Velocity":{"x":-69.46208,"y":-17.542078,"z":1.77258837}},{"Timestamp":"00:00:10.6000000","Position":{"x":505.637177,"y":88.1740952,"z":324.508942},"Rotation":{"x":-0.191983685,"y":-0.670769751,"z":-0.17402485,"w":0.694928467},"PitchYawRoll":{"x":-0.524006,"y":-1.53121459,"z":0.0156846959},"Speed":259.545959,"Velocity":{"x":-69.42222,"y":-19.37069,"z":1.7832557}},{"Timestamp":"00:00:10.7000000","Position":{"x":498.679016,"y":86.21422,"z":324.687683},"Rotation":{"x":-0.1921077,"y":-0.6707169,"z":-0.174091741,"w":0.694928467},"PitchYawRoll":{"x":-0.524288,"y":-1.53111911,"z":0.0157378},"Speed":261.107941,"Velocity":{"x":-69.35255,"y":-21.213625,"z":0.8970624}},{"Timestamp":"00:00:10.8000000","Position":{"x":491.7417,"y":84.01057,"z":324.86615},"Rotation":{"x":-0.192231715,"y":-0.670664,"z":-0.174158633,"w":0.694928467},"PitchYawRoll":{"x":-0.52457,"y":-1.53102374,"z":0.01579086},"Speed":262.9421,"Velocity":{"x":-68.6978,"y":-24.7903347,"z":0.9033639}},{"Timestamp":"00:00:10.9000000","Position":{"x":484.8251,"y":81.5638962,"z":325.043762},"Rotation":{"x":-0.19242,"y":-0.6705926,"z":-0.174225524,"w":0.694928467},"PitchYawRoll":{"x":-0.5249486,"y":-1.53087866,"z":0.015922986},"Speed":265.319244,"Velocity":{"x":-68.67894,"y":-26.7213631,"z":0.9115308}},{"Timestamp":"00:00:11","Position":{"x":478.041046,"y":80.2193451,"z":325.229034},"Rotation":{"x":-0.06349931,"y":-0.692664444,"z":-0.06070694,"w":0.715889931},"PitchYawRoll":{"x":-0.17592223,"y":-1.537729,"z":0.00104845408},"Speed":249.618515,"Velocity":{"x":-68.55517,"y":-10.2504549,"z":1.7150476}},{"Timestamp":"00:00:11.1000000","Position":{"x":471.167023,"y":80.32687,"z":325.4528},"Rotation":{"x":0.0620944947,"y":-0.6934262,"z":0.0636552349,"w":0.715019166},"PitchYawRoll":{"x":0.178018823,"y":-1.54057515,"z":0.00491354754},"Speed":259.805634,"Velocity":{"x":-72.1240845,"y":1.7844938,"z":1.78504}},{"Timestamp":"00:00:11.2000000","Position":{"x":463.788727,"y":80.41343,"z":325.6995},"Rotation":{"x":0.07896317,"y":-0.6905506,"z":0.08011915,"w":0.7144827},"PitchYawRoll":{"x":0.2253952,"y":-1.537348,"z":0.005431391},"Speed":273.672974,"Velocity":{"x":-75.97376,"y":-1.87974262,"z":1.88031793}},{"Timestamp":"00:00:11.3000000","Position":{"x":455.94754,"y":80.26379,"z":325.973816},"Rotation":{"x":0.05023969,"y":-0.6923709,"z":0.051275108,"w":0.717961967},"PitchYawRoll":{"x":0.143637747,"y":-1.53480148,"z":0.00405816874},"Speed":289.435883,"Velocity":{"x":-80.27592,"y":-3.974806,"z":1.98861969}},{"Timestamp":"00:00:11.4000000","Position":{"x":447.632568,"y":80.0383148,"z":326.2785},"Rotation":{"x":-0.0113427173,"y":-0.693810463,"z":-0.007651164,"w":0.7200276},"PitchYawRoll":{"x":-0.02695462,"y":-1.5336504,"z":0.00472131046},"Speed":304.580017,"Velocity":{"x":-84.5538,"y":-2.09202981,"z":2.09267}},{"Timestamp":"00:00:11.5000000","Position":{"x":438.9706,"y":80.03988,"z":326.601318},"Rotation":{"x":-0.0117861545,"y":-0.6924982,"z":-0.00687304744,"w":0.7212906},"PitchYawRoll":{"x":-0.0265252851,"y":-1.52998614,"z":0.00640889676},"Speed":319.5564,"Velocity":{"x":-88.67743,"y":-2.19405675,"z":3.29293227}},{"Timestamp":"00:00:11.6000000","Position":{"x":429.910339,"y":80.0133,"z":327.014923},"Rotation":{"x":0.0005607833,"y":-0.688118,"z":0.00286990823,"w":0.725593},"PitchYawRoll":{"x":0.004763517,"y":-1.51780045,"z":0.00339300674},"Speed":334.599365,"Velocity":{"x":-92.80214,"y":2.29611039,"z":4.59644}},{"Timestamp":"00:00:11.7000000","Position":{"x":420.437836,"y":80.0216141,"z":327.541077},"Rotation":{"x":-0.00167631533,"y":-0.685648441,"z":0.0003615586,"w":0.727930844},"PitchYawRoll":{"x":-0.001944688,"y":-1.51098824,"z":0.002825109},"Speed":345.134369,"Velocity":{"x":-95.72406,"y":2.36840439,"z":4.741161}},{"Timestamp":"00:00:11.8000000","Position":{"x":410.861572,"y":80.12666,"z":328.1251},"Rotation":{"x":-0.0109252837,"y":-0.6843344,"z":-0.0102374991,"w":0.7290146},"PitchYawRoll":{"x":-0.0299456026,"y":-1.507591,"z":2.65226317E-05},"Speed":344.4448,"Velocity":{"x":-95.37936,"y":4.72264242,"z":5.91325235}},{"Timestamp":"00:00:11.9000000","Position":{"x":401.3592,"y":81.4400558,"z":328.732849},"Rotation":{"x":-0.07784772,"y":-0.6790652,"z":-0.08533728,"w":0.724932849},"PitchYawRoll":{"x":-0.2308499,"y":-1.507568,"z":-0.01800121},"Speed":342.726868,"Velocity":{"x":-92.67479,"y":20.9802055,"z":5.88376045}},{"Timestamp":"00:00:12","Position":{"x":392.2241,"y":84.19172,"z":329.370331},"Rotation":{"x":-0.125230178,"y":-0.6709802,"z":-0.130951375,"w":0.718995631},"PitchYawRoll":{"x":-0.3638603,"y":-1.50546193,"z":-0.0202543736},"Speed":341.3587,"Velocity":{"x":-88.19989,"y":34.3165054,"z":5.860272}},{"Timestamp":"00:00:12.1000000","Position":{"x":383.642731,"y":88.21569,"z":330.017975},"Rotation":{"x":-0.171134025,"y":-0.660176,"z":-0.183821261,"w":0.7078775},"PitchYawRoll":{"x":-0.5066811,"y":-1.50996828,"z":-0.0342954546},"Speed":338.638733,"Velocity":{"x":-82.6288147,"y":44.57749,"z":5.813577}},{"Timestamp":"00:00:12.2000000","Position":{"x":375.375916,"y":92.5259,"z":330.6739},"Rotation":{"x":-0.171959579,"y":-0.659454763,"z":-0.184074655,"w":0.7082837},"PitchYawRoll":{"x":-0.5082518,"y":-1.50824761,"z":-0.0339615643},"Speed":333.597046,"Velocity":{"x":-82.45991,"y":41.8870354,"z":5.727024}},{"Timestamp":"00:00:12.3000000","Position":{"x":367.1325,"y":96.57167,"z":331.32785},"Rotation":{"x":-0.1724085,"y":-0.6588474,"z":-0.183876514,"w":0.708791137},"PitchYawRoll":{"x":-0.5086165,"y":-1.50649691,"z":-0.0334845558},"Speed":328.630432,"Velocity":{"x":-82.22802,"y":39.24156,"z":5.64176}},{"Timestamp":"00:00:12.4000000","Position":{"x":358.914063,"y":100.355675,"z":331.979919},"Rotation":{"x":-0.172807723,"y":-0.658310831,"z":-0.18372871,"w":0.7092306},"PitchYawRoll":{"x":-0.508982658,"y":-1.5049715,"z":-0.0330956951},"Speed":324.061646,"Velocity":{"x":-82.01716,"y":36.67858,"z":5.56332541}},{"Timestamp":"00:00:12.5000000","Position":{"x":350.72,"y":103.879707,"z":332.629974},"Rotation":{"x":-0.173146978,"y":-0.6578052,"z":-0.183654964,"w":0.709636033},"PitchYawRoll":{"x":-0.5093667,"y":-1.50358307,"z":-0.03286831},"Speed":319.5564,"Velocity":{"x":-81.74679,"y":34.15715,"z":5.48598146}},{"Timestamp":"00:00:12.6000000","Position":{"x":342.5505,"y":107.143623,"z":333.2781},"Rotation":{"x":-0.173487812,"y":-0.6573077,"z":-0.183548525,"w":0.7100412},"PitchYawRoll":{"x":-0.509707332,"y":-1.502193,"z":-0.0325900652},"Speed":315.11377,"Velocity":{"x":-81.4187546,"y":31.6781254,"z":5.409713}},{"Timestamp":"00:00:12.7000000","Position":{"x":334.405457,"y":110.14814,"z":333.924347},"Rotation":{"x":-0.173768923,"y":-0.6568412,"z":-0.18351604,"w":0.710412443},"PitchYawRoll":{"x":-0.5100655,"y":-1.50093973,"z":-0.03247268},"Speed":311.043823,"Velocity":{"x":-81.04767,"y":29.2469158,"z":6.40601254}},{"Timestamp":"00:00:12.8000000","Position":{"x":326.284821,"y":112.89402,"z":334.568634},"Rotation":{"x":-0.173995018,"y":-0.656423,"z":-0.183492333,"w":0.710749745},"PitchYawRoll":{"x":-0.5103556,"y":-1.49982059,"z":-0.0324112773},"Speed":307.3336,"Velocity":{"x":-80.77119,"y":26.908453,"z":6.3296}},{"Timestamp":"00:00:12.9000000","Position":{"x":318.1885,"y":115.382019,"z":335.211},"Rotation":{"x":-0.174166262,"y":-0.656053,"z":-0.1834774,"w":0.7110532},"PitchYawRoll":{"x":-0.5105777,"y":-1.49883544,"z":-0.0324054547},"Speed":303.971436,"Velocity":{"x":-80.5214157,"y":24.6299667,"z":6.26035547}},{"Timestamp":"00:00:13","Position":{"x":310.116425,"y":117.612938,"z":335.8514},"Rotation":{"x":-0.174343422,"y":-0.6557062,"z":-0.183503821,"w":0.7113228},"PitchYawRoll":{"x":-0.510868669,"y":-1.49794221,"z":-0.0324304476},"Speed":300.646118,"Velocity":{"x":-80.21871,"y":22.3832073,"z":6.19186974}},{"Timestamp":"00:00:13.1000000","Position":{"x":302.068542,"y":119.58754,"z":336.4899},"Rotation":{"x":-0.174520314,"y":-0.655359268,"z":-0.183530122,"w":0.711592257},"PitchYawRoll":{"x":-0.5111592,"y":-1.49704885,"z":-0.0324559137},"Speed":297.6546,"Velocity":{"x":-79.94435,"y":20.18929,"z":6.130259}},{"Timestamp":"00:00:13.2000000","Position":{"x":294.044769,"y":121.306572,"z":337.1265},"Rotation":{"x":-0.174634129,"y":-0.655029,"z":-0.183556318,"w":0.71186167},"PitchYawRoll":{"x":-0.5113551,"y":-1.49619949,"z":-0.03255833},"Speed":294.692932,"Velocity":{"x":-80.04055,"y":16.0497379,"z":6.0692625}},{"Timestamp":"00:00:13.3000000","Position":{"x":286.044983,"y":122.770828,"z":337.761169},"Rotation":{"x":-0.174756259,"y":-0.654730439,"z":-0.183591336,"w":0.7120973},"PitchYawRoll":{"x":-0.5115774,"y":-1.49544036,"z":-0.0326390937},"Speed":292.344757,"Velocity":{"x":-79.7723,"y":13.9529982,"z":6.02090168}},{"Timestamp":"00:00:13.4000000","Position":{"x":278.0692,"y":123.981071,"z":338.393951},"Rotation":{"x":-0.1748867,"y":-0.6544636,"z":-0.18363519,"w":0.712299168},"PitchYawRoll":{"x":-0.511826158,"y":-1.49477148,"z":-0.032698255},"Speed":290.01535,"Velocity":{"x":-79.454834,"y":11.8801861,"z":5.972927}},{"Timestamp":"00:00:13.5000000","Position":{"x":270.11734,"y":124.938042,"z":339.024841},"Rotation":{"x":-0.17495428,"y":-0.6542135,"z":-0.18367897,"w":0.712501049},"PitchYawRoll":{"x":-0.511980534,"y":-1.49414647,"z":-0.0328339152},"Speed":287.99234,"Velocity":{"x":-79.16825,"y":9.842145,"z":5.93126249}},{"Timestamp":"00:00:13.6000000","Position":{"x":262.18927,"y":125.642509,"z":339.653839},"Rotation":{"x":-0.175021753,"y":-0.6539633,"z":-0.183722675,"w":0.7127028},"PitchYawRoll":{"x":-0.5121346,"y":-1.49352157,"z":-0.03296969},"Speed":286.555939,"Velocity":{"x":-79.16131,"y":5.885436,"z":5.90168}},{"Timestamp":"00:00:13.7000000","Position":{"x":254.284943,"y":126.095222,"z":340.280945},"Rotation":{"x":-0.175097659,"y":-0.653744936,"z":-0.183775276,"w":0.712870955},"PitchYawRoll":{"x":-0.512315333,"y":-1.49298692,"z":-0.0330837332},"Speed":285.12674,"Velocity":{"x":-78.88724,"y":3.90604687,"z":5.872245}},{"Timestamp":"00:00:13.8000000","Position":{"x":246.404312,"y":126.296944,"z":340.9062},"Rotation":{"x":-0.1751712,"y":-0.653518,"z":-0.183860227,"w":0.713039041},"PitchYawRoll":{"x":-0.512538135,"y":-1.49245369,"z":-0.0332501},"Speed":283.988525,"Velocity":{"x":-78.644516,"y":1.94582236,"z":5.848803}},{"Timestamp":"00:00:13.9000000","Position":{"x":238.547287,"y":126.248421,"z":341.529572},"Rotation":{"x":-0.175246924,"y":-0.65329957,"z":-0.18391268,"w":0.713207066},"PitchYawRoll":{"x":-0.5127183,"y":-1.49191916,"z":-0.0333643556},"Speed":283.137817,"Velocity":{"x":-78.40893,"y":-1.9399935,"z":5.831283}},{"Timestamp":"00:00:14","Position":{"x":230.713791,"y":125.950409,"z":342.151062},"Rotation":{"x":-0.175268486,"y":-0.653129756,"z":-0.183974057,"w":0.7133414},"PitchYawRoll":{"x":-0.5128312,"y":-1.49151862,"z":-0.0335327871},"Speed":282.854858,"Velocity":{"x":-78.13888,"y":-5.809421,"z":5.82545471}},{"Timestamp":"00:00:14.1000000","Position":{"x":222.903763,"y":125.403641,"z":342.7707},"Rotation":{"x":-0.175352633,"y":-0.652943134,"z":-0.184035376,"w":0.7134758},"PitchYawRoll":{"x":-0.5130381,"y":-1.49107444,"z":-0.0336253233},"Speed":282.5721,"Velocity":{"x":-77.89334,"y":-7.732627,"z":5.819632}},{"Timestamp":"00:00:14.2000000","Position":{"x":215.117157,"y":124.608871,"z":343.388458},"Rotation":{"x":-0.1753764,"y":-0.6527818,"z":-0.184064239,"w":0.7136102},"PitchYawRoll":{"x":-0.513108432,"y":-1.49067247,"z":-0.03374159},"Speed":282.5721,"Velocity":{"x":-77.6782455,"y":-9.656909,"z":5.819632}},{"Timestamp":"00:00:14.3000000","Position":{"x":207.353851,"y":123.566849,"z":344.0044},"Rotation":{"x":-0.175397843,"y":-0.652611852,"z":-0.184125483,"w":0.713744462},"PitchYawRoll":{"x":-0.513220847,"y":-1.49027193,"z":-0.0339101627},"Speed":282.854858,"Velocity":{"x":-77.182785,"y":-13.5000648,"z":5.82545471}},{"Timestamp":"00:00:14.4000000","Position":{"x":199.6138,"y":122.27832,"z":344.6185},"Rotation":{"x":-0.175427824,"y":-0.6524738,"z":-0.184195668,"w":0.7138452},"PitchYawRoll":{"x":-0.5133602,"y":-1.48996174,"z":-0.0340568461},"Speed":283.4211,"Velocity":{"x":-76.97905,"y":-15.4358473,"z":5.837117}},{"Timestamp":"00:00:14.5000000","Position":{"x":191.896942,"y":120.744011,"z":345.230743},"Rotation":{"x":-0.175460055,"y":-0.6523443,"z":-0.184233427,"w":0.7139459},"PitchYawRoll":{"x":-0.5134573,"y":-1.48965013,"z":-0.03415132},"Speed":284.557068,"Velocity":{"x":-76.8806152,"y":-17.4046364,"z":5.86051226}},{"Timestamp":"00:00:14.6000000","Position":{"x":184.203186,"y":118.964653,"z":345.841125},"Rotation":{"x":-0.175489977,"y":-0.6522062,"z":-0.184303537,"w":0.7140466},"PitchYawRoll":{"x":-0.513596356,"y":-1.48933983,"z":-0.0342980549},"Speed":285.6976,"Velocity":{"x":-76.73292,"y":-19.37827,"z":5.88400173}},{"Timestamp":"00:00:14.7000000","Position":{"x":176.5325,"y":116.941017,"z":346.449677},"Rotation":{"x":-0.175522164,"y":-0.652076662,"z":-0.184341252,"w":0.71414727},"PitchYawRoll":{"x":-0.5136933,"y":-1.48902833,"z":-0.03439257},"Speed":287.129639,"Velocity":{"x":-76.06005,"y":-23.2653217,"z":5.913495}},{"Timestamp":"00:00:14.8000000","Position":{"x":168.884781,"y":114.673775,"z":347.056458},"Rotation":{"x":-0.17555432,"y":-0.6519471,"z":-0.184378937,"w":0.714247942},"PitchYawRoll":{"x":-0.5137901,"y":-1.4887166,"z":-0.0344871357},"Speed":288.857574,"Velocity":{"x":-75.91545,"y":-25.2907944,"z":5.94908237}},{"Timestamp":"00:00:14.9000000","Position":{"x":161.26004,"y":112.1637,"z":347.6614},"Rotation":{"x":-0.175595045,"y":-0.6518494,"z":-0.184425622,"w":0.714315},"PitchYawRoll":{"x":-0.5139139,"y":-1.48849523,"z":-0.03455981},"Speed":290.595947,"Velocity":{"x":-75.719635,"y":-27.3242378,"z":5.98488474}},{"Timestamp":"00:00:15","Position":{"x":153.658035,"y":109.411491,"z":348.264526},"Rotation":{"x":-0.175564677,"y":-0.6517366,"z":-0.184463263,"w":0.714415669},"PitchYawRoll":{"x":-0.5139166,"y":-1.48822749,"z":-0.0347300135},"Speed":292.930054,"Velocity":{"x":-75.68695,"y":-29.4480133,"z":5.028874}},{"Timestamp":"00:00:15.1000000","Position":{"x":146.078842,"y":106.417892,"z":348.865845},"Rotation":{"x":-0.175605357,"y":-0.6516389,"z":-0.184509918,"w":0.7144827},"PitchYawRoll":{"x":-0.514040351,"y":-1.48800611,"z":-0.03480275},"Speed":295.2829,"Velocity":{"x":-75.5373,"y":-31.56257,"z":5.069266}},{"Timestamp":"00:00:15.2000000","Position":{"x":138.555359,"y":104.328369,"z":349.528961},"Rotation":{"x":-0.09846344,"y":-0.6639853,"z":-0.08262955,"w":0.7366144},"PitchYawRoll":{"x":-0.25764,"y":-1.46600866,"z":0.009024448},"Speed":274.220856,"Velocity":{"x":-74.75229,"y":-13.0749474,"z":6.58672428}},{"Timestamp":"00:00:15.3000000","Position":{"x":131.29306,"y":104.387062,"z":350.4032},"Rotation":{"x":0.0806118548,"y":-0.644658864,"z":0.06927715,"w":0.75704515},"PitchYawRoll":{"x":0.2129805,"y":-1.41088438,"z":0.0009575712},"Speed":270.94986,"Velocity":{"x":-74.34531,"y":3.681156,"z":11.1298208}},{"Timestamp":"00:00:15.4000000","Position":{"x":123.910553,"y":104.56118,"z":351.821625},"Rotation":{"x":0.117123887,"y":-0.6106508,"z":0.0972984,"w":0.777123332},"PitchYawRoll":{"x":0.305615455,"y":-1.33328438,"z":0.008182217},"Speed":273.12616,"Velocity":{"x":-73.9732742,"y":1.83024657,"z":16.7515831}},{"Timestamp":"00:00:15.5000000","Position":{"x":116.551277,"y":104.550583,"z":353.882874},"Rotation":{"x":0.10605377,"y":-0.577126145,"z":0.09765309,"w":0.803829551},"PitchYawRoll":{"x":0.287321031,"y":-1.25037456,"z":0.03458697},"Speed":276.699982,"Velocity":{"x":-72.898674,"y":-1.80365872,"z":24.2932053}},{"Timestamp":"00:00:15.6000000","Position":{"x":109.288086,"y":104.349281,"z":356.6388},"Rotation":{"x":0.05628885,"y":-0.5444557,"z":0.0675122142,"w":0.834171236},"PitchYawRoll":{"x":0.168440357,"y":-1.16086566,"z":0.0513625033},"Speed":279.7605,"Velocity":{"x":-71.24022,"y":-3.52740979,"z":30.8452168}},{"Timestamp":"00:00:15.7000000","Position":{"x":102.183708,"y":104.0612,"z":360.056427},"Rotation":{"x":-0.019213818,"y":-0.5090373,"z":0.007570693,"w":0.8604967},"PitchYawRoll":{"x":-0.0253755245,"y":-1.06797063,"z":0.0325959846},"Speed":282.289673,"Velocity":{"x":-69.44536,"y":-1.7182169,"z":36.3746376}},{"Timestamp":"00:00:15.8000000","Position":{"x":95.32075,"y":104.083778,"z":363.922363},"Rotation":{"x":-0.008814688,"y":-0.4702146,"z":-0.0261342842,"w":0.882121},"PitchYawRoll":{"x":-0.0401682146,"y":-0.9802333,"z":-0.0378266349},"Speed":283.988525,"Velocity":{"x":-66.95869,"y":-1.65669155,"z":41.674263}},{"Timestamp":"00:00:15.9000000","Position":{"x":88.89243,"y":104.043251,"z":368.4937},"Rotation":{"x":-0.0005555256,"y":-0.4291972,"z":0.0139341867,"w":0.9031032},"PitchYawRoll":{"x":0.0109614581,"y":-0.8874405,"z":0.0256476887},"Speed":285.6976,"Velocity":{"x":-62.8917961,"y":-1.55606866,"z":48.3764458}},{"Timestamp":"00:00:16","Position":{"x":82.8419342,"y":104.0279,"z":373.67746},"Rotation":{"x":-0.00584265,"y":-0.3868861,"z":0.0132675888,"w":0.9220136},"PitchYawRoll":{"x":-0.000508127443,"y":-0.794585466,"z":0.0289907344},"Speed":287.704468,"Velocity":{"x":-58.21276,"y":-1.44029987,"z":54.73639}},{"Timestamp":"00:00:16.1000000","Position":{"x":77.30555,"y":104.042641,"z":379.48},"Rotation":{"x":-0.00875872653,"y":-0.3440087,"z":0.0190399252,"w":0.938732564},"PitchYawRoll":{"x":-0.00334733143,"y":-0.7024568,"z":0.04178511},"Speed":289.725464,"Velocity":{"x":-52.8914146,"y":-1.30863917,"z":60.6440735}},{"Timestamp":"00:00:16.2000000","Position":{"x":72.28862,"y":104.052345,"z":385.807},"Rotation":{"x":-0.009208425,"y":-0.3005145,"z":0.0255142264,"w":0.953391433},"PitchYawRoll":{"x":-0.00222695083,"y":-0.610635638,"z":0.05421117},"Speed":291.760681,"Velocity":{"x":-47.78426,"y":-1.182278,"z":65.44845}},{"Timestamp":"00:00:16.3000000","Position":{"x":67.8336639,"y":104.052391,"z":392.6105},"Rotation":{"x":-0.008133747,"y":-0.256602317,"z":0.02575889,"w":0.9661395},"PitchYawRoll":{"x":-0.00250073,"y":-0.519136667,"z":0.0539738424},"Speed":293.81015,"Velocity":{"x":-41.37571,"y":-1.02371764,"z":70.34086}},{"Timestamp":"00:00:16.4000000","Position":{"x":63.9877319,"y":104.044792,"z":399.841125},"Rotation":{"x":-0.006068219,"y":-0.213405862,"z":0.0218961686,"w":0.976699352},"PitchYawRoll":{"x":-0.00251069665,"y":-0.430175453,"z":0.0453775041},"Speed":295.874023,"Velocity":{"x":-35.38698,"y":-0.8755445,"z":74.17369}},{"Timestamp":"00:00:16.5000000","Position":{"x":60.7505836,"y":104.037262,"z":407.430939},"Rotation":{"x":-0.00446585938,"y":-0.177407026,"z":0.0180118661,"w":0.9839626},"PitchYawRoll":{"x":-0.00239926181,"y":-0.356719762,"z":0.0370390229},"Speed":298.250519,"Velocity":{"x":-30.03111,"y":-0.743029654,"z":77.2092361}},{"Timestamp":"00:00:16.6000000","Position":{"x":58.0843735,"y":104.034966,"z":415.3042},"Rotation":{"x":-0.003671565,"y":-0.13846536,"z":0.01673417,"w":0.990219057},"PitchYawRoll":{"x":-0.00263864454,"y":-0.2778193,"z":0.0341644026},"Speed":300.3456,"Velocity":{"x":-23.4075737,"y":-0.5791501,"z":80.07624}},{"Timestamp":"00:00:16.7000000","Position":{"x":56.04133,"y":104.040489,"z":423.423676},"Rotation":{"x":-0.00340325781,"y":-0.09842454,"z":0.0197865646,"w":0.99494195},"PitchYawRoll":{"x":-0.00287943427,"y":-0.1971505,"z":0.0400536023},"Speed":302.455383,"Velocity":{"x":-17.5355377,"y":-2.14741317E-15,"z":82.1650162}},{"Timestamp":"00:00:16.8000000","Position":{"x":54.62919,"y":104.045273,"z":431.7382},"Rotation":{"x":-0.002918728,"y":-0.060535226,"z":0.0224293116,"w":0.9979098},"PitchYawRoll":{"x":-0.0031129024,"y":-0.1211053,"z":0.0451335534},"Speed":304.580017,"Velocity":{"x":-11.4718695,"y":-0.283836961,"z":83.82372}},{"Timestamp":"00:00:16.9000000","Position":{"x":53.8632431,"y":104.044746,"z":440.1968},"Rotation":{"x":-0.001970159,"y":-0.0197599474,"z":0.0222365744,"w":0.9995555},"PitchYawRoll":{"x":-0.00306282239,"y":-0.03946409,"z":0.0445459746},"Speed":306.719543,"Velocity":{"x":-4.20829535,"y":-0.20837082,"z":85.09563}},{"Timestamp":"00:00:17","Position":{"x":53.76577,"y":104.041451,"z":448.7509},"Rotation":{"x":-0.00117452873,"y":0.0176385678,"z":0.0204527061,"w":0.9996345},"PitchYawRoll":{"x":-0.003072281,"y":0.0353491455,"z":0.0408603959},"Speed":309.183136,"Velocity":{"x":3.185064,"y":-0.07880484,"z":85.82509}},{"Timestamp":"00:00:17.1000000","Position":{"x":54.32606,"y":104.039223,"z":457.34787},"Rotation":{"x":-0.00048766195,"y":0.0568292551,"z":0.019183971,"w":0.998199463},"PitchYawRoll":{"x":-0.00315630366,"y":0.113801122,"z":0.03825276},"Speed":311.355042,"Velocity":{"x":9.607597,"y":0.0,"z":85.95222}},{"Timestamp":"00:00:17.2000000","Position":{"x":55.58343,"y":104.042076,"z":465.9307},"Rotation":{"x":0.000485737022,"y":0.0983733,"z":0.02078728,"w":0.994932353},"PitchYawRoll":{"x":-0.00312596862,"y":0.19717291,"z":0.04147133},"Speed":313.2288,"Velocity":{"x":17.1063328,"y":0.0,"z":85.3098145}},{"Timestamp":"00:00:17.3000000","Position":{"x":57.5639153,"y":104.046867,"z":474.4367},"Rotation":{"x":0.0017709363,"y":0.139396057,"z":0.0234886184,"w":0.9899565},"PitchYawRoll":{"x":-0.003045512,"y":0.279852718,"z":0.0470164642},"Speed":315.429077,"Velocity":{"x":23.5486183,"y":0.0,"z":84.39541}},{"Timestamp":"00:00:17.4000000","Position":{"x":60.2091942,"y":104.044991,"z":482.825317},"Rotation":{"x":0.00239152322,"y":0.173812941,"z":0.02235473,"w":0.984522045},"PitchYawRoll":{"x":-0.003065157,"y":0.3495585,"z":0.0448638536},"Speed":317.6448,"Velocity":{"x":29.95003,"y":0.0,"z":82.9961}},{"Timestamp":"00:00:17.5000000","Position":{"x":63.48282,"y":104.039421,"z":491.0547},"Rotation":{"x":0.00254877447,"y":0.21181345,"z":0.01914274,"w":0.9771193},"PitchYawRoll":{"x":-0.00313079078,"y":0.427001417,"z":0.038498722},"Speed":319.876129,"Velocity":{"x":36.27419,"y":0.0,"z":81.1129}},{"Timestamp":"00:00:17.6000000","Position":{"x":67.3931046,"y":104.037735,"z":499.070038},"Rotation":{"x":0.00305871,"y":0.2463389,"z":0.0181730073,"w":0.9690085},"PitchYawRoll":{"x":-0.00302765286,"y":0.4979438,"z":0.0367348157},"Speed":322.1231,"Velocity":{"x":42.48464,"y":0.0,"z":78.7495}},{"Timestamp":"00:00:17.7000000","Position":{"x":71.90561,"y":104.039818,"z":506.833954},"Rotation":{"x":0.00401578424,"y":0.28203395,"z":0.0191353187,"w":0.959205151},"PitchYawRoll":{"x":-0.00309205148,"y":0.5719996,"z":0.03898444},"Speed":324.3859,"Velocity":{"x":48.5450363,"y":0.0,"z":75.91235}},{"Timestamp":"00:00:17.8000000","Position":{"x":77.03177,"y":104.044991,"z":514.2787},"Rotation":{"x":0.005762851,"y":0.3205355,"z":0.0217334274,"w":0.9469696},"PitchYawRoll":{"x":-0.00302122673,"y":0.6528285,"z":0.0448712446},"Speed":326.338043,"Velocity":{"x":55.25799,"y":0.0,"z":71.86014}},{"Timestamp":"00:00:17.9000000","Position":{"x":82.78515,"y":104.049492,"z":521.3254},"Rotation":{"x":0.007613071,"y":0.360058755,"z":0.0238598064,"w":0.9325934},"PitchYawRoll":{"x":-0.002985802,"y":0.7369786,"z":0.05000614},"Speed":328.630432,"Velocity":{"x":61.6952057,"y":0.0,"z":67.282074}},{"Timestamp":"00:00:18","Position":{"x":89.15234,"y":104.050255,"z":527.903259},"Rotation":{"x":0.008797239,"y":0.399742573,"z":0.0238920934,"w":0.9162738},"PitchYawRoll":{"x":-0.00298387557,"y":0.8228307,"z":0.0508385561},"Speed":330.608124,"Velocity":{"x":66.9141541,"y":0.0,"z":62.8989029}},{"Timestamp":"00:00:18.1000000","Position":{"x":96.1041641,"y":104.048508,"z":533.948547},"Rotation":{"x":0.009367714,"y":0.439060658,"z":0.0226094257,"w":0.898124039},"PitchYawRoll":{"x":-0.003030702,"y":0.9094727,"z":0.0488575622},"Speed":332.597748,"Velocity":{"x":72.5363846,"y":0.0,"z":57.2194481}},{"Timestamp":"00:00:18.2000000","Position":{"x":103.60022,"y":104.046494,"z":539.4021},"Rotation":{"x":0.0102368649,"y":0.47765,"z":0.0213827752,"w":0.878230333},"PitchYawRoll":{"x":-0.002449062,"y":0.9963195,"z":0.0473549776},"Speed":334.9341,"Velocity":{"x":77.7549057,"y":0.0,"z":51.08919}},{"Timestamp":"00:00:18.3000000","Position":{"x":111.591591,"y":104.04847,"z":544.213},"Rotation":{"x":0.0114399306,"y":0.5153329,"z":0.02173322,"w":0.8566381},"PitchYawRoll":{"x":-0.00280330051,"y":1.0832237,"z":0.0490454137},"Speed":336.949738,"Velocity":{"x":82.37417,"y":0.0,"z":44.4401131}},{"Timestamp":"00:00:18.4000000","Position":{"x":120.018974,"y":104.049828,"z":548.3448},"Rotation":{"x":0.0126501173,"y":0.550807059,"z":0.0218539685,"w":0.834250569},"PitchYawRoll":{"x":-0.002971686,"y":1.16715777,"z":0.05042028},"Speed":338.977539,"Velocity":{"x":86.42542,"y":0.0,"z":37.3742371}},{"Timestamp":"00:00:18.5000000","Position":{"x":128.789413,"y":104.041687,"z":551.895142},"Rotation":{"x":0.0104533555,"y":0.5722677,"z":0.0177032519,"w":0.819809139},"PitchYawRoll":{"x":-0.00312511786,"y":1.21889615,"z":0.0410023},"Speed":344.100525,"Velocity":{"x":89.90861,"y":0.0,"z":32.44448}},{"Timestamp":"00:00:18.6000000","Position":{"x":137.961426,"y":104.026474,"z":555.1314},"Rotation":{"x":0.00357186818,"y":0.5866825,"z":0.009872849,"w":0.809748948},"PitchYawRoll":{"x":-0.00580103649,"y":1.25405061,"z":0.0201815329},"Speed":356.0011,"Velocity":{"x":94.19925,"y":0.0,"z":30.0927734}},{"Timestamp":"00:00:18.7000000","Position":{"x":147.559952,"y":104.017174,"z":558.1769},"Rotation":{"x":-0.00180322537,"y":0.597069561,"z":0.004894586,"w":0.8021725},"PitchYawRoll":{"x":-0.008738065,"y":1.27973127,"z":0.005699333},"Speed":369.419861,"Velocity":{"x":98.49238,"y":0.0,"z":28.7997189}},{"Timestamp":"00:00:18.8000000","Position":{"x":157.602,"y":104.0211,"z":561.130066},"Rotation":{"x":-0.002107533,"y":0.6022358,"z":0.006178477,"w":0.798291564},"PitchYawRoll":{"x":-0.0108071519,"y":1.2926693,"z":0.007326054},"Speed":384.111847,"Velocity":{"x":102.771996,"y":0.0,"z":28.67619}},{"Timestamp":"00:00:18.9000000","Position":{"x":168.062073,"y":104.025467,"z":564.087463},"Rotation":{"x":-0.00171064714,"y":0.6048171,"z":0.007828833,"w":0.7963241},"PitchYawRoll":{"x":-0.0121954447,"y":1.29918456,"z":0.0103995055},"Speed":398.5902,"Velocity":{"x":106.64579,"y":0.0,"z":29.757082}},{"Timestamp":"00:00:19","Position":{"x":178.903214,"y":104.023422,"z":567.069},"Rotation":{"x":-0.00148700876,"y":0.608218,"z":0.00717297,"w":0.7937362},"PitchYawRoll":{"x":-0.0110867806,"y":1.30772161,"z":0.009578188},"Speed":410.318542,"Velocity":{"x":110.154274,"y":0.0,"z":29.2725048}},{"Timestamp":"00:00:19.1000000","Position":{"x":190.073257,"y":104.01844,"z":570.0468},"Rotation":{"x":-0.000790803,"y":0.6109717,"z":0.00562364841,"w":0.791632056},"PitchYawRoll":{"x":-0.00812417548,"y":1.31463194,"z":0.007937487},"Speed":421.12674,"Velocity":{"x":113.418777,"y":0.0,"z":28.64298}},{"Timestamp":"00:00:19.2000000","Position":{"x":201.42189,"y":104.01564,"z":573.005},"Rotation":{"x":0.0006164231,"y":0.612316966,"z":0.00317020481,"w":0.7906058},"PitchYawRoll":{"x":-0.00290769758,"y":1.31799221,"z":0.005767689},"Speed":423.23764,"Velocity":{"x":113.987289,"y":0.0,"z":28.7865543}},{"Timestamp":"00:00:19.3000000","Position":{"x":212.831116,"y":104.019463,"z":575.946},"Rotation":{"x":0.00126369973,"y":0.613044,"z":-5.87767754E-05,"w":0.790047765},"PitchYawRoll":{"x":0.00206883554,"y":1.3198154,"z":0.00145653472},"Speed":424.934,"Velocity":{"x":114.444153,"y":0.0,"z":28.9019318}},{"Timestamp":"00:00:19.4000000","Position":{"x":224.309845,"y":104.024,"z":578.847168},"Rotation":{"x":0.0009752593,"y":0.6164851,"z":0.000177319947,"w":0.787366},"PitchYawRoll":{"x":0.00131714356,"y":1.32854128,"z":0.00148169766},"Speed":427.063965,"Velocity":{"x":115.368263,"y":0.0,"z":27.62202}},{"Timestamp":"00:00:19.5000000","Position":{"x":235.8664,"y":104.876915,"z":581.6504},"Rotation":{"x":-0.06396575,"y":0.6175531,"z":0.07579228,"w":0.780251265},"PitchYawRoll":{"x":-0.1948094,"y":1.34288681,"z":0.03927965},"Speed":425.7847,"Velocity":{"x":114.086243,"y":17.05832,"z":26.1145535}},{"Timestamp":"00:00:19.6000000","Position":{"x":247.008972,"y":107.906189,"z":584.331665},"Rotation":{"x":-0.109383039,"y":0.613083065,"z":0.138033092,"w":0.77013725},"PitchYawRoll":{"x":-0.3456162,"y":1.3584007,"z":0.0785678849},"Speed":423.23764,"Velocity":{"x":108.786407,"y":36.24156,"z":25.9583378}},{"Timestamp":"00:00:19.7000000","Position":{"x":257.391418,"y":112.780586,"z":586.956238},"Rotation":{"x":-0.155596167,"y":0.6035704,"z":0.199969813,"w":0.75597924},"PitchYawRoll":{"x":-0.5004305,"y":1.37688589,"z":0.114771381},"Speed":419.4456,"Velocity":{"x":101.315109,"y":51.46488,"z":25.72576}},{"Timestamp":"00:00:19.8000000","Position":{"x":267.429535,"y":117.955826,"z":589.557434},"Rotation":{"x":-0.15569745,"y":0.6037238,"z":0.20793359,"w":0.7536839},"PitchYawRoll":{"x":-0.511664748,"y":1.38367462,"z":0.125767171},"Speed":414.028076,"Velocity":{"x":101.23246,"y":48.3110237,"z":25.39349}},{"Timestamp":"00:00:19.9000000","Position":{"x":277.437622,"y":122.865906,"z":592.1508},"Rotation":{"x":-0.155849442,"y":0.603834331,"z":0.215584248,"w":0.751410961},"PitchYawRoll":{"x":-0.5226644,"y":1.39034152,"z":0.136190861},"Speed":409.089417,"Velocity":{"x":100.024925,"y":47.7347565,"z":25.0905876}},{"Timestamp":"00:00:20","Position":{"x":287.4157,"y":127.511658,"z":594.7364},"Rotation":{"x":-0.156165242,"y":0.603861451,"z":0.2228772,"w":0.7491926},"PitchYawRoll":{"x":-0.5335238,"y":1.396725,"z":0.1458683},"Speed":404.209717,"Velocity":{"x":99.96818,"y":44.7063866,"z":24.7913017}},{"Timestamp":"00:00:20.1000000","Position":{"x":297.363556,"y":131.894135,"z":597.3165},"Rotation":{"x":-0.156694278,"y":0.6037574,"z":0.229418367,"w":0.7471888},"PitchYawRoll":{"x":-0.543725431,"y":1.40232146,"z":0.154237822},"Speed":399.388184,"Velocity":{"x":99.8381042,"y":41.71644,"z":24.4955826}},{"Timestamp":"00:00:20.2000000","Position":{"x":307.280762,"y":136.01387,"z":599.889},"Rotation":{"x":-0.157453984,"y":0.603589654,"z":0.235183612,"w":0.74537003},"PitchYawRoll":{"x":-0.5532388,"y":1.40721965,"z":0.16121994},"Speed":395.018982,"Velocity":{"x":99.44935,"y":38.6934052,"z":25.5493889}},{"Timestamp":"00:00:20.3000000","Position":{"x":317.168274,"y":139.871643,"z":602.453735},"Rotation":{"x":-0.158380449,"y":0.603350163,"z":0.2402875,"w":0.743737936},"PitchYawRoll":{"x":-0.5620996,"y":1.41145229,"z":0.1670804},"Speed":390.697571,"Velocity":{"x":99.27789,"y":35.82549,"z":25.2698841}},{"Timestamp":"00:00:20.4000000","Position":{"x":327.026184,"y":143.4682,"z":605.010864},"Rotation":{"x":-0.159426853,"y":0.6030963,"z":0.245046973,"w":0.7421657},"PitchYawRoll":{"x":-0.5706907,"y":1.41542757,"z":0.172282413},"Speed":386.423462,"Velocity":{"x":99.03821,"y":32.9940071,"z":24.9934387}},{"Timestamp":"00:00:20.5000000","Position":{"x":336.8546,"y":146.804367,"z":607.560364},"Rotation":{"x":-0.160458118,"y":0.602785349,"z":0.24966982,"w":0.740653753},"PitchYawRoll":{"x":-0.5790914,"y":1.41921926,"z":0.17732197},"Speed":382.5785,"Velocity":{"x":98.8307343,"y":30.23044,"z":24.744751}},{"Timestamp":"00:00:20.6000000","Position":{"x":346.653259,"y":149.88089,"z":610.1022},"Rotation":{"x":-0.161547452,"y":0.602460444,"z":0.25410825,"w":0.7391704},"PitchYawRoll":{"x":-0.5873489,"y":1.42288232,"z":0.18200995},"Speed":378.771759,"Velocity":{"x":98.55771,"y":27.5002861,"z":24.4985352}},{"Timestamp":"00:00:20.7000000","Position":{"x":356.4217,"y":152.698578,"z":612.636353},"Rotation":{"x":-0.162638113,"y":0.6021409,"z":0.258361459,"w":0.7377157},"PitchYawRoll":{"x":-0.5953723,"y":1.42645228,"z":0.186410218},"Speed":375.00293,"Velocity":{"x":98.22063,"y":24.8048134,"z":24.25477}},{"Timestamp":"00:00:20.8000000","Position":{"x":366.160828,"y":155.258209,"z":615.1629},"Rotation":{"x":-0.163778991,"y":0.6017785,"z":0.2625184,"w":0.7362901},"PitchYawRoll":{"x":-0.6033577,"y":1.42989349,"z":0.190614253},"Speed":371.643036,"Velocity":{"x":97.91886,"y":22.1673851,"z":24.0374565}},{"Timestamp":"00:00:20.9000000","Position":{"x":375.87085,"y":157.560547,"z":617.681946},"Rotation":{"x":-0.164922863,"y":0.6014278,"z":0.2664888,"w":0.734893739},"PitchYawRoll":{"x":-0.61110276,"y":1.43324,"z":0.194528043},"Speed":368.681732,"Velocity":{"x":97.3562,"y":19.5218735,"z":25.0759277}},{"Timestamp":"00:00:21","Position":{"x":385.5518,"y":159.606323,"z":620.1933},"Rotation":{"x":-0.166119844,"y":0.6010453,"z":0.27025798,"w":0.73355937},"PitchYawRoll":{"x":-0.6186484,"y":1.43636,"z":0.198102638},"Speed":365.744049,"Velocity":{"x":97.02992,"y":16.9715347,"z":24.8761215}},{"Timestamp":"00:00:21.1000000","Position":{"x":395.203735,"y":161.396347,"z":622.699463},"Rotation":{"x":-0.167362541,"y":0.6006049,"z":0.2736332,"w":0.732385457},"PitchYawRoll":{"x":-0.6256742,"y":1.438968,"z":0.201125681},"Speed":363.1928,"Velocity":{"x":96.74046,"y":14.464756,"z":24.7025986}},{"Timestamp":"00:00:21.2000000","Position":{"x":404.826782,"y":162.931366,"z":625.198242},"Rotation":{"x":-0.168615252,"y":0.6002015,"z":0.276789069,"w":0.731242},"PitchYawRoll":{"x":-0.632407665,"y":1.44147527,"z":0.203801215},"Speed":360.659332,"Velocity":{"x":96.39154,"y":11.9833326,"z":24.530283}},{"Timestamp":"00:00:21.3000000","Position":{"x":414.421,"y":164.212158,"z":627.6896},"Rotation":{"x":-0.169864535,"y":0.5997869,"z":0.2798447,"w":0.730129242},"PitchYawRoll":{"x":-0.6389984,"y":1.44388568,"z":0.206341684},"Speed":358.501831,"Velocity":{"x":96.08023,"y":9.538075,"z":24.3835411}},{"Timestamp":"00:00:21.4000000","Position":{"x":423.9865,"y":165.239487,"z":630.1735},"Rotation":{"x":-0.171107069,"y":0.599349439,"z":0.282829553,"w":0.729047358},"PitchYawRoll":{"x":-0.6454826,"y":1.44619966,"z":0.208800316},"Speed":356.357269,"Velocity":{"x":95.71077,"y":7.115845,"z":24.2376785}},{"Timestamp":"00:00:21.5000000","Position":{"x":433.523346,"y":166.01413,"z":632.649963},"Rotation":{"x":-0.1723506,"y":0.5989167,"z":0.285683542,"w":0.7279965},"PitchYawRoll":{"x":-0.6517828,"y":1.44841444,"z":0.211069658},"Speed":354.579926,"Velocity":{"x":95.3794,"y":4.722645,"z":24.1167927}},{"Timestamp":"00:00:21.6000000","Position":{"x":443.031616,"y":166.5368,"z":635.119},"Rotation":{"x":-0.173588008,"y":0.598463953,"z":0.288466066,"w":0.726976931},"PitchYawRoll":{"x":-0.657973647,"y":1.45053244,"z":0.213256776},"Speed":353.164459,"Velocity":{"x":95.08593,"y":2.35261583,"z":24.02052}},{"Timestamp":"00:00:21.7000000","Position":{"x":452.511,"y":166.808289,"z":637.5806},"Rotation":{"x":-0.174880743,"y":0.597988844,"z":0.2911469,"w":0.7259887},"PitchYawRoll":{"x":-0.6641001,"y":1.45251191,"z":0.215243429},"Speed":351.7546,"Velocity":{"x":94.73532,"y":0.0,"z":23.9246273}},{"Timestamp":"00:00:21.8000000","Position":{"x":461.961182,"y":166.8293,"z":640.0349},"Rotation":{"x":-0.176123321,"y":0.597556353,"z":0.293740571,"w":0.7249989},"PitchYawRoll":{"x":-0.670036,"y":1.45452464,"z":0.217138246},"Speed":350.700928,"Velocity":{"x":94.4515457,"y":0.0,"z":23.8529625}},{"Timestamp":"00:00:21.9000000","Position":{"x":471.383118,"y":166.600647,"z":642.4818},"Rotation":{"x":-0.177360684,"y":0.597107232,"z":0.296262026,"w":0.7240407},"PitchYawRoll":{"x":-0.6758592,"y":1.4564395,"z":0.218950018},"Speed":350.000244,"Velocity":{"x":94.23399,"y":-2.331537,"z":23.8053036}},{"Timestamp":"00:00:22","Position":{"x":480.7252,"y":165.9296,"z":644.9312},"Rotation":{"x":-0.179971069,"y":0.600617349,"z":0.2709203,"w":0.730391264},"PitchYawRoll":{"x":-0.641076565,"y":1.43649459,"z":0.180547461},"Speed":347.906525,"Velocity":{"x":93.4410553,"y":-6.947098,"z":23.662899}},{"Timestamp":"00:00:22.1000000","Position":{"x":489.969055,"y":164.879471,"z":647.4195},"Rotation":{"x":-0.182883233,"y":0.608637869,"z":0.201338515,"w":0.74537003},"PitchYawRoll":{"x":-0.5460066,"y":1.39125025,"z":0.07760193},"Speed":347.906525,"Velocity":{"x":92.98316,"y":-11.5596046,"z":23.662899}},{"Timestamp":"00:00:22.2000000","Position":{"x":499.185944,"y":163.592514,"z":649.895447},"Rotation":{"x":-0.183271885,"y":0.613987446,"z":0.1349476,"w":0.755790949},"PitchYawRoll":{"x":-0.458764881,"y":1.35956538,"z":-0.0210704859},"Speed":348.254578,"Velocity":{"x":92.7615051,"y":-13.8698158,"z":23.686573}},{"Timestamp":"00:00:22.3000000","Position":{"x":508.376831,"y":162.067932,"z":652.358765},"Rotation":{"x":-0.181470513,"y":0.6170071,"z":0.07179329,"w":0.762375534},"PitchYawRoll":{"x":-0.376543522,"y":1.33891737,"z":-0.114721768},"Speed":348.603027,"Velocity":{"x":92.4825,"y":-16.1761436,"z":23.7102718}},{"Timestamp":"00:00:22.4000000","Position":{"x":517.542664,"y":160.305115,"z":654.8098},"Rotation":{"x":-0.177769974,"y":0.6179719,"z":0.0118693383,"w":0.7657465},"PitchYawRoll":{"x":-0.297294,"y":1.32752144,"z":-0.202925727},"Speed":348.9518,"Velocity":{"x":92.1462,"y":-18.4771652,"z":23.7339954}},{"Timestamp":"00:00:22.5000000","Position":{"x":526.6838,"y":158.303329,"z":657.2488},"Rotation":{"x":-0.172435239,"y":0.617206752,"z":-0.0448332839,"w":0.7663628},"PitchYawRoll":{"x":-0.219522789,"y":1.32434666,"z":-0.285433561},"Speed":350.000244,"Velocity":{"x":91.9363861,"y":-20.8130417,"z":23.8053036}},{"Timestamp":"00:00:22.6000000","Position":{"x":535.802063,"y":156.061417,"z":659.6746},"Rotation":{"x":-0.165187091,"y":0.6150907,"z":-0.0965988338,"w":0.764882565},"PitchYawRoll":{"x":-0.1434496,"y":1.32850468,"z":-0.358621359},"Speed":351.051819,"Velocity":{"x":91.66805,"y":-23.150013,"z":23.8768272}},{"Timestamp":"00:00:22.7000000","Position":{"x":544.9007,"y":153.575485,"z":662.084961},"Rotation":{"x":-0.155049771,"y":0.612862468,"z":-0.137671977,"w":0.7624996},"PitchYawRoll":{"x":-0.07393708,"y":1.338614,"z":-0.41151467},"Speed":352.106537,"Velocity":{"x":91.61932,"y":-25.56429,"z":22.773859}},{"Timestamp":"00:00:22.8000000","Position":{"x":553.9774,"y":150.8462,"z":664.483032},"Rotation":{"x":-0.14360103,"y":0.610511661,"z":-0.17191799,"w":0.75966996},"PitchYawRoll":{"x":-0.009184359,"y":1.35181928,"z":-0.4517516},"Speed":353.8715,"Velocity":{"x":91.41492,"y":-27.9620819,"z":22.8880138}},{"Timestamp":"00:00:22.9000000","Position":{"x":563.0293,"y":147.876343,"z":666.872559},"Rotation":{"x":-0.131728545,"y":0.607681632,"z":-0.204263642,"w":0.7560734},"PitchYawRoll":{"x":0.0555777252,"y":1.36787069,"z":-0.4881295},"Speed":355.289825,"Velocity":{"x":91.05883,"y":-30.3357239,"z":22.97975}},{"Timestamp":"00:00:23","Position":{"x":572.0562,"y":144.6667,"z":669.2529},"Rotation":{"x":-0.119603053,"y":0.604445755,"z":-0.235046089,"w":0.7517272},"PitchYawRoll":{"x":0.120596588,"y":1.38664126,"z":-0.521254241},"Speed":357.427948,"Velocity":{"x":90.8239441,"y":-32.7747879,"z":23.118042}},{"Timestamp":"00:00:23.1000000","Position":{"x":581.0582,"y":141.217621,"z":671.625732},"Rotation":{"x":-0.107253961,"y":0.600816548,"z":-0.264370054,"w":0.7467426},"PitchYawRoll":{"x":0.1859441,"y":1.40778315,"z":-0.551203251},"Speed":359.219574,"Velocity":{"x":90.43655,"y":-35.1867371,"z":23.2339211}},{"Timestamp":"00:00:23.2000000","Position":{"x":590.0356,"y":137.5299,"z":673.9893},"Rotation":{"x":-0.0947110355,"y":0.596815348,"z":-0.2922577,"w":0.7412332},"PitchYawRoll":{"x":0.2515046,"y":1.43089879,"z":-0.577955},"Speed":361.74292,"Velocity":{"x":90.16752,"y":-37.6756744,"z":23.39713}},{"Timestamp":"00:00:23.3000000","Position":{"x":598.988,"y":133.6037,"z":676.3454},"Rotation":{"x":-0.08205434,"y":0.5924215,"z":-0.318769366,"w":0.7353162},"PitchYawRoll":{"x":0.317052841,"y":1.45549214,"z":-0.6016628},"Speed":363.919922,"Velocity":{"x":90.0038,"y":-40.2502556,"z":22.3202152}},{"Timestamp":"00:00:23.4000000","Position":{"x":607.9154,"y":129.439682,"z":678.6931},"Rotation":{"x":-0.0693123862,"y":0.5876749,"z":-0.343982428,"w":0.729047358},"PitchYawRoll":{"x":0.382492751,"y":1.48128271,"z":-0.6224474},"Speed":366.4763,"Velocity":{"x":89.60575,"y":-42.7624245,"z":22.477005}},{"Timestamp":"00:00:23.5000000","Position":{"x":616.817566,"y":125.038567,"z":681.0327},"Rotation":{"x":-0.0565179,"y":0.582693934,"z":-0.367946982,"w":0.722418547},"PitchYawRoll":{"x":0.447719961,"y":1.50819528,"z":-0.6403657},"Speed":369.419861,"Velocity":{"x":89.231636,"y":-45.32686,"z":22.6575432}},{"Timestamp":"00:00:23.6000000","Position":{"x":625.695068,"y":120.400871,"z":683.3653},"Rotation":{"x":-0.0436853878,"y":0.5774921,"z":-0.390731454,"w":0.7154882},"PitchYawRoll":{"x":0.512585,"y":1.53589225,"z":-0.655535},"Speed":372.3871,"Velocity":{"x":89.94835,"y":-45.6909256,"z":22.83953}},{"Timestamp":"00:00:23.7000000","Position":{"x":634.547852,"y":115.527222,"z":685.6908},"Rotation":{"x":-0.0308793783,"y":0.572020352,"z":-0.412404478,"w":0.7083514},"PitchYawRoll":{"x":0.576803446,"y":1.56387782,"z":-0.668209851},"Speed":375.3781,"Velocity":{"x":89.50386,"y":-48.28652,"z":23.0229778}},{"Timestamp":"00:00:23.8000000","Position":{"x":643.5339,"y":110.697891,"z":688.0733},"Rotation":{"x":0.0142261731,"y":0.5761153,"z":-0.363090962,"w":0.732156932},"PitchYawRoll":{"x":0.538059235,"y":1.486085,"z":-0.541342854},"Speed":378.3932,"Velocity":{"x":90.8593445,"y":-46.1536827,"z":25.736454}},{"Timestamp":"00:00:23.9000000","Position":{"x":652.558838,"y":105.8546,"z":690.774},"Rotation":{"x":0.102668859,"y":0.5868325,"z":-0.2310599,"w":0.7692191},"PitchYawRoll":{"x":0.457267135,"y":1.35884523,"z":-0.237190291},"Speed":382.5785,"Velocity":{"x":90.94045,"y":-46.19488,"z":29.8255558}},{"Timestamp":"00:00:24","Position":{"x":661.794739,"y":101.2308,"z":693.524841},"Rotation":{"x":0.180750772,"y":0.5945022,"z":-0.135413811,"w":0.771724939},"PitchYawRoll":{"x":0.455593169,"y":1.31143332,"z":0.00590907224},"Speed":387.584473,"Velocity":{"x":94.49423,"y":-45.0953522,"z":25.068531}},{"Timestamp":"00:00:24.1000000","Position":{"x":671.298462,"y":96.49191,"z":695.7826},"Rotation":{"x":0.192731276,"y":0.6183238,"z":-0.125575751,"w":0.751505852},"PitchYawRoll":{"x":0.4617535,"y":1.36528885,"z":0.0496192053},"Speed":394.229736,"Velocity":{"x":97.35286,"y":-46.459568,"z":18.8676834}},{"Timestamp":"00:00:24.2000000","Position":{"x":681.0286,"y":91.53163,"z":697.4949},"Rotation":{"x":0.165689752,"y":0.6411981,"z":-0.1587914,"w":0.732254863},"PitchYawRoll":{"x":0.4627132,"y":1.44312358,"z":-0.02007298},"Speed":401.390137,"Velocity":{"x":98.64793,"y":-50.1100349,"z":13.7553768}},{"Timestamp":"00:00:24.3000000","Position":{"x":691.0134,"y":86.52018,"z":698.8273},"Rotation":{"x":0.146078482,"y":0.652691543,"z":-0.178247184,"w":0.721722066},"PitchYawRoll":{"x":0.460642785,"y":1.48606372,"z":-0.06665081},"Speed":408.272064,"Velocity":{"x":101.850517,"y":-48.60598,"z":11.20326}},{"Timestamp":"00:00:24.4000000","Position":{"x":701.191162,"y":81.4613,"z":700.1127},"Rotation":{"x":0.142941311,"y":0.646816552,"z":-0.177898437,"w":0.7277007},"PitchYawRoll":{"x":0.454904974,"y":1.47039187,"z":-0.07406773},"Speed":414.856964,"Velocity":{"x":103.358246,"y":-49.3255119,"z":12.8013945}},{"Timestamp":"00:00:24.5000000","Position":{"x":711.495544,"y":76.3162155,"z":701.662659},"Rotation":{"x":0.140574887,"y":0.6366878,"z":-0.178695917,"w":0.7368413},"PitchYawRoll":{"x":0.4514426,"y":1.44462073,"z":-0.08443673},"Speed":421.548065,"Velocity":{"x":104.702774,"y":-49.9671555,"z":15.8822775}},{"Timestamp":"00:00:24.6000000","Position":{"x":721.9199,"y":71.08702,"z":703.489136},"Rotation":{"x":0.140503436,"y":0.631188035,"z":-0.180490419,"w":0.7411367},"PitchYawRoll":{"x":0.453255951,"y":1.4317342,"z":-0.09029061},"Speed":428.347076,"Velocity":{"x":105.998688,"y":-50.5856056,"z":19.0493374}},{"Timestamp":"00:00:24.7000000","Position":{"x":732.4904,"y":65.78784,"z":705.4776},"Rotation":{"x":0.143829316,"y":0.6276604,"z":-0.178404257,"w":0.743994236},"PitchYawRoll":{"x":0.455106974,"y":1.42127311,"z":-0.08501391},"Speed":434.82074,"Velocity":{"x":107.600655,"y":-51.35011,"z":19.3372326}},{"Timestamp":"00:00:24.8000000","Position":{"x":743.2231,"y":60.4262924,"z":707.5648},"Rotation":{"x":0.146891832,"y":0.625578642,"z":-0.174225435,"w":0.7461365},"PitchYawRoll":{"x":0.453885764,"y":1.413093,"z":-0.07628108},"Speed":441.833832,"Velocity":{"x":109.108421,"y":-52.06966,"z":21.145998}},{"Timestamp":"00:00:24.9000000","Position":{"x":754.125366,"y":54.9876823,"z":709.6719},"Rotation":{"x":0.1492295,"y":0.628222,"z":-0.170060739,"w":0.7444105},"PitchYawRoll":{"x":0.4520286,"y":1.41702724,"z":-0.06573884},"Speed":448.5113,"Velocity":{"x":110.988518,"y":-52.9668961,"z":19.9460754}},{"Timestamp":"00:00:25","Position":{"x":765.202637,"y":49.45243,"z":711.709839},"Rotation":{"x":0.151074111,"y":0.631141365,"z":-0.16769819,"w":0.742101431},"PitchYawRoll":{"x":0.451868534,"y":1.42293262,"z":-0.0582328},"Speed":454.8346,"Velocity":{"x":112.770454,"y":-53.8172874,"z":18.6832638}},{"Timestamp":"00:00:25.1000000","Position":{"x":776.4517,"y":43.8210678,"z":713.69574},"Rotation":{"x":0.150425583,"y":0.6329874,"z":-0.169421569,"w":0.740267158},"PitchYawRoll":{"x":0.453365266,"y":1.42881477,"z":-0.0604362376},"Speed":461.708557,"Velocity":{"x":114.47477,"y":-54.63063,"z":18.9656239}},{"Timestamp":"00:00:25.2000000","Position":{"x":787.871643,"y":38.1048965,"z":715.6694},"Rotation":{"x":0.148059174,"y":0.634375155,"z":-0.173037708,"w":0.7387182},"PitchYawRoll":{"x":0.454819947,"y":1.43481338,"z":-0.06785414},"Speed":468.2179,"Velocity":{"x":116.088676,"y":-55.4008369,"z":19.23301}},{"Timestamp":"00:00:25.3000000","Position":{"x":799.4626,"y":32.3104324,"z":717.6454},"Rotation":{"x":0.14669545,"y":0.6351315,"z":-0.174590766,"w":0.7379746},"PitchYawRoll":{"x":0.454942852,"y":1.43781471,"z":-0.07140597},"Speed":475.294128,"Velocity":{"x":117.84314,"y":-56.2381172,"z":19.52368}},{"Timestamp":"00:00:25.4000000","Position":{"x":811.522339,"y":27.05904,"z":719.6331},"Rotation":{"x":0.0919842646,"y":0.6449918,"z":-0.110191293,"w":0.750588},"PitchYawRoll":{"x":0.284352869,"y":1.42645144,"z":-0.0467753857},"Speed":478.15448,"Velocity":{"x":124.626511,"y":-41.5186,"z":19.6411743}},{"Timestamp":"00:00:25.5000000","Position":{"x":824.444458,"y":24.256525,"z":721.660034},"Rotation":{"x":0.0293248668,"y":0.649633646,"z":-0.03601164,"w":0.7588276},"PitchYawRoll":{"x":0.09143364,"y":1.41680884,"z":-0.016553171},"Speed":479.591064,"Velocity":{"x":131.110626,"y":-13.0156126,"z":19.7001858}},{"Timestamp":"00:00:25.6000000","Position":{"x":837.669861,"y":24.0513248,"z":723.7253},"Rotation":{"x":-0.009057986,"y":0.649272859,"z":0.0149129843,"w":0.760355353},"PitchYawRoll":{"x":-0.0331478119,"y":1.41369689,"z":0.010916343},"Speed":480.5512,"Velocity":{"x":132.01886,"y":0.0,"z":19.7396259}},{"Timestamp":"00:00:25.7000000","Position":{"x":850.8703,"y":24.0178967,"z":725.8257},"Rotation":{"x":0.00469783135,"y":0.6489776,"z":0.00171114958,"w":0.7607911},"PitchYawRoll":{"x":0.004927348,"y":1.41247952,"z":0.008701339},"Speed":482.477264,"Velocity":{"x":132.548,"y":0.0,"z":19.8187428}},{"Timestamp":"00:00:25.8000000","Position":{"x":864.137,"y":24.0330334,"z":727.9537},"Rotation":{"x":0.000466544618,"y":0.6488117,"z":-0.007122868,"w":0.7609155},"PitchYawRoll":{"x":0.009953489,"y":1.412138,"z":-0.0102345813},"Speed":484.411041,"Velocity":{"x":133.079254,"y":0.0,"z":19.8981762}},{"Timestamp":"00:00:25.9000000","Position":{"x":877.4685,"y":24.031435,"z":730.0888},"Rotation":{"x":-0.00438518031,"y":0.648751736,"z":-0.00385654531,"w":0.760977745},"PitchYawRoll":{"x":-0.0016702807,"y":1.41190541,"z":-0.0115595348},"Speed":486.839172,"Velocity":{"x":133.746323,"y":0.0,"z":19.9979172}},{"Timestamp":"00:00:26","Position":{"x":890.8528,"y":24.020956,"z":732.2275},"Rotation":{"x":-0.00301661761,"y":0.648727357,"z":0.00304775,"w":0.761008859},"PitchYawRoll":{"x":-0.008545769,"y":1.41184068,"z":0.000724804937},"Speed":488.7904,"Velocity":{"x":134.282364,"y":0.0,"z":20.0780678}},{"Timestamp":"00:00:26.1000000","Position":{"x":904.2824,"y":24.02188,"z":734.3779},"Rotation":{"x":0.00139946374,"y":0.648731947,"z":0.0032343457,"w":0.761008859},"PitchYawRoll":{"x":-0.00206648652,"y":1.41185153,"z":0.006738536},"Speed":490.259,"Velocity":{"x":134.685822,"y":0.0,"z":20.1383934}},{"Timestamp":"00:00:26.2000000","Position":{"x":917.766235,"y":24.0224457,"z":736.5358},"Rotation":{"x":0.00252047717,"y":0.649101138,"z":0.0004978734,"w":0.7606978},"PitchYawRoll":{"x":0.00318833371,"y":1.41280365,"z":0.0040295627},"Speed":492.223969,"Velocity":{"x":135.225647,"y":0.0,"z":20.2191067}},{"Timestamp":"00:00:26.3000000","Position":{"x":931.3298,"y":24.0218754,"z":738.5542},"Rotation":{"x":0.00394670758,"y":0.658622444,"z":0.00375732873,"w":0.752453864},"PitchYawRoll":{"x":0.0009901671,"y":1.43799376,"z":0.0108534265},"Speed":494.196777,"Velocity":{"x":136.2282,"y":0.0,"z":16.9358}},{"Timestamp":"00:00:26.4000000","Position":{"x":944.9998,"y":24.034544,"z":740.1707},"Rotation":{"x":0.00988367852,"y":0.671530366,"z":0.01194581,"w":0.7408148},"PitchYawRoll":{"x":-0.00140067027,"y":1.472784,"z":0.0309786014},"Speed":496.177551,"Velocity":{"x":137.152939,"y":0.0,"z":13.6154461}},{"Timestamp":"00:00:26.5000000","Position":{"x":958.7627,"y":24.03978,"z":741.4087},"Rotation":{"x":0.012604774,"y":0.6793461,"z":0.014855355,"w":0.73355937},"PitchYawRoll":{"x":-0.00169243757,"y":1.4941268,"z":0.03893041},"Speed":498.16626,"Velocity":{"x":137.998642,"y":0.0,"z":10.2598381}},{"Timestamp":"00:00:26.6000000","Position":{"x":972.613464,"y":24.442585,"z":742.3872},"Rotation":{"x":-0.0309743583,"y":0.6861748,"z":0.0276081767,"w":0.7262524},"PitchYawRoll":{"x":-0.08297389,"y":1.51396179,"z":-0.00240664324},"Speed":499.163574,"Velocity":{"x":138.317444,"y":6.84869242,"z":6.85708237}},{"Timestamp":"00:00:26.7000000","Position":{"x":986.4236,"y":25.5762863,"z":743.119446},"Rotation":{"x":-0.0244161282,"y":0.6907889,"z":0.03156736,"w":0.7219543},"PitchYawRoll":{"x":-0.0789549649,"y":1.52715111,"z":0.0118478788},"Speed":499.163574,"Velocity":{"x":138.105728,"y":10.2677994,"z":6.85708237}},{"Timestamp":"00:00:26.8000000","Position":{"x":1000.19873,"y":26.56224,"z":743.8124},"Rotation":{"x":-0.0132912789,"y":0.6947966,"z":0.0282320566,"w":0.718529},"PitchYawRoll":{"x":-0.05837882,"y":1.53786111,"z":0.02210343},"Speed":496.673981,"Velocity":{"x":137.627579,"y":6.81453371,"z":6.822882}}]}